Workbook
Name \A: #REF!
Name \A: #REF!
Name \A: #REF!
Name \A: #REF!
Name \A: #REF!
Name \A: #REF!
Name \A: #REF!
Name \B: #REF!
Name \B: #REF!
Name \B: #REF!
Name \B: #REF!
Name \B: #REF!
Name \B: #REF!
Name \B: #REF!
Name \C: #REF!
Name \C: #REF!
Name \C: #REF!
Name \C: #REF!
Name \C: #REF!
Name \C: #REF!
Name \C: #REF!
Name \D: #REF!
Name \E: #REF!
Name \F: #REF!
Name \i: #REF!
Name \M: #REF!
Name \N: #REF!
Name \O: #REF!
Name \P: #REF!
Name \Q: #REF!
Name \S: #REF!
Name \T: #REF!
Name \U: #REF!
Name \w: #REF!
Name \X: #REF!
Name \Y: #REF!
Name \Z: #REF!
Name ____7HILLS: #REF!
Name ____Ins2: #REF!
Name ____Ins3: #REF!
Name ____NML9798: #REF!
Name ____NML98: #REF!
Name ____PEG1: #REF!
Name ____RR1: #REF!
Name ____SKY98: #REF!
Name ___1Module2_.PRINT_BCCAM: Insurance_Bonds!___1Module2_.PRINT_BCCAM
Name ___1Module2_.PRINT_BCCAM: Normalize!___1Module2_.PRINT_BCCAM
Name ___1Module2_.PRINT_BCCAM: #N/A
Name ___7HILLS: #REF!
Name ___Ins2: #REF!
Name ___Ins3: #REF!
Name ___MT1: #REF!
Name ___MT2: #REF!
Name ___MT3: #REF!
Name ___NML9798: #REF!
Name ___NML98: #REF!
Name ___PEG1: #REF!
Name ___RR1: #REF!
Name ___SKY98: #REF!
Name __1Module2_.PRINT_BCCAM: #N/A

Sheet Menu Pricing
A2: Lightweight | D2: QT | E2: ='Level 3'!$G$32 -> 261305.65
A3: Product | B3: Concrete Thickness | C3: Sound Mat | D3: Price / SF | E3: Budget | F3: Delta
A4: Basic "$0" | B4: 3/4" | C4: No | D4: 1.4 | E4: =D4*$E$2 -> 365827.91 | F4: =E4-$E$4 -> 0
A5: Basic + (+$1156,783) | B5: 3/4" | C5: 1/8 | D5: 2 | E5: =D5*$E$2 -> 522611.3 | F5: =E5-$E$4 -> 156783.39
A6: Standard (+$313,567) | B6: 1" | C6: 1/4 | D6: 2.6 | E6: =D6*$E$2 -> 679394.69 | F6: =E6-$E$4 -> 313566.78
A9: Unit Cabinets | D9: QT | E9: =SUM(L10:L13,P10:P13,T10:T11) -> 8559 | G9: 390 | I9: UNIT | J9: # UNITS | K9: QTY/UNIT | L9: TOTAL | M9: UNIT | N9: # UNITS | O9: QTY/UNIT | P9: TOTAL | Q9: UNIT | R9: # UNITS | S9: QTY/UNIT | T9: TOTAL
A10: Product | D10: Price / Box | E10: Budget | G10: Cost / Unit | I10: A1A | J10: 9 | K10: =14+2 -> 16 | L10: =J10*K10 -> 144 | M10: A2B | N10: 8 | O10: =10+3+3 -> 16 | P10: =N10*O10 -> 128 | Q10: A3A | R10: 3 | S10: =18+1+3 -> 22 | T10: =R10*S10 -> 66
A11: Thermafoil White "$0" | D11: 137.8 | E11: =D11*E9 -> 1179430.2 | F11: =E11-E11 -> 0 | G11: =E11/G9 -> 3024.18 | I11: B1A | J11: 106 | K11: =20+2 -> 22 | L11: =J11*K11 -> 2332 | M11: B2A | N11: 6 | O11: =20+2 -> 22 | P11: =N11*O11 -> 132 | Q11: B3A | R11: 45 | S11: =20+3+1 -> 24 | T11: =R11*S11 -> 1080
A12: Morning Dew (+$188,298) | D12: 159.8 | E12: =D12*E9 -> 1367728.2 | F12: =E12-E11 -> 188298 | G12: 3507 | I12: B1AE | J12: 3 | K12: =20+2 -> 22 | L12: =J12*K12 -> 66 | M12: B2B | N12: 107 | O12: =21+2+3 -> 26 | P12: =N12*O12 -> 2782
I13: B1B | J13: 60 | K13: =13+1 -> 14 | L13: =J13*K13 -> 840 | M13: B2C | N13: 43 | O13: =21+2 -> 23 | P13: =N13*O13 -> 989
A15: Common Area Cabinets | D15: QT | E15: =SUM(M16:M19) -> 98 | G15: 390 | J15: Level 1 | K15: Level 2 | L15: Level 3 | M15: TOTAL
A16: Product | D16: Price / Box | E16: Budget | G16: Cost / Unit | I16: Bldg 1 | J16: =55+31 -> 86 | K16: =9 -> 9 | L16: =1 -> 1 | M16: =SUM(J16:L16) -> 96
A17: Thermafoil White "$0" | D17: 137.8 | E17: =D17*E15 -> 13504.4 | F17: =E17-E17 -> 0 | G17: =E17/G15 -> 34.626667 | I17: Bldg 2 | J17: 0 | K17: 0 | L17: 0 | M17: =SUM(J17:L17) -> 0
A18: Morning Dew (+$2,156) | D18: 159.8 | E18: =D18*E15 -> 15660.4 | F18: =E18-E17 -> 2156 | G18: =E18/G15 -> 40.154872 | I18: Bldg 3 | J18: =2 -> 2 | K18: 0 | L18: 0 | M18: =SUM(J18:L18) -> 2
A19: Torrey Pines | E19: =85600*1.5 -> 128400 | F19: =E19-E17 -> 114895.6 | G19: =E19/G15 -> 329.23077 | I19: Bldg 4 | J19: 0 | K19: 0 | L19: 0 | M19: =SUM(J19:L19) -> 0
A21: Unit Counter Tops | D21: QT | E21: =SUM(L22:L25,P22:P25,T22:T23) -> 32355.9 | G21: 390 | I21: UNIT | J21: # UNITS | K21: SF/UNIT | L21: TOTAL | M21: UNIT | N21: # UNITS | O21: SF/UNIT | P21: TOTAL | Q21: UNIT | R21: # UNITS | S21: SF/UNIT | T21: TOTAL
A22: Product | C22: Sound Mat | D22: Price / SF | E22: Budget | F22: Delta | G22: Cost / Unit | I22: A1A | J22: 9 | K22: =38.87+23.94 -> 62.81 | L22: =J22*K22 -> 565.29 | M22: A2B | N22: 8 | O22: =39.2+19.93 -> 59.13 | P22: =N22*O22 -> 473.04 | Q22: A3A | R22: 3 | S22: =77.84+24.25 -> 102.09 | T22: =R22*S22 -> 306.27
A23: Arctic White "$0" | B23: 3/4" | C23: No | D23: 24.855498 | E23: =D23*E21 -> 804222.02 | F23: =E23-E23 -> 0 | G23: =E23/G21 -> 2062.1077 | I23: B1A | J23: 106 | K23: =52.72+23.95 -> 76.67 | L23: =J23*K23 -> 8127.02 | M23: B2A | N23: 6 | O23: =64.8+28.49 -> 93.29 | P23: =N23*O23 -> 559.74 | Q23: B3A | R23: 45 | S23: =63.06+20.79 -> 83.85 | T23: =R23*S23 -> 3773.25
A24: Carrera Trigato (+$94,156) | B24: 1" | C24: 1/4 | D24: 28.4 | E24: =D24*E21 -> 918907.56 | F24: =E24-E23 -> 114685.54 | G24: =E24/G21 -> 2356.1732 | I24: B1AE | J24: 3 | K24: =54.22+24.52 -> 78.74 | L24: =J24*K24 -> 236.22 | M24: B2B | N24: 107 | O24: =56.82+28.93 -> 85.75 | P24: =N24*O24 -> 9175.25
I25: B1B | J25: 60 | K25: =64.49+17.65 -> 82.14 | L25: =J25*K25 -> 4928.4 | M25: B2C | N25: 43 | O25: =67.2+30.74 -> 97.94 | P25: =N25*O25 -> 4211.42
A27: Common Area Counter Tops | D27: QT | E27: =SUM(M28:M31) -> 645.31 | G27: 390 | J27: Level 1 | K27: Level 2 | L27: Level 3 | M27: TOTAL
A28: Product | C28: Sound Mat | D28: Price / SF | E28: Budget | F28: Delta | G28: Cost / Unit | I28: Bldg 1 | J28: =510.59+50.75 -> 561.34 | K28: =39.69+7.86 -> 47.55 | L28: =10.04+2.2 -> 12.24 | M28: =SUM(J28:L28) -> 621.13
A29: Arctic White "$0" | B29: 3/4" | C29: No | D29: 24.86 | E29: =D29*E27 -> 16042.407 | F29: =E29-E29 -> 0 | G29: =E29/G27 -> 41.134376 | I29: Bldg 2 | J29: 0 | K29: 0 | L29: 0 | M29: =SUM(J29:L29) -> 0
A30: Carrera Trigato (+$1,878) | B30: 1" | C30: 1/4 | D30: 28.4 | E30: =D30*E27 -> 18326.804 | F30: =E30-E29 -> 2284.3974 | G30: =E30/G27 -> 46.991805 | I30: Bldg 3 | J30: =19.63+4.55 -> 24.18 | K30: 0 | L30: 0 | M30: =SUM(J30:L30) -> 24.18
A31: Torrey Pines | E31: =E19*0.304579439 -> 39108 | F31: =E31-E29 -> 23065.593 | G31: =E31/G27 -> 100.27692 | I31: Bldg 4 | J31: 0 | K31: 0 | L31: 0 | M31: =SUM(J31:L31) -> 0
A33: Unit Flooring | D33: QT | E33: =(SUM(L34:L37,P34:P37,T34:T35))/9 -> 29439.358 | G33: 390 | I33: UNIT | J33: # UNITS | K33: SF/UNIT | L33: TOTAL | M33: UNIT | N33: # UNITS | O33: SF/UNIT | P33: TOTAL | Q33: UNIT | R33: # UNITS | S33: SF/UNIT | T33: TOTAL | V33: ADDITIONAL GROSS SF PER PLANS
A34: Product | B34: Material Thickness | C34: Sound Mat | D34: Price / SY | E34: Budget | F34: Delta | G34: Cost / Unit | I34: A1A | J34: 9 | K34: 551.27 | L34: =J34*K34 -> 4961.43 | M34: A2B | N34: 8 | O34: 738.02 | P34: =N34*O34 -> 5904.16 | Q34: A3A | R34: 3 | S34: 986.11 | T34: =R34*S34 -> 2958.33 | V34: =(676-605)*J34 -> 639 | W34: =(904-806)*N34 -> 784 | X34: =(1216-1097)*R34 -> 357
A35: Sheet Vinyl "$0" | D35: =1.81*9 -> 16.29 | E35: =D35*E33 -> 479567.14 | F35: =E35-E35 -> 0 | G35: =E35/G33 -> 1229.6593 | I35: B1A | J35: 106 | K35: 535.09 | L35: =J35*K35 -> 56719.54 | M35: B2A | N35: 6 | O35: 743.09 | P35: =N35*O35 -> 4458.54 | Q35: B3A | R35: 45 | S35: 1008.6 | T35: =R35*S35 -> 45387 | V35: =(676-605)*J35 -> 7526 | W35: =(901-812)*N35 -> 534 | X35: =(1216-1103)*R35 -> 5085
A36: Vinyl Plank (+$98,033) | D36: =2.18*9 -> 19.62 | E36: =D36*E33 -> 577600.2 | F36: =E36-E35 -> 98033.061 | G36: =E36/G33 -> 1481.0262 | I36: B1AE | J36: 3 | K36: 552.32 | L36: =J36*K36 -> 1656.96 | M36: B2B | N36: 107 | O36: 721.73 | P36: =N36*O36 -> 77225.11 | V36: =(696-624)*J36 -> 216 | W36: =(904-806)*N36 -> 10486
I37: B1B | J37: 60 | K37: 532.53 | L37: =J37*K37 -> 31951.8 | M37: B2C | N37: 43 | O37: 784.45 | P37: =N37*O37 -> 33731.35 | V37: =(686-604)*J37 -> 4920 | W37: =(957-858)*N37 -> 4257
A39: Common Area Flooring | D39: QT | E39: =SUM(M40:M43) -> 67747.26 | G39: 390 | J39: Level 1 | K39: Level 2 | L39: Level 3 | M39: TOTAL
A40: Product | B40: Material Thickness | C40: Sound Mat | D40: Price / SF | E40: Budget | F40: Delta | G40: Cost / Unit | I40: Bldg 1 | J40: =14378.51 -> 14378.51 | K40: =8572.95+873.14 -> 9446.09 | L40: 8550.2 | M40: =SUM(J40:L40) -> 32374.8
A41: Vinyl Plank "$0" | D41: 3.05 | E41: =D41*E39 -> 206629.14 | F41: =E41-E41 -> 0 | G41: =E41/G39 -> 529.81832 | I41: Bldg 2 | J41: =1753.1 -> 1753.1 | K41: 1403.89 | L41: 0 | M41: =SUM(J41:L41) -> 3156.99 | P41: SF | Q41: SY | R41: Takeoff SF/Gross SF on Plans
A42: Tile (+$730,315) | D42: 13.83 | E42: =D42*E39 -> 936944.61 | F42: =E42-E41 -> 730315.46 | G42: =E42/G39 -> 2402.4221 | I42: Bldg 3 | J42: =10377.46 -> 10377.46 | K42: =8755+1050.24 -> 9805.24 | L42: 8719.59 | M42: =SUM(J42:L42) -> 28902.29 | P42: ='Level 3'!B8-(SUM(L22:L25,P22:P25,T22:T23,M28:M31,L34:L37,P34:P37,T34:T35,M40:M43)+1152.99)-(SUM(V34:W37,X34,X35)) -> 20975.32 | Q42: =P42/9 -> 2330.5911 | R42: =SUM(L34:L37,P34:P37,T34:T35)/SUM(L34:L37,P34:P37,T34:T35,V34:W37,X34:X35) -> 0.88389309
I43: Bldg 4 | J43: =1756.85 -> 1756.85 | K43: =1407.15+149.18 -> 1556.33 | L43: 0 | M43: =SUM(J43:L43) -> 3313.18 | P43: =P42/'Level 3'!B8 -> 0.04962987
A44: Offsite Water | D44: QT
A45: Product | C45: Savings | D45: Price / SF
A46: Per Plan | D46: 1772233.6
A47: Value (No Larson Ln Line) | C47: 250000 | D47: =D46-C47 -> 1522233.6
I49: Design | J49: 22140 | O49: 11700
A50: Common Area Cabinets | I50: Permits | J50: 21640 | O50: 95375
A51: Product | C51: LS | I51: Residential | J51: 938891 | O51: 862025 | P51: =O51/'Level 3'!$B$8 -> 2.0396441 | Q51: =O51/'Level 3'!$E$8 -> 2210.3205
A52: Allowance | C52: 30000 | I52: Stand Pipes | J52: 227360 | K52: =J52+J51 -> 1166251 | L52: =K52/'Level 3'!$B$8 -> 2.7594757 | M52: =K52/'Level 3'!$E$8 -> 2990.3872
A53: Torrey | C53: 85600 | J53: =SUM(J49:J52) -> 1210031 | O53: =SUM(O49:O52) -> 969100 | P53: =O53/'Level 3'!$B$8 -> 2.2929951 | Q53: =O53/'Level 3'!$E$8 -> 2484.8718
I54: Pump | J54: 118500

Sheet Level 2 - Transmitted
A1: Project Details | D1: Unit Breakdown | H1: Breakdown Per Building | P1: List of Take offs | S1: List of Take offs | V1: List of Take offs
A2: Project | B2: West Henderson | D2: Unit Type | E2: Number | F2: % | H2: Bldg. | I2: Levels | J2: Unit | K2: 1 Br - 1 Ba | L2: 2 Br - 1 Ba | M2: 2 Br - 2 Ba | N2: 3 Br - 2 Ba | O2: GSF | P2: Slab SF | Q2: 145399.85 | R2: GSF (Provided in Matrix) | S2: 1 Br - 1 Ba Counter | T2: 9150.98 | U2: SF | V2: Structural | W2: 59616.52 | AP2: Finish Carpentry | AW2: Exhaust Per Building | BE2: Unit Breakdown | BF2: Wire Shelving LF | BG2: Bedrooms | BH2: Bathrooms | BI2: Unit Count | BJ2: Windows
A3: Budget Level | B3: Level 2 | D3: Studios | E3: 0 | F3: 0 | H3: 1 | I3: 3 | J3: 169 | K3: 87 | L3: 17 | M3: 48 | N3: 17 | O3: 185300 | P3: Elevators | Q3: 4 | R3: Count | S3: 2 Br - 1 Ba Counter | T3: 2673.44 | U3: SF | AA3: Railing Estimate | AE3: Building 3 | AF3: =21*7 -> 147 | AH3: Stucco | AJ3: 1.1 | AP3: Unit Type | AQ3: Number | AR3: TP $ | AS3: % | AT3: % | AW3: Building | AX3: Floors | AY3: U / Floor | AZ3: Total Units | BA3: Cost / U | BB3: Total | BE3: A1A | BF3: 41 | BG3: 1 | BH3: 1 | BI3: 9 | BJ3: 3 | BK3: =BJ3*BI3 -> 27
A4: Product | B4: Affordable | D4: 1 Br - 1 Ba | E4: 178 | F4: 0.45641026 | H4: 2 | I4: 2 | J4: 24 | K4: 9 | L4: 7 | M4: 8 | N4: 0 | O4: 24353 | P4: Elevators Stops | Q4: 12 | R4: Count | S4: 2 Br - 2 Ba Counter | T4: 2893.8 | U4: SF | AA4: Building 1 | AF4: =14*7 -> 98 | AH4: Building 1 | AI4: =88591.52+6310.7+12391.66+5996.96 -> 113290.84 | AJ4: =AI4*$AJ$3 -> 124619.92 | AP4: Studios | AQ4: 0 | AR4: 3192.5 | AS4: 0 | AT4: =AR4*(1+AS4) -> 3192.5 | AW4: Building 1 | AX4: 3 | AY4: 9 | AZ4: =AY4*AX4 -> 27 | BA4: =275 -> 275 | BB4: =BA4*AZ4 -> 7425 | BE4: B1A | BF4: 31 | BG4: 1 | BH4: 1 | BI4: 106 | BJ4: 3 | BK4: =BJ4*BI4 -> 318
A5: UPDATED | B5: 45884 | D5: 2 Br - 1 Ba | E5: 49 | F5: 0.12564103 | H5: 3 | I5: 3 | J5: 173 | K5: 73 | L5: 18 | M5: 51 | N5: 31 | O5: 192543 | P5: Trash Encl. | Q5: 13 | R5: Provided in Site Plan | S5: 3 Br - 2 Ba Counter | T5: 3543.36 | U5: SF | AA5: Northwest | AB5: =21*4+8*8+7*6 -> 190 | AF5: =8*22 -> 176 | AH5: Building 2 | AI5: =31183.77/2 -> 15591.885 | AJ5: =AI5*$AJ$3 -> 17151.074 | AP5: 1 Br - 1 Ba | AQ5: 171 | AR5: 3192.5 | AS5: 0 | AT5: =AR5*(1+AS5) -> 3192.5 | AW5: Building 2 | AX5: 2 | AY5: 2 | AZ5: =AY5*AX5 -> 4 | BA5: =275 -> 275 | BB5: =BA5*AZ5 -> 1100 | BE5: B1AE | BF5: 31 | BG5: 1 | BH5: 1 | BI5: 3 | BJ5: 3 | BK5: =BJ5*BI5 -> 9
A6: Timeline | B6: 26 | D6: 2 Br - 2 Ba | E6: 115 | F6: 0.29487179 | H6: 4 | I6: 2 | J6: 24 | K6: 9 | L6: 7 | M6: 8 | N6: 0 | O6: 24353 | P6: Stairs | Q6: 17 | R6: Count | S6: 1x1 Decks | T6: 3440 | U6: SF | AA6: Southwest | AB6: =14*4+21*2+8*6 -> 146 | AF6: =7*10 -> 70 | AH6: Building 3 | AI6: =65053.99+12730.03+12624.72 -> 90408.74 | AJ6: =AI6*$AJ$3 -> 99449.614 | AP6: 2 Br - 1 Ba | AQ6: 52 | AR6: 3192.5 | AS6: 0 | AT6: =AR6*(1+AS6) -> 3192.5 | AW6: Building 3 | AX6: 2 | AY6: 9 | AZ6: =AY6*AX6 -> 18 | BA6: =275 -> 275 | BB6: =BA6*AZ6 -> 4950 | BE6: B1B | BF6: 19 | BG6: 1 | BH6: 1 | BI6: 60 | BJ6: 2 | BK6: =BJ6*BI6 -> 120
A7: Floors | B7: 2 & 3 Levels | D7: 3 Br - 2 Ba | E7: 48 | F7: 0.12307692 | P7: Pool | Q7: 1 | S7: 2x1 Decks | U7: SF | AA7: Northeast | AB7: =21*2+14*2+8*6 -> 118 | AF7: =SUM(AF3:AF6) -> 491 | AH7: Building 4 | AI7: =31183.77/2 -> 15591.885 | AJ7: =AI7*$AJ$3 -> 17151.074 | AP7: 2 Br - 2 Ba | AQ7: 118 | AR7: 3192.5 | AS7: 0.1 | AT7: =AR7*(1+AS7) -> 3511.75 | AW7: Building 4 | AX7: 3 | AY7: 3 | AZ7: =AY7*AX7 -> 9 | BA7: =275 -> 275 | BB7: =BA7*AZ7 -> 2475 | BE7: A2B | BF7: 66 | BG7: 2 | BH7: 2 | BI7: 8 | BJ7: 3 | BK7: =BJ7*BI7 -> 24
A8: Bldg. SF | B8: 422635 | D8: Totals | E8: 390 | F8: 1 | H8: Totals | I8: 10 | J8: 390 | K8: 178 | L8: 49 | M8: 115 | N8: 48 | O8: 426549 | P8: Gym | Q8: 2 | S8: Lightweight | T8: 261305.65 | U8: SF | AA8: Southeast | AB8: =21*2+14*8+8*12+7*8 -> 306 | AJ8: =SUM(AJ4:AJ7) -> 258371.69 | AK8: sf | AP8: 3 Br - 2 Ba | AQ8: 49 | AR8: 3192.5 | AS8: 0.2 | AT8: =AR8*(1+AS8) -> 3831 | AW8: Building 5 | AX8: 2 | AY8: 2 | AZ8: =AY8*AX8 -> 4 | BA8: 275 | BB8: =BA8*AZ8 -> 1100 | BE8: B2A | BF8: 45 | BG8: 2 | BH8: 1 | BI8: 6 | BJ8: 3 | BK8: =BJ8*BI8 -> 18
A9: Acres | B9: 15.826 | D9: Parking | P9: Iron Rail | Q9: 3074.7 | R9: LF | S9: Pavers | T9: 900 | U9: SF | AA9: More | AB9: =21*4+8*6 -> 132 | AC9: =SUM(AB5:AB9) -> 892 | AJ9: =AJ8/9 -> 28707.965 | AK9: sy | AP9: Totals | AQ9: =SUM(AQ4:AQ8) -> 390 | AT9: =SUMPRODUCT(AQ4:AQ8,AT4:AT8)/AQ9 -> 3369.3154 | BB9: =SUM(BB4:BB8) -> 17050 | BE9: B2B | BF9: 68 | BG9: 2 | BH9: 2 | BI9: 107 | BJ9: 3 | BK9: =BJ9*BI9 -> 321
A10: Site SF | B10: 689380.56 | D10: Garage Parking | F10: 0 | P10: Roofing | Q10: 1734.0111 | R10: Square | S10: Pool Deck | T10: 7964 | U10: SF | AT10: =AT9-AR8 -> 176.81538 | BE10: B2C | BF10: 44 | BG10: 2 | BH10: 1 | BI10: 43 | BJ10: 6 | BK10: =BJ10*BI10 -> 258
A11: Buildings | B11: 4 | D11: Cover Parking | F11: 375 | P11: Stucco | Q11: 28186.002 | R11: Square Yard | S11: Pool Fence | T11: 372 | U11: LF | V11: Corridor Bldg. 1 | W11: 19288 | X11: SF | AA11: Building 2 & 5 | AE11: Building 4 | AF11: =14*8 -> 112 | AT11: =AT10/AR8 -> 0.055384615 | BE11: A3A | BF11: 48 | BG11: 3 | BH11: 2 | BI11: 3 | BJ11: 4 | BK11: =BJ11*BI11 -> 12
A12: Reports Available | D12: Open Parking | F12: 320 | P12: Liav GSF | Q12: 329873 | R12: SF | S12: Dog Park Fence | T12: 400 | U12: LF | V12: Corridor Bldg. 2 | W12: 2159 | X12: SF | AA12: Northwest | AF12: =20*8 -> 160 | BE12: B3A | BF12: 55 | BG12: 3 | BH12: 2 | BI12: 45 | BJ12: 4 | BK12: =BJ12*BI12 -> 180
A13: Site Evaluation Report (GCW) | B13: 45062 | D13: Accessible Parking | F13: 16 | P13: Carports | Q13: 375 | R13: Count | S13: Common Bldg. 1 | T13: 7476 | U13: SF | V13: Corridor Bldg. 3 | W13: 20355 | X13: SF | AA13: Southwest | AF13: =8*18 -> 144 | BF13: =SUMPRODUCT(BF3:BF12,BI3:BI12) -> 17473 | BI13: =SUM(BI3:BI12) -> 390 | BK13: =SUM(BK3:BK12) -> 1287
A14: Soils Report (Universal) | B14: 45848 | D14: Private Garages | F14: 0 | J14: TOTAL COST | L14: 79847909 | P14: Stairs Landings | Q14: 47 | R14: Landings | S14: Common Bldg. 2 | T14: 0 | U14: SF | V14: Corridor Bldg. 4 | W14: 2159 | X14: SF | AA14: Northeast | AF14: =7*12 -> 84 | BK14: =(6+7)*2+4 -> 30
A15: Alta Survey (Wallace) | B15: 45583 | D15: Total Parking Provided | F15: 711 | J15: PER UNIT | L15: 204738.23 | P15: Pump House | Q15: 1 | R15: EA | S15: Common Bldg. 3 | T15: 1888 | U15: SF | V15: TOTAL | W15: 43961 | X15: SF | AA15: Southeast | AB15: =21*2+14*2+8*6+7*6 -> 160 | AC15: =AB15*2 -> 320 | AF15: =SUM(AF11:AF14) -> 500 | BK15: 7 | BL15: 10
A16: Plans | B16: 45825 | D16: Parking Ratio | F16: 1.8230769 | J16: PER GSF | L16: 188.92877 | P16: Lock Boxes | Q16: 10 | R16: EA | S16: Common Bldg. 4 | T16: 1557 | U16: SF | V16: BBQ | W16: 8 | X16: Count | BK16: 13 | BL16: 6
A17: NVE Planning Memo | B17: 45043 | P17: Awning Small | Q17: 58 | R17: EA | S17: Common Bldg. 5 | T17: 0 | U17: SF | V17: Fire Pumps | W17: 1 | X17: Count | AA17: B1B Railings | AB17: =12.5*62 -> 775 | BK17: 22 | BL17: 3
P18: Awning Large | Q18: 10 | R18: EA | S18: HVAC ADD Count | T18: 135.25641 | V18: Asphalt | W18: 256408.47 | BL18: =BK13+BK14+BK15+BK16+BK17+BL15+BL16+BL17 -> 1378
A19: Description | B19: Cost Code | C19: Cost Category | D19: Sub job | E19: Source | F19: Unit Meas. | G19: QTY | H19: Unit Cost | I19: Escalation % | J19: T. Unit Cost | K19: Sub Total | L19: Total | M19: Description / Details | BL19: =BL18*368 -> 507104
A20: General Requirements | B20: 01 | L20: 3849810.3
A21: General Requirements | B21: 01 | C21: S | F21: Mo | G21: 26 | H21: 148069.63 | I21: 0 | J21: 148069.63 | K21: 3849810.3 | AX21: Slab | AY21: Lightweight | AZ21: Roofing
A22: Existing Conditions | B22: 02 | L22: 12000 | AW22: Building 1 | AX22: 59487.01 | AY22: =58247.42+58464.84 -> 116712.26 | AZ22: =62310.84+10234.24 -> 72545.08 | BE22: 15 | BG22: 2
A23: Potholing | B23: 02-3213 | C23: S | D23: ON-SITE | E23: Allowance | G23: 1 | H23: 12000 | I23: 0 | J23: 12000 | K23: 12000 | AW23: Building 2 | AX23: 11996.7 | AY23: 11552.49 | AZ23: =12091.16+2030.7 -> 14121.86 | BE23: 5 | BG23: 2
A24: Concrete | B24: 03 | L24: 2546599.2 | AW24: Building 3 | AX24: 61844.96 | AY24: =60632.4+60507.06 -> 121139.46 | AZ24: =62164.89+10362.59 -> 72527.48 | BE24: 8 | BG24: 3
A25: Slabs | B25: 03-3101 | C25: S | D25: BUILDING | E25: Torrey Pines | F25: SF | G25: 145399.85 | H25: 11.5 | I25: 0 | J25: 11.5 | K25: 1672098.3 | M25: Proposal from NRC at $9.16. Conversation with NRC said he would at $11 to 11.50 if he wasn't aggressive. | AW25: Building 4 | AX25: 12071.18 | AY25: 11901.44 | AZ25: =12174.39+2032.3 -> 14206.69 | BE25: 22 | BG25: 1
A26: Deepened Footings | B26: 03-3101 | C26: S | D26: BUILDING | E26: N/A | J26: 0 | K26: 0 | AW26: Total | AX26: =SUM(AX22:AX25) -> 145399.85 | AY26: =SUM(AY22:AY25) -> 261305.65 | AZ26: =SUM(AZ22:AZ25) -> 173401.11 | BE26: 8 | BG26: 1
A27: Concrete Slab Repairs | B27: 03-3101 | C27: RR | D27: BUILDING | E27: Allowance | F27: LS | G27: 1 | H27: 7500 | I27: 0 | J27: 7500 | K27: 7500 | AF27: =1800+1350+1350+360+900+360+900+1080+360+450 -> 8910
A28: Pump House Concrete | B28: 03-3101 | C28: S | D28: PUMPHOUSE | E28: Allowance | F28: LS | G28: 1 | H28: 10000 | I28: 0 | J28: 10000 | K28: 10000
A29: Trash Enclosure Concrete | B29: 03-3102 | C29: S | D29: OTHER SITE | E29: Bruner | F29: Count | G29: 14 | H29: 5500 | I29: 0 | J29: 5500 | K29: 77000
A30: Pool Area Shower Concrete | B30: 03-3105 | C30: S | D30: POOL AREA | E30: Allowance | F30: LS | G30: 1 | H30: 2500 | I30: 0 | J30: 2500 | K30: 2500
A31: Cabana Concrete | B31: 03-3107 | C31: S | D31: POOL AREA | E31: Allowance | F31: LS | G31: 1 | H31: 23500 | I31: 0 | J31: 23500 | K31: 23500 | AA31: Railings | AD31: Length Ea | AE31: Bldg 1 | AF31: Bldg 2 | AG31: Bldg 3 | AH31: Bldg 4 | AI31: Bldg 5
A32: Pool Equipment Foundation | B32: 03-3108 | C32: S | D32: POOL EQUIP | E32: Allowance | F32: LS | G32: 1 | H32: 4000 | I32: 0 | J32: 4000 | K32: 4000 | AB32: Outside Corner Units | AD32: =(21+15) -> 36 | AE32: =AD32*7*2 -> 504 | AF32: =AD32*2 -> 72 | AG32: =AD32*7 -> 252 | AH32: =AD32*8 -> 288 | AI32: 0
A33: Lightweight Concrete | B33: 03-3116 | C33: S | D33: BUILDING | E33: Bruner | F33: SF | G33: 261305.65 | H33: 2.6 | I33: 0 | J33: 2.6 | K33: 679394.69 | M33: NV Gypsum proposal at Bruner. | AB33: Inside Corner Units | AD33: 13 | AE33: =AD33*10*2 -> 260 | AF33: N/A | AG33: 260 | AH33: N/A | AI33: N/A | AL33: =AG33+AE33 -> 520
A34: Deck Concrete | B34: 03-5001 | C34: S | D34: BUILDING | E34: Bruner | F34: SF | G34: 3440 | H34: 20.525068 | I34: 0 | J34: 20.525068 | K34: 70606.233 | AB34: Small Railings | AD34: 8 | AE34: =AD34*52 -> 416 | AF34: =AD34*12 -> 96 | AG34: =AD34*28 -> 224 | AH34: =AD34*30 -> 240 | AI34: 0 | AL34: =AL33/AJ35 -> 0.19908116
A35: Parking Garage | B35: 03-G | L35: 0 | AE35: =SUM(AE32:AE34) -> 1180 | AF35: =SUM(AF32:AF34) -> 168 | AG35: =SUM(AG32:AG34) -> 736 | AH35: =SUM(AH32:AH34) -> 528 | AI35: =SUM(AI32:AI34) -> 0 | AJ35: =SUM(AE35:AI35) -> 2612
A36: Parking Garage Structure | C36: S | E36: N/A | G36: 0 | J36: 0 | K36: 0
A37: Core Slab Precast Concrete | C37: S | E37: N/A | J37: 0 | K37: 0 | AA37: Lightweight | AE37: Bldg 1 | AF37: Bldg 2 | AG37: Bldg 3 | AH37: Bldg 4 | AI37: Bldg 5
A38: Concrete Slab on Grade | C38: S | E38: N/A | J38: 0 | K38: 0 | AB38: Level 2 | AD38: SF | AE38: =62029-860-2726 -> 58443 | AF38: =12359-669 -> 11690 | AG38: =64481-860-2888 -> 60733 | AH38: =12359-669 -> 11690 | AI38: 0
A39: Concrete Topping Slab 4" / Level | C39: S | E39: N/A | J39: 0 | K39: 0 | AB39: Level 3 | AD39: SF | AE39: =62109-860-2827 -> 58422 | AF39: N/A | AG39: 60733 | AH39: N/A | AI39: 0
A40: Electrical | C40: S | E40: N/A | J40: 0 | K40: 0 | AB40: Total | AD40: SF | AE40: =SUM(AE38:AE39) -> 116865 | AF40: =SUM(AF38:AF39) -> 11690 | AG40: =SUM(AG38:AG39) -> 121466 | AH40: =SUM(AH38:AH39) -> 11690 | AI40: =SUM(AI38:AI39) -> 0 | AJ40: =SUM(AE40:AI40) -> 261711
A41: Dry Sprinklers | C41: S | E41: N/A | J41: 0 | K41: 0
A42: Mechanical Ventilation | C42: S | E42: N/A | J42: 0 | K42: 0
A43: Stairs and Railings | C43: S | E43: N/A | J43: 0 | K43: 0
A44: Masonry | B44: 04 | L44: 275600
A45: Elevator Shaft | B45: 04-2201 | C45: S | D45: BUILDING | E45: Bruner | F45: Per Stop | G45: 12 | H45: 10800 | I45: 0 | J45: 10800 | K45: 129600 | M45: Ave 2 Bidders Bruner | AY45: 145637 | BE45: Building 1 | BG45: Building 2 | BH45: Building 3 | BI45: Building 4
A46: Trash Enclosure | B46: 04-2202 | C46: S | D46: OTHER SITE | E46: Bruner | F46: Count | G46: 14 | H46: 6500 | I46: 0 | J46: 6500 | K46: 91000 | AY46: 505788 | BE46: =26738+14573 -> 41311 | BG46: 9811 | BH46: =28098+20414 -> 48512 | BI46: 9811
A47: Masonry Veneer | B47: 04-4301 | C47: S | D47: ON-SITE | E47: Allowance | F47: LS | G47: 1 | J47: 0 | K47: 0 | AY47: =AY46/AY45 -> 3.4729361 | BE47: =28744+20323 -> 49067 | BG47: 10036 | BH47: =28888+22223 -> 51111 | BI47: 10036
A48: Masonry Veneer Pool Area | B48: 04-4305 | C48: S | D48: POOL AREA | E48: Allowance | F48: LS | G48: 4 | H48: 10000 | I48: 0 | J48: 10000 | K48: 40000 | BE48: =28744+20323 -> 49067 | BH48: =28888+22223 -> 51111
A49: Pool Eq. Shower Stone | B49: 04-4306 | C49: A | D49: POOL EQUIP | E49: Allowance | F49: LS | G49: 1 | H49: 15000 | I49: 0 | J49: 15000 | K49: 15000 | BE49: =SUM(BE46:BE48) -> 139445 | BG49: =SUM(BG46:BG48) -> 19847 | BH49: =SUM(BH46:BH48) -> 150734 | BI49: =SUM(BI46:BI48) -> 19847 | BJ49: =SUM(BE49:BI49) -> 329873
A50: Metals | B50: 05 | L50: 609026.98
A51: Structural Steel | B51: 05-1201 | C51: S | D51: BUILDING | E51: Allowance | F51: LSB | G51: 59616.52 | H51: 4.03 | I51: 0 | J51: 4.03 | K51: 240254.58
A52: Elevator Shaft Iron | B52: 05-1202 | C52: S | D52: BUILDING | E52: Budget | F52: Elevators | G52: 4 | H52: 4100 | I52: 0 | J52: 4100 | K52: 16400
A53: Stair Handrails | B53: 05-5201 | C53: S | D53: BUILDING | E53: Bruner | F53: EA | G53: 30 | H53: 2250 | I53: 0 | J53: 2250 | K53: 67500
A54: Garage Stair Railings | B54: 05-5201 | C54: S | D54: BUILDING | E54: N/A | H54: 0 | I54: 0 | J54: 0 | K54: 0
A55: Cabana Iron | B55: 05-7004 | C55: S | D55: POOL AREA | E55: N/A | H55: 0 | I55: 0 | J55: 0 | K55: 0
A56: Pool Equipment Gate | B56: 05-7005 | C56: S | D56: POOL EQUIP | E56: Bruner | F56: Count | G56: 1 | H56: 2000 | I56: 0 | J56: 2000 | K56: 2000
A57: Iron Railings | B57: 05-7300 | C57: S | D57: BUILDING | E57: Bruner | F57: LF | G57: 3074.7 | H57: 92 | I57: 0 | J57: 92 | K57: 282872.4 | M57: Updated take off.
A58: Cable Railings | B58: 05-7316 | C58: S | D58: COMMON AREA | E58: N/A | H58: 0 | I58: 0 | J58: 0 | K58: 0 | BE58: Common Area SF
A59: Wood, Plastics, & Composites | B59: 06 | L59: 9324491 | BE59: Building 1 | BG59: Building 2 | BH59: Building 3 | BI59: Building 4
A60: Dumpsters | B60: 06-0111 | C60: S | D60: DUMPSTERS | H60: 0 | I60: 0 | J60: 0 | K60: 0 | BE60: =34267-26738 -> 7529 | BG60: =24339-9711-10036 -> 4592 | BH60: =108549-28098-28888-28888 -> 22675 | BI60: =24339-9711-10036 -> 4592
A61: Framing | B61: 06-1100 | C61: S | D61: BUILDING | E61: Proposals | F61: SF | G61: 422635 | H61: 18 | I61: 0 | J61: 18 | K61: 7607430 | M61: Gilmore proposal including pump house and shade structure came up to $17.36 psf building. | BE61: =35267-28744 -> 6523 | BH61: =26740-20414+27152-22223+27170-22223 -> 16202
A62: Framing - Crane | B62: 06-1100 | C62: S | D62: BUILDING | E62: N/A | I62: 0 | J62: 0 | K62: 0 | BE62: =35321-28744 -> 6577
A63: Cabana Framing | B63: 06-1109 | C63: S | D63: COMMON AREA | E63: Allowance | F63: LS | G63: 1 | H63: 15000 | I63: 0 | J63: 15000 | K63: 15000 | BE63: =25934-14573 -> 11361
A64: BBQ Framing | B64: 06-1110 | C64: S | D64: COMMON AREA | E64: Allowance | F64: LS | G64: 8 | H64: 2500 | I64: 0 | J64: 2500 | K64: 20000 | BE64: =26745-20323 -> 6422
A65: Fireplace Framing | B65: 06-1111 | C65: S | D65: COMMON AREA | E65: N/A | I65: 0 | J65: 0 | K65: 0
A66: Trellis | B66: 06-1114 | C66: S | D66: BUILDING | E66: N/A | I66: 0 | J66: 0 | K66: 0
A67: Pool Equipment Framing | B67: 06-1114 | C67: S | D67: POOL EQUIP | E67: N/A | I67: 0 | J67: 0 | K67: 0
A68: Finish Carpentry - Units | B68: 06-2001 | C68: S | D68: BUILDING | E68: Proposal | F68: Liav GSF | G68: 329873 | H68: 3.5481958 | I68: 0 | J68: 3.5481958 | K68: 1170454 | M68: Door & Milwood Proposal. Rystin proposal is lower at $1,064,161 | BE68: =26781-20323 -> 6458
A69: Finish Carpentry - Common | B69: 06-2001 | C69: S | D69: COMMON AREA | E69: Proposal | F69: Common SF | G69: 87842 | H69: 5.7148858 | I69: 0 | J69: 5.7148858 | K69: 502007 | M69: Door & Milwood Proposal. Rystin proposal is lower at $419K | BE69: =SUM(BE60:BE68) -> 44870 | BG69: =SUM(BG60:BG68) -> 4592 | BH69: =SUM(BH60:BH68) -> 38877 | BI69: =SUM(BI60:BI68) -> 4592 | BJ69: =SUM(BE69:BI69) -> 92931
A70: BBQ Trim | B70: 06-2006 | C70: S | D70: COMMON AREA | E70: Allowance | F70: LS | G70: 8 | H70: 1200 | I70: 0 | J70: 1200 | K70: 9600
A71: Shutters | B71: 06-4919 | C71: S | D71: BUILDING | E71: N/A | I71: 0 | J71: 0 | K71: 0
A72: Thermal & Moisture Protection | B72: 07 | C72: Jason | L72: 2237303.8
A73: Insulation | B73: 07-2101 | C73: S | D73: BUILDING | E73: Bruner | F73: SF | G73: 422635 | H73: 2.5 | I73: 0 | J73: 2.5 | K73: 1056587.5 | M73: Red Rock contract per SF at Bruner.
A74: Roofing | B74: 07-3001 | C74: S | D74: BUILDING | E74: Proposals | F74: Square | G74: 1734.0111 | H74: 565 | I74: 0 | J74: 565 | K74: 979716.27 | M74: We have 2 proposal under $565/square (Xbuilt and Deset Roofing)
A75: Cabana Roofing | B75: 07-3002 | C75: S | D75: COMMON AREA | E75: Allowance | F75: LS | G75: 1 | H75: 5500 | I75: 0 | J75: 5500 | K75: 5500
A76: Pump House Roofing | B76: 07-3002 | C76: S | D76: PUMPHOUSE | E76: Allowance | F76: LS | G76: 1 | H76: 9500 | I76: 0 | J76: 9500 | K76: 9500
A77: Pool Equipment Roofing | B77: 07-3003 | C77: S | D77: POOL EQUIP | E77: Allowance | F77: LS | G77: 0 | H77: 7500 | I77: 0 | J77: 7500 | K77: 0
A78: Trash Enclosure Cover | B78: 07-6101 | C78: S | D78: OTHER SITE | E78: Bruner | F78: Count | G78: 14 | H78: 6500 | I78: 0 | J78: 6500 | K78: 91000
A79: Pigeon Proofing | B79: 07-7001 | C79: S | D79: BUILDING | E79: Allowance | F79: LS | G79: 1 | H79: 25000 | I79: 0 | J79: 25000 | K79: 25000
A80: Gutters and Downspouts | B80: 07-7124 | C80: S | D80: BUILDING | E80: Allowance | F80: LS | G80: 1 | H80: 25000 | I80: 0 | J80: 25000 | K80: 25000
A81: Roof Ladders | B81: 07-7210 | C81: S | D81: BUILDING | E81: Bruner | F81: Count | G81: 10 | H81: 1750 | I81: 0 | J81: 1750 | K81: 17500 | M81: 2 Per building
A82: Roof Access Doors | B82: 07-7233 | C82: S | D82: BUILDING | E82: Bruner | F82: Count | G82: 10 | H82: 2750 | I82: 0 | J82: 2750 | K82: 27500 | M82: 2 Per building
A83: Roof Winch | B83: 07-7250 | C83: S | D83: BUILDING | E83: N/A | I83: 0 | J83: 0 | K83: 0
A84: Openings | B84: 08 | C84: Jason | L84: 690619
A85: Dumpsters | B85: 08-0151 | C85: S | D85: DUMPSTERS | H85: 79 | I85: 0 | J85: 79 | K85: 0
A86: Entry Doors | B86: 08-1001 | C86: S | D86: COMMON AREA | E86: N/A | I86: 0 | J86: 0 | K86: 0
A87: Common Doors | B87: 08-1002 | C87: S | D87: COMMON AREA | E87: Included | I87: 0 | J87: 0 | K87: 0
A88: Pocket Doors - 3 Panel | B88: 08-1002 | C88: S | D88: BUILDING | E88: N/A | I88: 0 | J88: 0 | K88: 0
A89: Garage Doors | B89: 08-3619 | C89: S | D89: BUILDING | E89: N/A | I89: 0 | J89: 0 | K89: 0
A90: Windows and Sliding Glass Doors | B90: 08-5301 | C90: S | D90: BUILDING | E90: Bruner | F90: Per Unit | G90: 390 | H90: 1336 | I90: 0.1 | J90: 1469.6 | K90: 573144 | M90: Bruner approved cost per sf + 10% escalation to account for the extra bedrooms
A91: Windows Repair and Replacement | B91: 08-5301 | C91: RR | D91: BUILDING | E91: Allowance | F91: Per Unit | G91: 390 | H91: 50 | I91: 0 | J91: 50 | K91: 19500
A92: Pool Equipment Windows | B92: 08-5303 | C92: S | D92: POOL EQUIP | E92: N/A | I92: 0 | J92: 0 | K92: 0
A93: Pool Glass Walls | B93: 08-8001 | C93: S | D93: POOL AREA | E93: N/A | I93: 0 | J93: 0 | K93: 0
A94: Fixed Glass | B94: 08-8002 | C94: S | D94: BUILDING | E94: N/A | I94: 0 | J94: 0 | K94: 0
A95: Mirrors - LED | B95: 08-8301 | C95: S | D95: BUILDING | E95: N/A | I95: 0 | J95: 0 | K95: 0
A96: Mirrors - LED Install | B96: 08-8302 | C96: S | D96: BUILDING | E96: N/A | I96: 0 | J96: 0 | K96: 0
A97: Mirrors - Framed | B97: 08-8301 | C97: S | D97: BUILDING | E97: N/A | I97: 0 | J97: 0 | K97: 0
A98: Mirrors - Polished Edges (Units) | B98: 08-8301 | C98: S | D98: BUILDING | E98: Bruner | F98: Bathrooms | G98: 553 | H98: 175 | I98: 0 | J98: 175 | K98: 96775
A99: Mirrors - Polished Edges (Restrooms) | B99: 08-8301 | C99: S | D99: BUILDING | E99: Allowance | F99: Count | G99: 4 | H99: 300 | I99: 0 | J99: 300 | K99: 1200
A100: Finishes | B100: 09 | C100: Jason | L100: 6934652.6
...

Sheet Insurance_Bonds
A1: West Henderson | U1: Contractor Insurance and Bonds
B8: Contractor General Liability Insurance | K8: P&P Bond
B10: Underlying Policy (First $1 mm) | K10: Months of Construction | M10: 18
B11: Rate (per $1,000 of Contractor Revenue) | E11: 3.7395 | K11: Total Hard Costs | M11: 77376748
B12: Total GC Contract | E12: 77376748
B13: Subtotal | E13: =E11/1000*E12 -> 289350.35
B14: Fees/Taxes/Possible Increases | E14: =E13*F14 -> 22424.652 | F14: 0.0775 | K14: Basic Rate Table
B15: Total Insurance | E15: =E13+E14 -> 311775 | Q15: Total
M16: Rate Per $K | N16: Contract Price | O16: Base Rate | P16: Surcharge | Q16: Premium
B17: Umbrella Policy ($20 mm Excess Coverage) | K17: First | L17: 100000 | M17: 14.4 | N17: 100000 | O17: =+N17/1000*M17 -> 1440 | P17: =IF(O17>0,IF((M10-12)>0,(M10-12)*0.01,"0"),"0") -> 0.06 | Q17: =IF((M10-12)>0,(1+P17)*O17,O17) -> 1526.4
B18: Rate (per $1,000 of Contractor Revenue) | E18: 3.996 | K18: Next | L18: 400000 | M18: 13.68 | N18: 400000 | O18: =+N18/1000*M18 -> 5472 | P18: =IF(O18>0,IF((M10-12)>0,(M10-12)*0.01,"0"),"0") -> 0.06 | Q18: =IF((M10-12)>0,(1+P18)*O18,O18) -> 5800.32
B19: Total GC Contract | E19: =E12 -> 77376748 | K19: Next | L19: 2000000 | M19: 8.7 | N19: 2000000 | O19: =+N19/1000*M19 -> 17400 | P19: =IF(O19>0,IF((M10-12)>0,(M10-12)*0.01,"0"),"0") -> 0.06 | Q19: =IF((M10-12)>0,(1+P19)*O19,O19) -> 18444
B20: Subtotal | E20: =E18/1000*E19 -> 309197.48 | K20: Next | L20: 2500000 | M20: 6.9 | N20: 2500000 | O20: =+N20/1000*M20 -> 17250 | P20: =IF(O20>0,IF((M10-12)>0,(M10-12)*0.01,"0"),"0") -> 0.06 | Q20: =IF((M10-12)>0,(1+P20)*O20,O20) -> 18285
B21: Fees/Taxes/Possible Increases | E21: =E20*F21 -> 18551.849 | F21: 0.06 | K21: Next | L21: 2500000 | M21: 6.3 | N21: 2500000 | O21: =+N21/1000*M21 -> 15750 | P21: =IF(O21>0,IF((M10-12)>0,(M10-12)*0.01,"0"),"0") -> 0.06 | Q21: =IF((M10-12)>0,(1+P21)*O21,O21) -> 16695
B22: Total Umbrella | E22: =E20+E21 -> 327749.33 | K22: Next | L22: 2500000 | M22: 5.76 | N22: =+M11-SUM(N17:N21) -> 69876748 | O22: =+N22/1000*M22 -> 402490.07 | P22: =IF(O22>0,IF((M10-12)>0,(M10-12)*0.01,"0"),"0") -> 0.06 | Q22: =IF((M10-12)>0,(1+P22)*O22,O22) -> 426639.47
K23: Over | L23: 10000000 | M23: 5.76 | O23: =+N23/1000*M23 -> 0 | P23: =IF(O23>0,IF((M10-12)>0,(M10-12)*0.01,"0"),"0") -> 0 | Q23: =IF((M10-12)>0,(1+P23)*O23,O23) -> 0
B24: Total GL Insurance | E24: =E15+E22 -> 639524.33 | M24: Totals | N24: =SUM(N17:N23) -> 77376748 | O24: =SUM(O17:O23) -> 459802.07 | Q24: =SUM(Q17:Q23) -> 487390.19
B26: Annual Policy Inflation | E26: 0.1
B30: % Completed by Year
F31: Policy Allocation | K31: Sub Bonds
B32: Year | E32: % Completed | F32: Pre-Inflation | G32: Post-Inflation | K32: Sub Bonds % | M32: ='[83]Level 1.1 UPDATE B'!G327 -> 0.013
B33: 1 | E33: 0.85921962 | F33: =E33*$E$24 -> 549491.85 | G33: =F33*(1+$E$26)^(B33-1) -> 549491.85 | K33: Applicable Costs* | M33: =SUM('[84]Level 1.1'!L16:L286) -> 27580796
B34: 2 | E34: 0.14078038 | F34: =E34*$E$24 -> 90032.482 | G34: =F34*(1+$E$26)^(B34-1) -> 99035.73 | K34: Sub Bonds | M34: =M32*M33 -> 358550.35
B35: 3 | E35: 0 | F35: =E35*$E$24 -> 0 | G35: =F35*(1+$E$26)^(B35-1) -> 0 | K35: *Hard Costs excluding FF&E, Contingency, Insurance, Contractor Fee, and General Requirements
D36: Total GL Insurance | F36: =SUM(F33:F35) -> 639524.33 | G36: =SUM(G33:G35) -> 648527.58
B42: Summary of Contractor Insurance and Bonds
E43: Include In Budget | F43: Budget
B44: Contractor General Liability Insurance | D44: =G36 -> 648527.58 | E44: x | F44: =IF(E44="x",D44,0) -> 648527.58
B45: P&P Bond | D45: =Q24 -> 487390.19 | F45: =IF(E45="x",D45,0) -> 0
B46: Sub Bonds | D46: =M34 -> 358550.35 | E46: x | F46: =IF(E46="x",D46,0) -> 358550.35
B47: Subtotal | D47: =SUM(D44:D46) -> 1494468.1 | F47: =SUM(F44:F46) -> 1007077.9

Sheet Level 3
A1: Project Details | D1: Unit Breakdown | H1: Breakdown Per Building | P1: List of Take offs | S1: List of Take offs | V1: List of Take offs
A2: Project | B2: West Henderson | D2: Unit Type | E2: Number | F2: % | H2: Bldg. | I2: Levels | J2: Unit | K2: 1 Br - 1 Ba | L2: 2 Br - 1 Ba | M2: 2 Br - 2 Ba | N2: 3 Br - 2 Ba | O2: GSF | P2: Slab SF | Q2: 145399.85 | R2: GSF (Provided in Matrix) | S2: 1 Br - 1 Ba Counter | T2: =(14.42+12.35+13.12+11.52)*K8 -> 9150.98 | U2: SF | V2: Structural | W2: 59616.52
A3: Budget Level | B3: Level 3 | D3: Studios | E3: 0 | F3: =E3/$E$8 -> 0 | H3: 1 | I3: 3 | J3: =SUM(K3:N3) -> 169 | K3: =29*3 -> 87 | L3: 17 | M3: 48 | N3: 17 | O3: 185300 | P3: Elevators | Q3: 4 | R3: Count | S3: 2 Br - 1 Ba Counter | T3: =L8*(43.46+3.6+7.5) -> 2673.44 | U3: SF | V3: Corridor Bldg. 1 | W3: =3808+3514+3590+3041+2630+2705 -> 19288 | X3: SF
A4: Product | B4: Affordable | D4: 1 Br - 1 Ba | E4: =K8 -> 178 | F4: =E4/$E$8 -> 0.45641026 | H4: 2 | I4: 2 | J4: =SUM(K4:N4) -> 24 | K4: 9 | L4: 7 | M4: 8 | N4: 0 | O4: 24353 | P4: Elevators Stops | Q4: =Q3*3 -> 12 | R4: Count | S4: 2 Br - 2 Ba Counter | T4: =(13+13+12+12.5+6.3)*6+(8.5+16+13+7+11)*46 -> 2893.8 | U4: SF | V4: Corridor Bldg. 2 | W4: =1077+1082 -> 2159 | X4: SF
A5: UPDATED | B5: 46020 | D5: 2 Br - 1 Ba | E5: =L8 -> 49 | F5: =E5/$E$8 -> 0.12564103 | H5: 3 | I5: 3 | J5: 173 | K5: 73 | L5: 18 | M5: 51 | N5: 31 | O5: 192543 | P5: Trash Encl. | Q5: 13 | R5: Provided in Site Plan | S5: 3 Br - 2 Ba Counter | T5: =(15+7+4+16.82+31)*N8 -> 3543.36 | U5: SF | V5: Corridor Bldg. 3 | W5: =3955+3726+3726+3298+2825+2825 -> 20355 | X5: SF
A6: Timeline | B6: 26 | D6: 2 Br - 2 Ba | E6: =M8 -> 115 | F6: =E6/$E$8 -> 0.29487179 | H6: 4 | I6: 2 | J6: 24 | K6: 9 | L6: 7 | M6: 8 | N6: 0 | O6: 24353 | P6: Stairs | Q6: =6+7+4 -> 17 | R6: Count | S6: 1x1 Decks | T6: =86*20*2 -> 3440 | U6: SF | V6: Corridor Bldg. 4 | W6: =1077+1082 -> 2159 | X6: SF
A7: Floors | B7: 2 & 3 Levels | D7: 3 Br - 2 Ba | E7: =N8 -> 48 | F7: =E7/$E$8 -> 0.12307692 | P7: Pool | Q7: 1 | S7: 2x1 Decks | U7: SF | V7: TOTAL | W7: =SUM(W3:W6) -> 43961 | X7: SF
A8: Bldg. SF | B8: 422635 | D8: Totals | E8: =SUM(E3:E7) -> 390 | F8: =E8/$E$8 -> 1 | H8: Totals | I8: =SUM(I3:I7) -> 10 | J8: =SUM(J3:J7) -> 390 | K8: =SUM(K3:K7) -> 178 | L8: =SUM(L3:L7) -> 49 | M8: =SUM(M3:M7) -> 115 | N8: =SUM(N3:N7) -> 48 | O8: =SUM(O3:O7) -> 426549 | P8: Gym | Q8: 2 | S8: Lightweight | T8: 261305.65 | U8: SF | V8: BBQ | W8: 8 | X8: Count
A9: Acres | B9: 15.826 | D9: Parking | P9: Iron Rail | Q9: 3228 | R9: LF | S9: Pavers | T9: 900 | U9: SF | V9: Fire Pumps | W9: 1 | X9: Count
A10: Site SF | B10: =B9*43560 -> 689380.56 | D10: Garage Parking | F10: 0 | P10: Roofing | Q10: 1734.0111 | R10: Square | S10: Pool Deck | T10: =10114-1655-215-35*8 -> 7964 | U10: SF | V10: Asphalt Onsite | W10: 243608.62
A11: Buildings | B11: 4 | D11: Cover Parking | F11: 375 | P11: Stucco | Q11: 28186.002 | R11: Square Yard | S11: Pool Fence | T11: 372 | U11: LF | V11: Asphalt Offsite | W11: 145460
A12: Reports Available | D12: Open Parking | F12: 320 | P12: GSF | Q12: 329873 | R12: SF | S12: Dog Park Fence | T12: =200*2 -> 400 | U12: LF
A13: Site Evaluation Report (GCW) | B13: 45062 | D13: Accessible Parking | F13: 16 | P13: Carports | Q13: =F11 -> 375 | R13: Count | S13: Common Bldg. 1 | T13: 7476 | U13: SF
A14: Soils Report (Universal) | B14: 45848 | D14: Private Garages | F14: 0 | J14: TOTAL COST | L14: =L321 -> 77376748 | P14: Stairs Landings | Q14: =4*2+13*3 -> 47 | R14: Landings | S14: Common Bldg. 2 | T14: 0 | U14: SF
A15: Alta Survey (Wallace) | B15: 45583 | D15: Total Parking Provided | F15: =SUM(F10:F14) -> 711 | J15: PER UNIT | L15: =L14/E8 -> 198401.92 | P15: Pump House | Q15: 1 | R15: EA | S15: Common Bldg. 3 | T15: =748+1140 -> 1888 | U15: SF
A16: Plans | B16: 45938 | D16: Parking Ratio | F16: =SUM(F10:F13)/E8 -> 1.8230769 | J16: PER GSF | L16: =L14/B8 -> 183.08173 | P16: Lock Boxes | Q16: 10 | R16: EA | S16: Common Bldg. 4 | T16: 1557 | U16: SF
A17: NVE Planning Memo | B17: 45043 | P17: Awning Small | Q17: 58 | R17: EA | S17: Common Bldg. 5 | T17: 0 | U17: SF
P18: Awning Large | Q18: 10 | R18: EA | S18: HVAC ADD Count | T18: =(E6*250+E7*500)/E8 -> 135.25641
A19: Description | B19: Cost Code | C19: Cost Category | D19: Sub job | E19: Source | F19: Unit Meas. | G19: QTY | H19: Unit Cost | I19: Esc. % | J19: T. Unit Cost | K19: Sub Total | L19: Total | M19: Description / Details
A20: General Requirements | B20: 01 | C20: S | I20: 0.06 | K20: =I20*SUM(K22:K308,K311) -> 3857213.7
A21: General Requirements | B21: 01 | L21: =K20 -> 3857213.7
A22: Potholing | B22: 02-3213 | C22: S | D22: ON-SITE | E22: Allowance | G22: 1 | H22: 12000 | I22: 0 | J22: =H22*(1+I22) -> 12000 | K22: =J22*G22 -> 12000
A23: Existing Conditions | B23: 02 | L23: =K22 -> 12000
A24: Slabs | B24: 03-3101 | C24: S | D24: BUILDING | E24: Proposal | F24: SF | G24: =Q2 -> 145399.85 | H24: 9.5 | I24: 0 | J24: =H24*(1+I24) -> 9.5 | K24: =J24*G24 -> 1381298.6 | M24: Proposal by NRC at $9.16/sf
A25: Deepened Footings | B25: 03-3101 | C25: S | D25: BUILDING | E25: N/A | J25: =H25*(1+I25) -> 0 | K25: =J25*G25 -> 0
A26: Concrete Slab Repairs | B26: 03-3101 | C26: RR | D26: BUILDING | E26: Allowance | F26: LS | G26: 1 | H26: =2500*3 -> 7500 | I26: 0 | J26: =H26*(1+I26) -> 7500 | K26: =J26*G26 -> 7500
A27: Pump House Concrete | B27: 03-3101 | C27: S | D27: PUMPHOUSE | E27: Allowance | F27: LS | G27: 1 | H27: 10000 | I27: 0 | J27: =H27*(1+I27) -> 10000 | K27: =J27*G27 -> 10000
A28: Trash Enclosure Concrete | B28: 03-3102 | C28: S | D28: OTHER SITE | E28: Bruner | F28: Count | G28: 14 | H28: 5500 | I28: 0 | J28: =H28*(1+I28) -> 5500 | K28: =J28*G28 -> 77000
A29: Pool Area Shower Concrete | B29: 03-3105 | C29: S | D29: POOL AREA | E29: Allowance | F29: LS | G29: =$Q$7 -> 1 | H29: 2500 | I29: 0 | J29: =H29*(1+I29) -> 2500 | K29: =J29*G29 -> 2500
A30: Cabana Concrete | B30: 03-3107 | C30: S | D30: POOL AREA | E30: Allowance | F30: LS | G30: 1 | H30: 35000 | I30: 0 | J30: =H30*(1+I30) -> 35000 | K30: =J30*G30 -> 35000 | M30: Added $15k for sunken seating at pool area courtyard
A31: Pool Equipment Foundation | B31: 03-3108 | C31: S | D31: POOL EQUIP | E31: Allowance | F31: LS | G31: 1 | H31: 7500 | I31: 0 | J31: =H31*(1+I31) -> 7500 | K31: =J31*G31 -> 7500
A32: Lightweight Concrete | B32: 03-3116 | C32: S | D32: BUILDING | E32: Bruner | F32: SF | G32: =T8 -> 261305.65 | H32: 2.6 | I32: 0 | J32: =H32*(1+I32) -> 2.6 | K32: =J32*G32 -> 679394.69
A33: Deck Concrete | B33: 03-5001 | C33: S | D33: BUILDING | E33: Bruner | F33: SF | G33: =SUM($T$6:$T$7) -> 3440 | H33: 20.525068 | I33: 0 | J33: =H33*(1+I33) -> 20.525068 | K33: =J33*G33 -> 70606.233
A34: Concrete | B34: 03 | L34: =SUM(K24:K33) -> 2270799.5
A35: Elevator Shaft | B35: 04-2201 | C35: S | D35: BUILDING | E35: Bruner | F35: Per Stop | G35: =4*3 -> 12 | H35: 14000 | I35: 0 | J35: =H35*(1+I35) -> 14000 | K35: =J35*G35 -> 168000 | M35: Elevator shaf plus elevator pits.
A36: Trash Enclosure | B36: 04-2202 | C36: S | D36: OTHER SITE | E36: Bruner | F36: Count | G36: 14 | H36: 6500 | I36: 0 | J36: =H36*(1+I36) -> 6500 | K36: =J36*G36 -> 91000
A37: Masonry Veneer | B37: 04-4301 | C37: S | D37: ON-SITE | E37: Allowance | F37: LS | G37: 1 | J37: =H37*(1+I37) -> 0 | K37: =J37*G37 -> 0
A38: Masonry Veneer Pool Area | B38: 04-4305 | C38: S | D38: POOL AREA | E38: Allowance | F38: LS | G38: 4 | H38: 10000 | I38: 0 | J38: =H38*(1+I38) -> 10000 | K38: =J38*G38 -> 40000
A39: Pool Eq. Shower Stone | B39: 04-4306 | C39: A | D39: POOL EQUIP | E39: Allowance | F39: LS | G39: =$Q$7 -> 1 | H39: 15000 | I39: 0 | J39: =H39*(1+I39) -> 15000 | K39: =J39*G39 -> 15000
A40: Masonry | B40: 04 | L40: =SUM(K35:K39) -> 314000
A41: Structural Steel | B41: 05-1201 | C41: S | D41: BUILDING | E41: Allowance | F41: LSB | G41: =W2 -> 59616.52 | H41: 5 | I41: 0 | J41: =H41*(1+I41) -> 5 | K41: =J41*G41 -> 298082.6
A42: Elevator Shaft Iron | B42: 05-1202 | C42: S | D42: BUILDING | E42: Budget | F42: Elevators | G42: 4 | H42: 4100 | I42: 0 | J42: =H42*(1+I42) -> 4100 | K42: =J42*G42 -> 16400
A43: Stair Handrails | B43: 05-5201 | C43: S | D43: BUILDING | E43: Bruner | F43: EA | G43: =4*2+6*3+7*3 -> 47 | H43: 2000 | I43: 0 | J43: =H43*(1+I43) -> 2000 | K43: =J43*G43 -> 94000
A44: Garage Stair Railings | B44: 05-5201 | C44: S | D44: BUILDING | E44: N/A | H44: 0 | I44: 0 | J44: =H44*(1+I44) -> 0 | K44: =J44*G44 -> 0
A45: Shower Cover | B45: 05-7003 | D45: POOL AREA | E45: Allowance | F45: LS | G45: 1 | H45: 6000 | I45: 0 | J45: =H45*(1+I45) -> 6000 | K45: =J45*G45 -> 6000 | M45: ADDED LINE
A46: Cabana Iron | B46: 05-7004 | C46: S | D46: POOL AREA | E46: N/A | H46: 0 | I46: 0 | J46: =H46*(1+I46) -> 0 | K46: =J46*G46 -> 0
A47: Pool Equipment Gate | B47: 05-7005 | C47: S | D47: POOL EQUIP | E47: Bruner | F47: Count | G47: 1 | H47: 2000 | I47: 0 | J47: =H47*(1+I47) -> 2000 | K47: =J47*G47 -> 2000
A48: Iron Railings | B48: 05-7300 | C48: S | D48: BUILDING | E48: Bruner | F48: LF | G48: =$Q$9 -> 3228 | H48: 93 | I48: 0 | J48: =H48*(1+I48) -> 93 | K48: =J48*G48 -> 300204
A49: Cable Railings | B49: 05-7316 | C49: S | D49: COMMON AREA | E49: N/A | H49: 0 | I49: 0 | J49: =H49*(1+I49) -> 0 | K49: =J49*G49 -> 0
A50: Metals | B50: 05 | L50: =SUM(K41:K49) -> 716686.6
A51: Dumpsters | B51: 06-0111 | C51: S | D51: DUMPSTERS | H51: 0 | I51: 0 | J51: =H51*(1+I51) -> 0 | K51: =J51*G51 -> 0
A52: Framing | B52: 06-1100 | C52: S | D52: BUILDING | E52: Proposals | F52: SF | G52: =B8 -> 422635 | H52: ='Comparison to Other'!K8 -> 17.716624 | I52: 0 | J52: =H52*(1+I52) -> 17.716624 | K52: =J52*G52 -> 7487665.3 | M52: Average of 3 best proposals
A53: Framing - Crane | B53: 06-1100 | C53: S | D53: BUILDING | E53: N/A | I53: 0 | J53: =H53*(1+I53) -> 0 | K53: =J53*G53 -> 0
A54: Cabana Framing | B54: 06-1109 | C54: S | D54: COMMON AREA | E54: Allowance | F54: LS | G54: 1 | H54: 15000 | I54: 0 | J54: =H54*(1+I54) -> 15000 | K54: =J54*G54 -> 15000
A55: BBQ Framing | B55: 06-1110 | C55: S | D55: COMMON AREA | E55: Allowance | F55: LS | G55: =$W$8 -> 8 | H55: 2500 | I55: 0 | J55: =H55*(1+I55) -> 2500 | K55: =J55*G55 -> 20000
A56: Fireplace Framing | B56: 06-1111 | C56: S | D56: COMMON AREA | E56: N/A | I56: 0 | J56: =H56*(1+I56) -> 0 | K56: =J56*G56 -> 0
A57: Trellis | B57: 06-1114 | C57: S | D57: BUILDING | E57: N/A | I57: 0 | J57: =H57*(1+I57) -> 0 | K57: =J57*G57 -> 0
A58: Pool Equipment Framing | B58: 06-1114 | C58: S | D58: POOL EQUIP | E58: N/A | I58: 0 | J58: =H58*(1+I58) -> 0 | K58: =J58*G58 -> 0
A59: Finish Carpentry - Units | B59: 06-2001 | C59: S | D59: BUILDING | E59: Proposal | F59: Liav GSF | G59: =Q12 -> 329873 | H59: 3.55 | I59: 0 | J59: =H59*(1+I59) -> 3.55 | K59: =J59*G59 -> 1171049.1
A60: Finish Carpentry - Common | B60: 06-2001 | C60: S | D60: COMMON AREA | E60: Proposal | F60: Common SF | G60: 87842 | H60: =502007/87842 -> 5.7148858 | I60: 0 | J60: =H60*(1+I60) -> 5.7148858 | K60: =J60*G60 -> 502007
A61: Finish Carpentry - Pump House | B61: 06-2001S | C61: S | D61: PUMPHOUSE | E61: Allowance | F61: LS | G61: 1 | H61: 2500 | I61: 0 | J61: =H61*(1+I61) -> 2500 | K61: =J61*G61 -> 2500
A62: BBQ Trim | B62: 06-2006 | C62: S | D62: COMMON AREA | E62: Allowance | F62: LS | G62: =$W$8 -> 8 | H62: 1200 | I62: 0 | J62: =H62*(1+I62) -> 1200 | K62: =J62*G62 -> 9600
A63: Shutters | B63: 06-4919 | C63: S | D63: BUILDING | E63: N/A | I63: 0 | J63: =H63*(1+I63) -> 0 | K63: =J63*G63 -> 0
A64: Wood, Plastics, & Composites | B64: 06 | L64: =SUM(K51:K63) -> 9207821.5
A65: Insulation | B65: 07-2101 | C65: S | D65: BUILDING | E65: Proposals | F65: SF | G65: =B8 -> 422635 | H65: ='Comparison to Other'!K18 -> 2.3794882 | I65: 0 | J65: =H65*(1+I65) -> 2.3794882 | K65: =J65*G65 -> 1005655 | M65: Average of 3 best proposals
A66: Insulation - PH | B66: 07-2101 | C66: S | D66: PUMPHOUSE | E66: Proposal | F66: SF | G66: 450 | H66: =H65 -> 2.3794882 | I66: 0 | J66: =H66*(1+I66) -> 2.3794882 | K66: =J66*G66 -> 1070.7697
A67: Roofing | B67: 07-3001 | C67: S | D67: BUILDING | E67: Proposals | F67: Square | G67: =Q10 -> 1734.0111 | H67: ='Comparison to Other'!K21 -> 572.53228 | I67: 0 | J67: =H67*(1+I67) -> 572.53228 | K67: =J67*G67 -> 992777.33 | M67: Average of 3 best proposals
A68: Roofing - PH | B68: 07-3001 | C68: S | D68: PUMPHOUSE | E68: Allowance | F68: LS | G68: 1 | H68: 7500 | I68: 0 | J68: =H68*(1+I68) -> 7500 | K68: =J68*G68 -> 7500
A69: Cabana Roofing | B69: 07-3002 | C69: S | D69: COMMON AREA | E69: Allowance | F69: LS | G69: 1 | H69: 5500 | I69: 0 | J69: =H69*(1+I69) -> 5500 | K69: =J69*G69 -> 5500
A70: Pump House Roofing | B70: 07-3002 | C70: S | D70: PUMPHOUSE | E70: Allowance | F70: LS | G70: 1 | H70: 9500 | I70: 0 | J70: =H70*(1+I70) -> 9500 | K70: =J70*G70 -> 9500
A71: Pool Equipment Roofing | B71: 07-3003 | C71: S | D71: POOL EQUIP | E71: Allowance | F71: LS | G71: 0 | H71: 7500 | I71: 0 | J71: =H71*(1+I71) -> 7500 | K71: =J71*G71 -> 0
A72: Trash Enclosure Cover | B72: 07-6101 | C72: S | D72: OTHER SITE | E72: Bruner | F72: Count | G72: 14 | H72: 6000 | I72: 0 | J72: =H72*(1+I72) -> 6000 | K72: =J72*G72 -> 84000
A73: Pigeon Proofing | B73: 07-7001 | C73: S | D73: BUILDING | E73: Allowance | F73: LS | G73: 1 | H73: 25000 | I73: 0 | J73: =H73*(1+I73) -> 25000 | K73: =J73*G73 -> 25000
A74: Gutters and Downspouts | B74: 07-7124 | C74: S | D74: BUILDING | E74: Allowance | F74: LS | G74: 1 | H74: 25000 | I74: 0 | J74: =H74*(1+I74) -> 25000 | K74: =J74*G74 -> 25000
A75: Roof Ladders | B75: 07-7210 | C75: S | D75: BUILDING | E75: Bruner | F75: Count | G75: 8 | H75: 2000 | I75: 0 | J75: =H75*(1+I75) -> 2000 | K75: =J75*G75 -> 16000
A76: Roof Access Doors | B76: 07-7233 | C76: S | D76: BUILDING | E76: Bruner | F76: Count | G76: 8 | H76: 3000 | I76: 0 | J76: =H76*(1+I76) -> 3000 | K76: =J76*G76 -> 24000
A77: Roof Winch | B77: 07-7250 | C77: S | D77: BUILDING | E77: N/A | I77: 0 | J77: =H77*(1+I77) -> 0 | K77: =J77*G77 -> 0
A78: Thermal & Moisture Protection | B78: 07 | L78: =SUM(K65:K77) -> 2196003.1
A79: Entry Doors | B79: 08-1001 | C79: S | D79: COMMON AREA | E79: N/A | I79: 0 | J79: =H79*(1+I79) -> 0 | K79: =J79*G79 -> 0
A80: Common Doors | B80: 08-1002 | C80: S | D80: COMMON AREA | E80: Included | I80: 0 | J80: =H80*(1+I80) -> 0 | K80: =J80*G80 -> 0
A81: Pocket Doors - 3 Panel | B81: 08-1002 | C81: S | D81: BUILDING | E81: N/A | I81: 0 | J81: =H81*(1+I81) -> 0 | K81: =J81*G81 -> 0
A82: Garage Doors | B82: 08-3619 | C82: S | D82: BUILDING | E82: N/A | I82: 0 | J82: =H82*(1+I82) -> 0 | K82: =J82*G82 -> 0
A83: Windows and Sliding Glass Doors | B83: 08-5301 | C83: S | D83: BUILDING | E83: Contempo Proposal | F83: Per Unit | G83: =$E$8 -> 390 | H83: 1400 | I83: 0 | J83: =H83*(1+I83) -> 1400 | K83: =J83*G83 -> 546000
A84: Windows Repair and Replacement | B84: 08-5301 | C84: RR | D84: BUILDING | E84: Allowance | F84: Per Unit | G84: =$E$8 -> 390 | H84: 100 | I84: 0 | J84: =H84*(1+I84) -> 100 | K84: =J84*G84 -> 39000
A85: Pool Equipment Windows | B85: 08-5303 | C85: S | D85: POOL EQUIP | E85: N/A | I85: 0 | J85: =H85*(1+I85) -> 0 | K85: =J85*G85 -> 0
A86: Pool Glass Walls | B86: 08-8001 | C86: S | D86: POOL AREA | E86: N/A | I86: 0 | J86: =H86*(1+I86) -> 0 | K86: =J86*G86 -> 0
A87: Fixed Glass | B87: 08-8002 | C87: S | D87: BUILDING | E87: N/A | I87: 0 | J87: =H87*(1+I87) -> 0 | K87: =J87*G87 -> 0
A88: Mirrors - LED | B88: 08-8301 | C88: S | D88: BUILDING | E88: N/A | I88: 0 | J88: =H88*(1+I88) -> 0 | K88: =J88*G88 -> 0
A89: Mirrors - LED Install | B89: 08-8302 | C89: S | D89: BUILDING | E89: N/A | I89: 0 | J89: =H89*(1+I89) -> 0 | K89: =J89*G89 -> 0
A90: Mirrors - Framed | B90: 08-8301 | C90: S | D90: BUILDING | E90: N/A | I90: 0 | J90: =H90*(1+I90) -> 0 | K90: =J90*G90 -> 0
A91: Mirrors - Polished Edges (Units) | B91: 08-8301 | C91: S | D91: BUILDING | E91: Bruner | F91: Bathrooms | G91: =K8+L8+M8*2+N8*2 -> 553 | H91: 150 | I91: 0 | J91: =H91*(1+I91) -> 150 | K91: =J91*G91 -> 82950
A92: Mirrors - Polished Edges (Restrooms) | B92: 08-8301 | C92: S | D92: BUILDING | E92: Allowance | F92: Count | G92: 4 | H92: 500 | I92: 0 | J92: =H92*(1+I92) -> 500 | K92: =J92*G92 -> 2000
A93: Openings | B93: 08 | L93: =SUM(K79:K92) -> 669950
A94: Cost Prep Labor | B94: 09-0101 | C94: S | D94: BUILDING | H94: 0.05 | I94: 0 | J94: =H94*(1+I94) -> 0.05 | K94: =J94*G94 -> 0
A95: Cost Prep Mat | B95: 09-0102 | C95: S | D95: BUILDING | E95: Allowance | F95: LS | G95: 1 | H95: 25000 | I95: 0 | J95: =H95*(1+I95) -> 25000 | K95: =J95*G95 -> 25000
A96: Clean Up - Final | B96: 09-0103 | C96: S | D96: BUILDING | E96: Bruner | F96: SF | G96: =$B$8 -> 422635 | H96: 0.85 | I96: 0 | J96: =H96*(1+I96) -> 0.85 | K96: =J96*G96 -> 359239.75
A97: Clean Up - During Construction | B97: 09-0104 | C97: S | D97: BUILDING | E97: Allowance | F97: LS | G97: 1 | H97: 50000 | I97: 0 | J97: =H97*(1+I97) -> 50000 | K97: =J97*G97 -> 50000
A98: Dumpsters | B98: 09-0113 | C98: S | D98: DUMPSTERS | E98: Allowance | F98: LS | G98: 1 | H98: 20000 | I98: 0 | J98: =H98*(1+I98) -> 20000 | K98: =J98*G98 -> 20000
A99: Clean Up - Hauling Exterior | B99: 09-0121 | C99: S | D99: ON-SITE | E99: Allowance | F99: LS | G99: 1 | H99: 10000 | I99: 0 | J99: =H99*(1+I99) -> 10000 | K99: =J99*G99 -> 10000
A100: Stucco | B100: 09-2423 | C100: S | D100: BUILDING | E100: Proposal | F100: SY | G100: =Q11 -> 28186.002 | H100: =AVERAGE('Comparison to Other'!H19:I19) -> 39.311357 | I100: 0 | J100: =H100*(1+I100) -> 39.311357 | K100: =J100*G100 -> 1108030 | M100: Average of 2 best proposals
...

Sheet Summary Changes
A2: Line Item | B2: Level 2 | C2: Level 3 | D2: Variance | E2: Comments
A3: Slab Concrete | B3: ='Level 2 - Transmitted (2)'!K25 -> 1672098.3 | C3: ='Level 3'!K24 -> 1381298.6 | D3: =B3-C3 -> 290799.7 | E3: Increased unit cost $11.50 to average of 3 proposals $11.83. Recommend leaving at $11.50
A4: ='Level 2 - Transmitted (2)'!A45 -> Elevator Shaft | B4: ='Level 2 - Transmitted (2)'!K45 -> 129600 | C4: ='Level 3'!K35 -> 168000 | D4: =B4-C4 -> -38400 | E4: Increase to include elevator pis (CMU)
A5: ='Level 3'!A41 -> Structural Steel | B5: ='Level 2 - Transmitted (2)'!K51 -> 240254.58 | C5: ='Level 3'!K41 -> 298082.6 | D5: =B5-C5 -> -57828.024 | E5: Increased price per pound based on current proposals.
A6: ='Level 3'!A52 -> Framing | B6: ='Comparison to Previous'!K48 -> 7607430 | C6: ='Comparison to Previous'!R48 -> 7487665.3 | D6: =B6-C6 -> 119764.67 | E6: Changed unit cost to average of 3 current proposals
A7: ='Comparison to Previous'!A61 -> Insulation | B7: ='Comparison to Previous'!K61 -> 1056587.5 | C7: ='Comparison to Previous'!R61 -> 1005655 | D7: =B7-C7 -> 50932.5 | E7: Changed unit cost to average of 3 current proposals
A8: ='Level 3'!A117 -> Hall Flooring | B8: ='Comparison to Previous'!K114 -> 217606.95 | C8: ='Level 3'!K117 -> 292500 | D8: =B8-C8 -> -74893.05 | E8: Updated pricing per unit to Bruner (from Torrey Pines)
A9: ='Comparison to Previous'!A148 -> Appliances - Laundry Room | B9: ='Comparison to Previous'!K148 -> 0 | C9: ='Comparison to Previous'!R148 -> 130000 | D9: =B9-C9 -> -130000 | E9: Added a line item to consider cost of laundry room appliances. Considering 2.
A10: ='Comparison to Previous'!A177 -> HVAC Standard | B10: ='Comparison to Previous'!K177 -> 3851250 | C10: ='Comparison to Previous'!R177 -> 4117739.5 | D10: =B10-C10 -> -266489.5 | E10: Change unit cost to average of 2 best proposals vs Bruner.
A11: ='Comparison to Previous'!A180 -> Electrical | B11: ='Comparison to Previous'!K180 -> 4251708.1 | C11: ='Comparison to Previous'!R180 -> 4787239.7 | D11: =B11-C11 -> -535531.57 | E11: Change unit cost to average of 2 best proposals vs Bruner.
A12: ='Comparison to Previous'!A211 -> Mass Grading | B12: ='Comparison to Previous'!K211 -> 876756 | C12: ='Comparison to Previous'!R211 -> 572075 | D12: =B12-C12 -> 304681
A13: ='Comparison to Previous'!A236 -> Entry Security Gates | B13: ='Comparison to Previous'!K236 -> 192000 | C13: ='Comparison to Previous'!R236 -> 100000 | D13: =B13-C13 -> 92000
A14: ='Comparison to Previous'!A246 -> Site Landscaping | B14: ='Comparison to Previous'!K246 -> 3662724.8 | C14: ='Comparison to Previous'!R246 -> 2289198.3 | D14: =B14-C14 -> 1373526.4
A15: ='Comparison to Previous'!A250 -> Offsite Paving | B15: ='Comparison to Previous'!K250 -> 795028.78 | C15: ='Level 3'!H252 -> 1006389.8 | D15: =B15-C15 -> -211361.02
A16: ='Comparison to Previous'!A267 -> Off Site Water | B16: ='Comparison to Previous'!K267 -> 2362698.4 | C16: ='Comparison to Previous'!R267 -> 1635293.3 | D16: =B16-C16 -> 727405.11
A17: ='Comparison to Previous'!A268 -> Off Site Sewer | B17: ='Comparison to Previous'!K268 -> 1073770.8 | C17: ='Comparison to Previous'!R268 -> 436684.18 | D17: =B17-C17 -> 637086.67
A18: ='Comparison to Previous'!A274 -> Solar PV System | B18: ='Comparison to Previous'!K274 -> 399750 | C18: ='Comparison to Previous'!R274 -> 1567975.9 | D18: =B18-C18 -> -1168225.9
A19: ='Comparison to Previous'!A289 -> Bid Risk | B19: ='Comparison to Previous'!K289 -> 1254667.1 | C19: ='Comparison to Previous'!R289 -> 632953.91 | D19: =B19-C19 -> 621713.23
D20: =B20-C20 -> 0
A21: Total | D21: =SUM(D3:D20) -> 1735180.3

Sheet Comparison to Previous
A1: WEST HENDERSON | C1: Level 1 | F1: Level 1 (New Site Plan) A | K1: Level 2 | R1: Level 3
C3: Details | F3: Details | H3: Change | I3: % | K3: Details | R3: Details | T3: Change | U3: %
C4: Buildings | D4: 5 | F4: Buildings | G4: 4 | H4: =D4-G4 -> 1 | I4: =H4/D4 -> 0.2 | K4: Buildings | L4: 4 | R4: Buildings | S4: 4 | T4: =L4-S4 -> 0 | U4: =T4/L4 -> 0
C5: Bldg. SF | D5: 431911 | F5: Bldg. SF | G5: ='Level 1.1 UPDATE A'!B8 -> 426549 | H5: =D5-G5 -> 5362 | I5: =H5/D5 -> 0.012414595 | K5: Bldg. SF | L5: ='Level 1.1 UPDATE B'!B8 -> 426549 | R5: Bldg. SF | S5: ='Level 3'!B8 -> 422635 | T5: =L5-S5 -> 3914 | U5: =T5/L5 -> 0.0091759681
C6: Unit Count | D6: ='Level 1'!$E$8 -> 390 | F6: Unit Count | G6: ='Level 1'!$E$8 -> 390 | H6: =D6-G6 -> 0 | I6: =H6/D6 -> 0 | K6: Unit Count | L6: ='Level 1'!$E$8 -> 390 | R6: Unit Count | S6: ='Level 3'!J8 -> 390 | T6: =L6-S6 -> 0 | U6: =T6/L6 -> 0
C8: TOTAL COST | D8: =D317 -> 84590981 | F8: TOTAL COST | G8: =G317 -> 82551538 | H8: =D8-G8 -> 2039443 | I8: =H8/D8 -> 0.024109461 | K8: TOTAL COST | L8: =L317 -> 79847909 | R8: TOTAL COST | S8: =S317 -> 77376748 | T8: =L8-S8 -> 2471161.1 | U8: =T8/L8 -> 0.030948351
C9: PER GSF | D9: =D8/D5 -> 195.85281 | F9: PER GSF | G9: =G8/G5 -> 193.53354 | H9: =D9-G9 -> 2.3192652 | I9: =H9/D9 -> 0.011841879 | K9: PER GSF | L9: =L8/L5 -> 187.19516 | R9: PER GSF | S9: =S8/S5 -> 183.08173 | T9: =L9-S9 -> 4.1134294 | U9: =T9/L9 -> 0.021974016
C10: PER UNIT | D10: =D8/D6 -> 216899.95 | F10: PER UNIT | G10: =G8/G6 -> 211670.61 | H10: =D10-G10 -> 5229.341 | I10: =H10/D10 -> 0.024109461 | K10: PER UNIT | L10: =L8/L6 -> 204738.23 | R10: PER UNIT | S10: =S8/S6 -> 198401.92 | T10: =L10-S10 -> 6336.3105 | U10: =T10/L10 -> 0.030948351
H13: Conditions | I13: Conditions | N13: Conditions | P13: Conditions | T13: Conditions | U13: Conditions
H14: 50000 | I14: 0.05 | N14: 50000 | P14: 0.05 | T14: 50000 | U14: 0.05
A15: Description | C15: Sub Total | D15: Total | F15: Sub Total | G15: Total | H15: PV$ | I15: PV% | K15: Sub Total | L15: Total | N15: PV$ | P15: PV% | R15: Sub Total | S15: Total | T15: PV$ | U15: PV%
A16: General Requirements | C16: ='Level 1'!K21 -> 4240149 | F16: =VLOOKUP(A16,'Level 1.1 UPDATE A'!$A$21:$K$292,11,FALSE) -> 4080000 | H16: =C16-F16 -> 160149 | I16: =IF(D16=0,0,H16/D16) -> 0 | K16: =VLOOKUP(A16,'Level 2 - Transmitted (2)'!$A$21:$K$335,11,FALSE) -> 3849810.3 | N16: =C16-K16 -> 390338.7 | P16: =IF(D16=0,0,N16/D16) -> 0 | R16: =VLOOKUP(A16,'Level 3'!$A$20:$K$319,11,FALSE) -> 3857213.7 | T16: =K16-R16 -> -7403.3925 | U16: =IF(K16=0,0,T16/K16) -> -0.0019230539
A17: General Requirements | D17: ='Level 1'!L20 -> 4240149 | G17: =VLOOKUP(A17,'Level 1.1 UPDATE A'!$A$20:$L$330,12,FALSE) -> 4080000 | H17: =D17-G17 -> 160149 | I17: =IF(D17=0,0,H17/D17) -> 0.037769663 | L17: =K16 -> 3849810.3 | N17: =D17-L17 -> 390338.7 | P17: =IF(D17=0,0,N17/D17) -> 0.092057778 | S17: =VLOOKUP(A17,'Level 3'!$A$21:$L$320,12,FALSE) -> 3857213.7 | T17: =L17-S17 -> -7403.3925 | U17: =IF(K17=0,0,T17/K17) -> 0
A18: Potholing | C18: ='Level 1'!K23 -> 12000 | F18: =VLOOKUP(A18,'Level 1.1 UPDATE A'!$A$21:$K$292,11,FALSE) -> 12000 | H18: =C18-F18 -> 0 | I18: =IF(D18=0,0,H18/D18) -> 0 | K18: =VLOOKUP(A18,'Level 2 - Transmitted (2)'!$A$20:$K$335,11,FALSE) -> 12000 | N18: =C18-K18 -> 0 | P18: =IF(D18=0,0,N18/D18) -> 0 | R18: =VLOOKUP(A18,'Level 3'!$A$20:$K$319,11,FALSE) -> 12000 | T18: =K18-R18 -> 0 | U18: =IF(K18=0,0,T18/K18) -> 0
A19: Existing Conditions | D19: ='Level 1'!L22 -> 12000 | G19: =VLOOKUP(A19,'Level 1.1 UPDATE A'!$A$20:$L$330,12,FALSE) -> 12000 | H19: =D19-G19 -> 0 | I19: =IF(D19=0,0,H19/D19) -> 0 | L19: =K18 -> 12000 | N19: =D19-L19 -> 0 | P19: =IF(D19=0,0,N19/D19) -> 0 | S19: =VLOOKUP(A19,'Level 3'!$A$21:$L$320,12,FALSE) -> 12000 | T19: =L19-S19 -> 0 | U19: =IF(K19=0,0,T19/K19) -> 0
A20: Slabs | C20: ='Level 1'!K25 -> 2063622.9 | F20: =VLOOKUP(A20,'Level 1.1 UPDATE A'!$A$21:$K$292,11,FALSE) -> 1795622.4 | H20: =C20-F20 -> 268000.48 | I20: =IF(D20=0,0,H20/D20) -> 0 | K20: =VLOOKUP(A20,'Level 2 - Transmitted (2)'!$A$20:$K$335,11,FALSE) -> 1672098.3 | N20: =C20-K20 -> 391524.6 | P20: =IF(D20=0,0,N20/D20) -> 0 | R20: =VLOOKUP(A20,'Level 3'!$A$20:$K$319,11,FALSE) -> 1381298.6 | T20: =K20-R20 -> 290799.7 | U20: =IF(K20=0,0,T20/K20) -> 0.17391304
A21: Deepened Footings | C21: ='Level 1'!K26 -> 0 | F21: =VLOOKUP(A21,'Level 1.1 UPDATE A'!$A$21:$K$292,11,FALSE) -> 0 | H21: =C21-F21 -> 0 | I21: =IF(D21=0,0,H21/D21) -> 0 | K21: =VLOOKUP(A21,'Level 2 - Transmitted (2)'!$A$20:$K$335,11,FALSE) -> 0 | N21: =C21-K21 -> 0 | P21: =IF(D21=0,0,N21/D21) -> 0 | R21: =VLOOKUP(A21,'Level 3'!$A$20:$K$319,11,FALSE) -> 0 | T21: =K21-R21 -> 0 | U21: =IF(K21=0,0,T21/K21) -> 0
A22: Concrete Slab Repairs | C22: ='Level 1'!K27 -> 7500 | F22: =VLOOKUP(A22,'Level 1.1 UPDATE A'!$A$21:$K$292,11,FALSE) -> 7500 | H22: =C22-F22 -> 0 | I22: =IF(D22=0,0,H22/D22) -> 0 | K22: =VLOOKUP(A22,'Level 2 - Transmitted (2)'!$A$20:$K$335,11,FALSE) -> 7500 | N22: =C22-K22 -> 0 | P22: =IF(D22=0,0,N22/D22) -> 0 | R22: =VLOOKUP(A22,'Level 3'!$A$20:$K$319,11,FALSE) -> 7500 | T22: =K22-R22 -> 0 | U22: =IF(K22=0,0,T22/K22) -> 0
A23: Pump House Concrete | C23: ='Level 1'!K28 -> 3597 | F23: =VLOOKUP(A23,'Level 1.1 UPDATE A'!$A$21:$K$292,11,FALSE) -> 3597 | H23: =C23-F23 -> 0 | I23: =IF(D23=0,0,H23/D23) -> 0 | K23: =VLOOKUP(A23,'Level 2 - Transmitted (2)'!$A$20:$K$335,11,FALSE) -> 10000 | N23: =C23-K23 -> -6403 | P23: =IF(D23=0,0,N23/D23) -> 0 | R23: =VLOOKUP(A23,'Level 3'!$A$20:$K$319,11,FALSE) -> 10000 | T23: =K23-R23 -> 0 | U23: =IF(K23=0,0,T23/K23) -> 0
A24: Trash Enclosure Concrete | C24: ='Level 1'!K29 -> 38608.5 | F24: =VLOOKUP(A24,'Level 1.1 UPDATE A'!$A$21:$K$292,11,FALSE) -> 38608.5 | H24: =C24-F24 -> 0 | I24: =IF(D24=0,0,H24/D24) -> 0 | K24: =VLOOKUP(A24,'Level 2 - Transmitted (2)'!$A$20:$K$335,11,FALSE) -> 77000 | N24: =C24-K24 -> -38391.5 | P24: =IF(D24=0,0,N24/D24) -> 0 | R24: =VLOOKUP(A24,'Level 3'!$A$20:$K$319,11,FALSE) -> 77000 | T24: =K24-R24 -> 0 | U24: =IF(K24=0,0,T24/K24) -> 0
A25: Pool Area Shower Concrete | C25: ='Level 1'!K30 -> 2500 | F25: =VLOOKUP(A25,'Level 1.1 UPDATE A'!$A$21:$K$292,11,FALSE) -> 2500 | H25: =C25-F25 -> 0 | I25: =IF(D25=0,0,H25/D25) -> 0 | K25: =VLOOKUP(A25,'Level 2 - Transmitted (2)'!$A$20:$K$335,11,FALSE) -> 2500 | N25: =C25-K25 -> 0 | P25: =IF(D25=0,0,N25/D25) -> 0 | R25: =VLOOKUP(A25,'Level 3'!$A$20:$K$319,11,FALSE) -> 2500 | T25: =K25-R25 -> 0 | U25: =IF(K25=0,0,T25/K25) -> 0
A26: Cabana Concrete | C26: ='Level 1'!K31 -> 0 | F26: =VLOOKUP(A26,'Level 1.1 UPDATE A'!$A$21:$K$292,11,FALSE) -> 0 | H26: =C26-F26 -> 0 | I26: =IF(D26=0,0,H26/D26) -> 0 | K26: =VLOOKUP(A26,'Level 2 - Transmitted (2)'!$A$20:$K$335,11,FALSE) -> 23500 | N26: =C26-K26 -> -23500 | P26: =IF(D26=0,0,N26/D26) -> 0 | R26: =VLOOKUP(A26,'Level 3'!$A$20:$K$319,11,FALSE) -> 35000 | T26: =K26-R26 -> -11500 | U26: =IF(K26=0,0,T26/K26) -> -0.4893617
A27: Pool Equipment Foundation | C27: ='Level 1'!K32 -> 0 | F27: =VLOOKUP(A27,'Level 1.1 UPDATE A'!$A$21:$K$292,11,FALSE) -> 0 | H27: =C27-F27 -> 0 | I27: =IF(D27=0,0,H27/D27) -> 0 | K27: =VLOOKUP(A27,'Level 2 - Transmitted (2)'!$A$20:$K$335,11,FALSE) -> 4000 | N27: =C27-K27 -> -4000 | P27: =IF(D27=0,0,N27/D27) -> 0 | R27: =VLOOKUP(A27,'Level 3'!$A$20:$K$319,11,FALSE) -> 7500 | T27: =K27-R27 -> -3500 | U27: =IF(K27=0,0,T27/K27) -> -0.875
A28: Lightweight Concrete | C28: ='Level 1'!K33 -> 754201.14 | F28: =VLOOKUP(A28,'Level 1.1 UPDATE A'!$A$21:$K$292,11,FALSE) -> 769430.34 | H28: =C28-F28 -> -15229.2 | I28: =IF(D28=0,0,H28/D28) -> 0 | K28: =VLOOKUP(A28,'Level 2 - Transmitted (2)'!$A$20:$K$335,11,FALSE) -> 679394.69 | N28: =C28-K28 -> 74806.45 | P28: =IF(D28=0,0,N28/D28) -> 0 | R28: =VLOOKUP(A28,'Level 3'!$A$20:$K$319,11,FALSE) -> 679394.69 | T28: =K28-R28 -> 0 | U28: =IF(K28=0,0,T28/K28) -> 0
A29: Deck Concrete | C29: ='Level 1'!K34 -> 64575.68 | F29: =VLOOKUP(A29,'Level 1.1 UPDATE A'!$A$21:$K$292,11,FALSE) -> 64575.68 | H29: =C29-F29 -> 0 | I29: =IF(D29=0,0,H29/D29) -> 0 | K29: =VLOOKUP(A29,'Level 2 - Transmitted (2)'!$A$20:$K$335,11,FALSE) -> 70606.233 | N29: =C29-K29 -> -6030.5531 | P29: =IF(D29=0,0,N29/D29) -> 0 | R29: =VLOOKUP(A29,'Level 3'!$A$20:$K$319,11,FALSE) -> 70606.233 | T29: =K29-R29 -> 0 | U29: =IF(K29=0,0,T29/K29) -> 0
A30: Concrete | D30: ='Level 1'!L24 -> 2934605.2 | G30: =VLOOKUP(A30,'Level 1.1 UPDATE A'!$A$20:$L$330,12,FALSE) -> 2681833.9 | H30: =D30-G30 -> 252771.28 | I30: =IF(D30=0,0,H30/D30) -> 0.08613468 | L30: =VLOOKUP(A30,'Level 2 - Transmitted (2)'!$A$21:$L$335,12,FALSE) -> 2546599.2 | N30: =D30-L30 -> 388006 | P30: =IF(D30=0,0,N30/D30) -> 0.13221745 | S30: =VLOOKUP(A30,'Level 3'!$A$21:$L$320,12,FALSE) -> 2270799.5 | T30: =L30-S30 -> 275799.7 | U30: =IF(L30=0,0,T30/L30) -> 0.10830118
A31: Elevator Shaft | C31: ='Level 1'!K45 -> 152000 | F31: =VLOOKUP(A31,'Level 1.1 UPDATE A'!$A$21:$K$292,11,FALSE) -> 114000 | H31: =C31-F31 -> 38000 | I31: =IF(D31=0,0,H31/D31) -> 0 | K31: =VLOOKUP(A31,'Level 2 - Transmitted (2)'!$A$20:$K$335,11,FALSE) -> 129600 | N31: =C31-K31 -> 22400 | P31: =IF(D31=0,0,N31/D31) -> 0 | R31: =VLOOKUP(A31,'Level 3'!$A$20:$K$319,11,FALSE) -> 168000 | T31: =K31-R31 -> -38400 | U31: =IF(K31=0,0,T31/K31) -> -0.2962963
A32: Trash Enclosure | C32: ='Level 1'!K46 -> 79800 | F32: =VLOOKUP(A32,'Level 1.1 UPDATE A'!$A$21:$K$292,11,FALSE) -> 79800 | H32: =C32-F32 -> 0 | I32: =IF(D32=0,0,H32/D32) -> 0 | K32: =VLOOKUP(A32,'Level 2 - Transmitted (2)'!$A$20:$K$335,11,FALSE) -> 91000 | N32: =C32-K32 -> -11200 | P32: =IF(D32=0,0,N32/D32) -> 0 | R32: =VLOOKUP(A32,'Level 3'!$A$20:$K$319,11,FALSE) -> 91000 | T32: =K32-R32 -> 0 | U32: =IF(K32=0,0,T32/K32) -> 0
A33: Masonry Veneer | C33: ='Level 1'!K47 -> 0 | F33: =VLOOKUP(A33,'Level 1.1 UPDATE A'!$A$21:$K$292,11,FALSE) -> 0 | H33: =C33-F33 -> 0 | I33: =IF(D33=0,0,H33/D33) -> 0 | K33: =VLOOKUP(A33,'Level 2 - Transmitted (2)'!$A$20:$K$335,11,FALSE) -> 0 | N33: =C33-K33 -> 0 | P33: =IF(D33=0,0,N33/D33) -> 0 | R33: =VLOOKUP(A33,'Level 3'!$A$20:$K$319,11,FALSE) -> 0 | T33: =K33-R33 -> 0 | U33: =IF(K33=0,0,T33/K33) -> 0
A34: Masonry Veneer Pool Area | C34: ='Level 1'!K48 -> 6000 | F34: =VLOOKUP(A34,'Level 1.1 UPDATE A'!$A$21:$K$292,11,FALSE) -> 6000 | H34: =C34-F34 -> 0 | I34: =IF(D34=0,0,H34/D34) -> 0 | K34: =VLOOKUP(A34,'Level 2 - Transmitted (2)'!$A$20:$K$335,11,FALSE) -> 40000 | N34: =C34-K34 -> -34000 | P34: =IF(D34=0,0,N34/D34) -> 0 | R34: =VLOOKUP(A34,'Level 3'!$A$20:$K$319,11,FALSE) -> 40000 | T34: =K34-R34 -> 0 | U34: =IF(K34=0,0,T34/K34) -> 0
A35: Pool Eq. Shower Stone | C35: ='Level 1'!K49 -> 9000 | F35: =VLOOKUP(A35,'Level 1.1 UPDATE A'!$A$21:$K$292,11,FALSE) -> 9000 | H35: =C35-F35 -> 0 | I35: =IF(D35=0,0,H35/D35) -> 0 | K35: =VLOOKUP(A35,'Level 2 - Transmitted (2)'!$A$20:$K$335,11,FALSE) -> 15000 | N35: =C35-K35 -> -6000 | P35: =IF(D35=0,0,N35/D35) -> 0 | R35: =VLOOKUP(A35,'Level 3'!$A$20:$K$319,11,FALSE) -> 15000 | T35: =K35-R35 -> 0 | U35: =IF(K35=0,0,T35/K35) -> 0
A36: Masonry | D36: ='Level 1'!L44 -> 246800 | G36: =VLOOKUP(A36,'Level 1.1 UPDATE A'!$A$20:$L$330,12,FALSE) -> 208800 | H36: =D36-G36 -> 38000 | I36: =IF(D36=0,0,H36/D36) -> 0.15397083 | L36: =VLOOKUP(A36,'Level 2 - Transmitted (2)'!$A$21:$L$335,12,FALSE) -> 275600 | N36: =D36-L36 -> -28800 | P36: =IF(D36=0,0,N36/D36) -> -0.11669368 | S36: =VLOOKUP(A36,'Level 3'!$A$21:$L$320,12,FALSE) -> 314000 | T36: =L36-S36 -> -38400 | U36: =IF(L36=0,0,T36/L36) -> -0.13933237
A37: Structural Steel | C37: ='Level 1'!K51 -> 125000 | F37: =VLOOKUP(A37,'Level 1.1 UPDATE A'!$A$21:$K$292,11,FALSE) -> 125000 | H37: =C37-F37 -> 0 | I37: =IF(D37=0,0,H37/D37) -> 0 | K37: =VLOOKUP(A37,'Level 2 - Transmitted (2)'!$A$20:$K$335,11,FALSE) -> 240254.58 | N37: =C37-K37 -> -115254.58 | P37: =IF(D37=0,0,N37/D37) -> 0 | R37: =VLOOKUP(A37,'Level 3'!$A$20:$K$319,11,FALSE) -> 298082.6 | T37: =K37-R37 -> -57828.024 | U37: =IF(K37=0,0,T37/K37) -> -0.24069479
A38: Elevator Shaft Iron | C38: ='Level 1'!K52 -> 24240 | F38: =VLOOKUP(A38,'Level 1.1 UPDATE A'!$A$21:$K$292,11,FALSE) -> 16160 | H38: =C38-F38 -> 8080 | I38: =IF(D38=0,0,H38/D38) -> 0 | K38: =VLOOKUP(A38,'Level 2 - Transmitted (2)'!$A$20:$K$335,11,FALSE) -> 16400 | N38: =C38-K38 -> 7840 | P38: =IF(D38=0,0,N38/D38) -> 0 | R38: =VLOOKUP(A38,'Level 3'!$A$20:$K$319,11,FALSE) -> 16400 | T38: =K38-R38 -> 0 | U38: =IF(K38=0,0,T38/K38) -> 0
A39: Stair Handrails | C39: ='Level 1'!K53 -> 120000 | F39: =VLOOKUP(A39,'Level 1.1 UPDATE A'!$A$21:$K$292,11,FALSE) -> 88000 | H39: =C39-F39 -> 32000 | I39: =IF(D39=0,0,H39/D39) -> 0 | K39: =VLOOKUP(A39,'Level 2 - Transmitted (2)'!$A$20:$K$335,11,FALSE) -> 67500 | N39: =C39-K39 -> 52500 | P39: =IF(D39=0,0,N39/D39) -> 0 | R39: =VLOOKUP(A39,'Level 3'!$A$20:$K$319,11,FALSE) -> 94000 | T39: =K39-R39 -> -26500 | U39: =IF(K39=0,0,T39/K39) -> -0.39259259
A40: Garage Stair Railings | C40: ='Level 1'!K54 -> 0 | F40: =VLOOKUP(A40,'Level 1.1 UPDATE A'!$A$21:$K$292,11,FALSE) -> 0 | H40: =C40-F40 -> 0 | I40: =IF(D40=0,0,H40/D40) -> 0 | K40: =VLOOKUP(A40,'Level 2 - Transmitted (2)'!$A$20:$K$335,11,FALSE) -> 0 | N40: =C40-K40 -> 0 | P40: =IF(D40=0,0,N40/D40) -> 0 | R40: =VLOOKUP(A40,'Level 3'!$A$20:$K$319,11,FALSE) -> 0 | T40: =K40-R40 -> 0 | U40: =IF(K40=0,0,T40/K40) -> 0
A41: Shower Cover | K41: 0 | N41: =C41-K41 -> 0 | P41: =IF(D41=0,0,N41/D41) -> 0 | R41: =VLOOKUP(A41,'Level 3'!$A$20:$K$319,11,FALSE) -> 6000 | T41: =K41-R41 -> -6000 | U41: =IF(K41=0,0,T41/K41) -> 0
A42: Cabana Iron | C42: ='Level 1'!K55 -> 0 | F42: =VLOOKUP(A42,'Level 1.1 UPDATE A'!$A$21:$K$292,11,FALSE) -> 0 | H42: =C42-F42 -> 0 | I42: =IF(D42=0,0,H42/D42) -> 0 | K42: =VLOOKUP(A42,'Level 2 - Transmitted (2)'!$A$20:$K$335,11,FALSE) -> 0 | N42: =C42-K42 -> 0 | P42: =IF(D42=0,0,N42/D42) -> 0 | R42: =VLOOKUP(A42,'Level 3'!$A$20:$K$319,11,FALSE) -> 0 | T42: =K42-R42 -> 0 | U42: =IF(K42=0,0,T42/K42) -> 0
A43: Pool Equipment Gate | C43: ='Level 1'!K56 -> 1950 | F43: =VLOOKUP(A43,'Level 1.1 UPDATE A'!$A$21:$K$292,11,FALSE) -> 1950 | H43: =C43-F43 -> 0 | I43: =IF(D43=0,0,H43/D43) -> 0 | K43: =VLOOKUP(A43,'Level 2 - Transmitted (2)'!$A$20:$K$335,11,FALSE) -> 2000 | N43: =C43-K43 -> -50 | P43: =IF(D43=0,0,N43/D43) -> 0 | R43: =VLOOKUP(A43,'Level 3'!$A$20:$K$319,11,FALSE) -> 2000 | T43: =K43-R43 -> 0 | U43: =IF(K43=0,0,T43/K43) -> 0
A44: Iron Railings | C44: ='Level 1'!K57 -> 250976 | F44: =VLOOKUP(A44,'Level 1.1 UPDATE A'!$A$21:$K$292,11,FALSE) -> 269744 | H44: =C44-F44 -> -18768 | I44: =IF(D44=0,0,H44/D44) -> 0 | K44: =VLOOKUP(A44,'Level 2 - Transmitted (2)'!$A$20:$K$335,11,FALSE) -> 282872.4 | N44: =C44-K44 -> -31896.4 | P44: =IF(D44=0,0,N44/D44) -> 0 | R44: =VLOOKUP(A44,'Level 3'!$A$20:$K$319,11,FALSE) -> 300204 | T44: =K44-R44 -> -17331.6 | U44: =IF(K44=0,0,T44/K44) -> -0.061270028
A45: Cable Railings | C45: ='Level 1'!K58 -> 0 | F45: =VLOOKUP(A45,'Level 1.1 UPDATE A'!$A$21:$K$292,11,FALSE) -> 0 | H45: =C45-F45 -> 0 | I45: =IF(D45=0,0,H45/D45) -> 0 | K45: =VLOOKUP(A45,'Level 2 - Transmitted (2)'!$A$20:$K$335,11,FALSE) -> 0 | N45: =C45-K45 -> 0 | P45: =IF(D45=0,0,N45/D45) -> 0 | R45: =VLOOKUP(A45,'Level 3'!$A$20:$K$319,11,FALSE) -> 0 | T45: =K45-R45 -> 0 | U45: =IF(K45=0,0,T45/K45) -> 0
A46: Metals | D46: ='Level 1'!L50 -> 522166 | G46: =VLOOKUP(A46,'Level 1.1 UPDATE A'!$A$20:$L$330,12,FALSE) -> 500854 | H46: =D46-G46 -> 21312 | I46: =IF(D46=0,0,H46/D46) -> 0.040814607 | L46: =VLOOKUP(A46,'Level 2 - Transmitted (2)'!$A$21:$L$335,12,FALSE) -> 609026.98 | N46: =D46-L46 -> -86860.976 | P46: =IF(D46=0,0,N46/D46) -> -0.16634744 | S46: =VLOOKUP(A46,'Level 3'!$A$21:$L$320,12,FALSE) -> 716686.6 | T46: =L46-S46 -> -107659.62 | U46: =IF(L46=0,0,T46/L46) -> -0.17677316
A47: Dumpsters | C47: ='Level 1'!K60 -> 0 | F47: =VLOOKUP(A47,'Level 1.1 UPDATE A'!$A$21:$K$292,11,FALSE) -> 0 | H47: =C47-F47 -> 0 | I47: =IF(D47=0,0,H47/D47) -> 0 | K47: =VLOOKUP(A47,'Level 2 - Transmitted (2)'!$A$20:$K$335,11,FALSE) -> 0 | N47: =C47-K47 -> 0 | P47: =IF(D47=0,0,N47/D47) -> 0 | R47: =VLOOKUP(A47,'Level 3'!$A$20:$K$319,11,FALSE) -> 0 | T47: =K47-R47 -> 0 | U47: =IF(K47=0,0,T47/K47) -> 0
A48: Framing | C48: ='Level 1'!K61 -> 9052854.6 | F48: =VLOOKUP(A48,'Level 1.1 UPDATE A'!$A$21:$K$292,11,FALSE) -> 8940467 | H48: =C48-F48 -> 112387.52 | I48: =IF(D48=0,0,H48/D48) -> 0 | K48: =VLOOKUP(A48,'Level 2 - Transmitted (2)'!$A$20:$K$335,11,FALSE) -> 7607430 | N48: =C48-K48 -> 1445424.6 | P48: =IF(D48=0,0,N48/D48) -> 0 | R48: =VLOOKUP(A48,'Level 3'!$A$20:$K$319,11,FALSE) -> 7487665.3 | T48: =K48-R48 -> 119764.67 | U48: =IF(K48=0,0,T48/K48) -> 0.015743118 | V48: Updated to proposals average
A49: Framing - Crane | C49: ='Level 1'!K62 -> 0 | F49: =VLOOKUP(A49,'Level 1.1 UPDATE A'!$A$21:$K$292,11,FALSE) -> 0 | H49: =C49-F49 -> 0 | I49: =IF(D49=0,0,H49/D49) -> 0 | K49: =VLOOKUP(A49,'Level 2 - Transmitted (2)'!$A$20:$K$335,11,FALSE) -> 0 | N49: =C49-K49 -> 0 | P49: =IF(D49=0,0,N49/D49) -> 0 | R49: =VLOOKUP(A49,'Level 3'!$A$20:$K$319,11,FALSE) -> 0 | T49: =K49-R49 -> 0 | U49: =IF(K49=0,0,T49/K49) -> 0
A50: Cabana Framing | C50: ='Level 1'!K63 -> 0 | F50: =VLOOKUP(A50,'Level 1.1 UPDATE A'!$A$21:$K$292,11,FALSE) -> 0 | H50: =C50-F50 -> 0 | I50: =IF(D50=0,0,H50/D50) -> 0 | K50: =VLOOKUP(A50,'Level 2 - Transmitted (2)'!$A$20:$K$335,11,FALSE) -> 15000 | N50: =C50-K50 -> -15000 | P50: =IF(D50=0,0,N50/D50) -> 0 | R50: =VLOOKUP(A50,'Level 3'!$A$20:$K$319,11,FALSE) -> 15000 | T50: =K50-R50 -> 0 | U50: =IF(K50=0,0,T50/K50) -> 0
A51: BBQ Framing | C51: ='Level 1'!K64 -> 15000 | F51: =VLOOKUP(A51,'Level 1.1 UPDATE A'!$A$21:$K$292,11,FALSE) -> 10000 | H51: =C51-F51 -> 5000 | I51: =IF(D51=0,0,H51/D51) -> 0 | K51: =VLOOKUP(A51,'Level 2 - Transmitted (2)'!$A$20:$K$335,11,FALSE) -> 20000 | N51: =C51-K51 -> -5000 | P51: =IF(D51=0,0,N51/D51) -> 0 | R51: =VLOOKUP(A51,'Level 3'!$A$20:$K$319,11,FALSE) -> 20000 | T51: =K51-R51 -> 0 | U51: =IF(K51=0,0,T51/K51) -> 0
A52: Fireplace Framing | C52: ='Level 1'!K65 -> 0 | F52: =VLOOKUP(A52,'Level 1.1 UPDATE A'!$A$21:$K$292,11,FALSE) -> 0 | H52: =C52-F52 -> 0 | I52: =IF(D52=0,0,H52/D52) -> 0 | K52: =VLOOKUP(A52,'Level 2 - Transmitted (2)'!$A$20:$K$335,11,FALSE) -> 0 | N52: =C52-K52 -> 0 | P52: =IF(D52=0,0,N52/D52) -> 0 | R52: =VLOOKUP(A52,'Level 3'!$A$20:$K$319,11,FALSE) -> 0 | T52: =K52-R52 -> 0 | U52: =IF(K52=0,0,T52/K52) -> 0
A53: Trellis | C53: ='Level 1'!K66 -> 0 | F53: =VLOOKUP(A53,'Level 1.1 UPDATE A'!$A$21:$K$292,11,FALSE) -> 0 | H53: =C53-F53 -> 0 | I53: =IF(D53=0,0,H53/D53) -> 0 | K53: =VLOOKUP(A53,'Level 2 - Transmitted (2)'!$A$20:$K$335,11,FALSE) -> 0 | N53: =C53-K53 -> 0 | P53: =IF(D53=0,0,N53/D53) -> 0 | R53: =VLOOKUP(A53,'Level 3'!$A$20:$K$319,11,FALSE) -> 0 | T53: =K53-R53 -> 0 | U53: =IF(K53=0,0,T53/K53) -> 0
A54: Pool Equipment Framing | C54: ='Level 1'!K67 -> 0 | F54: =VLOOKUP(A54,'Level 1.1 UPDATE A'!$A$21:$K$292,11,FALSE) -> 0 | H54: =C54-F54 -> 0 | I54: =IF(D54=0,0,H54/D54) -> 0 | K54: =VLOOKUP(A54,'Level 2 - Transmitted (2)'!$A$20:$K$335,11,FALSE) -> 0 | N54: =C54-K54 -> 0 | P54: =IF(D54=0,0,N54/D54) -> 0 | R54: =VLOOKUP(A54,'Level 3'!$A$20:$K$319,11,FALSE) -> 0 | T54: =K54-R54 -> 0 | U54: =IF(K54=0,0,T54/K54) -> 0
A55: Finish Carpentry - Units | C55: ='Level 1'!K68 -> 1430266.6 | F55: =VLOOKUP(A55,'Level 1.1 UPDATE A'!$A$21:$K$292,11,FALSE) -> 1430266.6 | H55: =C55-F55 -> 0 | I55: =IF(D55=0,0,H55/D55) -> 0 | K55: =VLOOKUP(A55,'Level 2 - Transmitted (2)'!$A$20:$K$335,11,FALSE) -> 1170454 | N55: =C55-K55 -> 259812.64 | P55: =IF(D55=0,0,N55/D55) -> 0 | R55: =VLOOKUP(A55,'Level 3'!$A$20:$K$319,11,FALSE) -> 1171049.1 | T55: =K55-R55 -> -595.15 | U55: =IF(K55=0,0,T55/K55) -> -0.00050847791
A56: Finish Carpentry - Common | C56: ='Level 1'!K69 -> 315492.08 | F56: =VLOOKUP(A56,'Level 1.1 UPDATE A'!$A$21:$K$292,11,FALSE) -> 298513.43 | H56: =C56-F56 -> 16978.658 | I56: =IF(D56=0,0,H56/D56) -> 0 | K56: =VLOOKUP(A56,'Level 2 - Transmitted (2)'!$A$20:$K$335,11,FALSE) -> 502007 | N56: =C56-K56 -> -186514.92 | P56: =IF(D56=0,0,N56/D56) -> 0 | R56: =VLOOKUP(A56,'Level 3'!$A$20:$K$319,11,FALSE) -> 502007 | T56: =K56-R56 -> 0 | U56: =IF(K56=0,0,T56/K56) -> 0
A57: Finish Carpentry - Pump House | K57: 0 | R57: =VLOOKUP(A57,'Level 3'!$A$20:$K$319,11,FALSE) -> 2500 | T57: =K57-R57 -> -2500 | U57: =IF(K57=0,0,T57/K57) -> 0
A58: BBQ Trim | C58: ='Level 1'!K70 -> 7200 | F58: =VLOOKUP(A58,'Level 1.1 UPDATE A'!$A$21:$K$292,11,FALSE) -> 4800 | H58: =C58-F58 -> 2400 | I58: =IF(D58=0,0,H58/D58) -> 0 | K58: =VLOOKUP(A58,'Level 2 - Transmitted (2)'!$A$20:$K$335,11,FALSE) -> 9600 | N58: =C58-K58 -> -2400 | P58: =IF(D58=0,0,N58/D58) -> 0 | R58: =VLOOKUP(A58,'Level 3'!$A$20:$K$319,11,FALSE) -> 9600 | T58: =K58-R58 -> 0 | U58: =IF(K58=0,0,T58/K58) -> 0
A59: Shutters | C59: ='Level 1'!K71 -> 0 | F59: =VLOOKUP(A59,'Level 1.1 UPDATE A'!$A$21:$K$292,11,FALSE) -> 0 | H59: =C59-F59 -> 0 | I59: =IF(D59=0,0,H59/D59) -> 0 | K59: =VLOOKUP(A59,'Level 2 - Transmitted (2)'!$A$20:$K$335,11,FALSE) -> 0 | N59: =C59-K59 -> 0 | P59: =IF(D59=0,0,N59/D59) -> 0 | R59: =VLOOKUP(A59,'Level 3'!$A$20:$K$319,11,FALSE) -> 0 | T59: =K59-R59 -> 0 | U59: =IF(K59=0,0,T59/K59) -> 0
A60: Wood, Plastics, & Composites | D60: ='Level 1'!L59 -> 10820813 | G60: =VLOOKUP(A60,'Level 1.1 UPDATE A'!$A$20:$L$330,12,FALSE) -> 10684047 | H60: =D60-G60 -> 136766.18 | I60: =IF(D60=0,0,H60/D60) -> 0.012639177 | L60: =VLOOKUP(A60,'Level 2 - Transmitted (2)'!$A$21:$L$335,12,FALSE) -> 9324491 | N60: =D60-L60 -> 1496322.3 | P60: =IF(D60=0,0,N60/D60) -> 0.13828187 | S60: =VLOOKUP(A60,'Level 3'!$A$21:$L$320,12,FALSE) -> 9207821.5 | T60: =L60-S60 -> 116669.52 | U60: =IF(L60=0,0,T60/L60) -> 0.012512159
A61: Insulation | C61: ='Level 1'!K73 -> 1166159.7 | F61: =VLOOKUP(A61,'Level 1.1 UPDATE A'!$A$21:$K$292,11,FALSE) -> 1151682.3 | H61: =C61-F61 -> 14477.4 | I61: =IF(D61=0,0,H61/D61) -> 0 | K61: =VLOOKUP(A61,'Level 2 - Transmitted (2)'!$A$20:$K$335,11,FALSE) -> 1056587.5 | N61: =C61-K61 -> 109572.2 | P61: =IF(D61=0,0,N61/D61) -> 0 | R61: =VLOOKUP(A61,'Level 3'!$A$20:$K$319,11,FALSE) -> 1005655 | T61: =K61-R61 -> 50932.5 | U61: =IF(K61=0,0,T61/K61) -> 0.048204716
A62: Insulation - PH | K62: 0 | R62: =VLOOKUP(A62,'Level 3'!$A$20:$K$319,11,FALSE) -> 1070.7697 | T62: =K62-R62 -> -1070.7697 | U62: =IF(K62=0,0,T62/K62) -> 0
A63: Roofing | C63: ='Level 1'!K74 -> 1052524.4 | F63: =VLOOKUP(A63,'Level 1.1 UPDATE A'!$A$21:$K$292,11,FALSE) -> 903052.8 | H63: =C63-F63 -> 149471.64 | I63: =IF(D63=0,0,H63/D63) -> 0 | K63: =VLOOKUP(A63,'Level 2 - Transmitted (2)'!$A$20:$K$335,11,FALSE) -> 979716.27 | N63: =C63-K63 -> 72808.169 | P63: =IF(D63=0,0,N63/D63) -> 0 | R63: =VLOOKUP(A63,'Level 3'!$A$20:$K$319,11,FALSE) -> 992777.33 | T63: =K63-R63 -> -13061.062 | U63: =IF(K63=0,0,T63/K63) -> -0.013331474
A64: Roofing - PH | K64: 0 | R64: =VLOOKUP(A64,'Level 3'!$A$20:$K$319,11,FALSE) -> 7500 | T64: =K64-R64 -> -7500 | U64: =IF(K64=0,0,T64/K64) -> 0
A65: Cabana Roofing | C65: ='Level 1'!K75 -> 0 | F65: =VLOOKUP(A65,'Level 1.1 UPDATE A'!$A$21:$K$292,11,FALSE) -> 0 | H65: =C65-F65 -> 0 | I65: =IF(D65=0,0,H65/D65) -> 0 | K65: =VLOOKUP(A65,'Level 2 - Transmitted (2)'!$A$20:$K$335,11,FALSE) -> 5500 | N65: =C65-K65 -> -5500 | P65: =IF(D65=0,0,N65/D65) -> 0 | R65: =VLOOKUP(A65,'Level 3'!$A$20:$K$319,11,FALSE) -> 5500 | T65: =K65-R65 -> 0 | U65: =IF(K65=0,0,T65/K65) -> 0
A66: Pump House Roofing | C66: ='Level 1'!K76 -> 7500 | F66: =VLOOKUP(A66,'Level 1.1 UPDATE A'!$A$21:$K$292,11,FALSE) -> 7500 | H66: =C66-F66 -> 0 | I66: =IF(D66=0,0,H66/D66) -> 0 | K66: =VLOOKUP(A66,'Level 2 - Transmitted (2)'!$A$20:$K$335,11,FALSE) -> 9500 | N66: =C66-K66 -> -2000 | P66: =IF(D66=0,0,N66/D66) -> 0 | R66: =VLOOKUP(A66,'Level 3'!$A$20:$K$319,11,FALSE) -> 9500 | T66: =K66-R66 -> 0 | U66: =IF(K66=0,0,T66/K66) -> 0
A67: Pool Equipment Roofing | C67: ='Level 1'!K77 -> 9000 | F67: =VLOOKUP(A67,'Level 1.1 UPDATE A'!$A$21:$K$292,11,FALSE) -> 9000 | H67: =C67-F67 -> 0 | I67: =IF(D67=0,0,H67/D67) -> 0 | K67: =VLOOKUP(A67,'Level 2 - Transmitted (2)'!$A$20:$K$335,11,FALSE) -> 0 | N67: =C67-K67 -> 9000 | P67: =IF(D67=0,0,N67/D67) -> 0 | R67: =VLOOKUP(A67,'Level 3'!$A$20:$K$319,11,FALSE) -> 0 | T67: =K67-R67 -> 0 | U67: =IF(K67=0,0,T67/K67) -> 0
A68: Trash Enclosure Cover | C68: ='Level 1'!K78 -> 97440 | F68: =VLOOKUP(A68,'Level 1.1 UPDATE A'!$A$21:$K$292,11,FALSE) -> 97440 | H68: =C68-F68 -> 0 | I68: =IF(D68=0,0,H68/D68) -> 0 | K68: =VLOOKUP(A68,'Level 2 - Transmitted (2)'!$A$20:$K$335,11,FALSE) -> 91000 | N68: =C68-K68 -> 6440 | P68: =IF(D68=0,0,N68/D68) -> 0 | R68: =VLOOKUP(A68,'Level 3'!$A$20:$K$319,11,FALSE) -> 84000 | T68: =K68-R68 -> 7000 | U68: =IF(K68=0,0,T68/K68) -> 0.076923077
A69: Pigeon Proofing | C69: ='Level 1'!K79 -> 34552.88 | F69: =VLOOKUP(A69,'Level 1.1 UPDATE A'!$A$21:$K$292,11,FALSE) -> 34123.92 | H69: =C69-F69 -> 428.96 | I69: =IF(D69=0,0,H69/D69) -> 0 | K69: =VLOOKUP(A69,'Level 2 - Transmitted (2)'!$A$20:$K$335,11,FALSE) -> 25000 | N69: =C69-K69 -> 9552.88 | P69: =IF(D69=0,0,N69/D69) -> 0 | R69: =VLOOKUP(A69,'Level 3'!$A$20:$K$319,11,FALSE) -> 25000 | T69: =K69-R69 -> 0 | U69: =IF(K69=0,0,T69/K69) -> 0
A70: Gutters and Downspouts | C70: ='Level 1'!K80 -> 21595.55 | F70: =VLOOKUP(A70,'Level 1.1 UPDATE A'!$A$21:$K$292,11,FALSE) -> 21327.45 | H70: =C70-F70 -> 268.1 | I70: =IF(D70=0,0,H70/D70) -> 0 | K70: =VLOOKUP(A70,'Level 2 - Transmitted (2)'!$A$20:$K$335,11,FALSE) -> 25000 | N70: =C70-K70 -> -3404.45 | P70: =IF(D70=0,0,N70/D70) -> 0 | R70: =VLOOKUP(A70,'Level 3'!$A$20:$K$319,11,FALSE) -> 25000 | T70: =K70-R70 -> 0 | U70: =IF(K70=0,0,T70/K70) -> 0
A71: Roof Ladders | C71: ='Level 1'!K81 -> 15500 | F71: =VLOOKUP(A71,'Level 1.1 UPDATE A'!$A$21:$K$292,11,FALSE) -> 12400 | H71: =C71-F71 -> 3100 | I71: =IF(D71=0,0,H71/D71) -> 0 | K71: =VLOOKUP(A71,'Level 2 - Transmitted (2)'!$A$20:$K$335,11,FALSE) -> 17500 | N71: =C71-K71 -> -2000 | P71: =IF(D71=0,0,N71/D71) -> 0 | R71: =VLOOKUP(A71,'Level 3'!$A$20:$K$319,11,FALSE) -> 16000 | T71: =K71-R71 -> 1500 | U71: =IF(K71=0,0,T71/K71) -> 0.085714286
A72: Roof Access Doors | C72: ='Level 1'!K82 -> 25000 | F72: =VLOOKUP(A72,'Level 1.1 UPDATE A'!$A$21:$K$292,11,FALSE) -> 20000 | H72: =C72-F72 -> 5000 | I72: =IF(D72=0,0,H72/D72) -> 0 | K72: =VLOOKUP(A72,'Level 2 - Transmitted (2)'!$A$20:$K$335,11,FALSE) -> 27500 | N72: =C72-K72 -> -2500 | P72: =IF(D72=0,0,N72/D72) -> 0 | R72: =VLOOKUP(A72,'Level 3'!$A$20:$K$319,11,FALSE) -> 24000 | T72: =K72-R72 -> 3500 | U72: =IF(K72=0,0,T72/K72) -> 0.12727273
A73: Roof Winch | C73: ='Level 1'!K83 -> 0 | F73: =VLOOKUP(A73,'Level 1.1 UPDATE A'!$A$21:$K$292,11,FALSE) -> 0 | H73: =C73-F73 -> 0 | I73: =IF(D73=0,0,H73/D73) -> 0 | K73: =VLOOKUP(A73,'Level 2 - Transmitted (2)'!$A$20:$K$335,11,FALSE) -> 0 | N73: =C73-K73 -> 0 | P73: =IF(D73=0,0,N73/D73) -> 0 | R73: =VLOOKUP(A73,'Level 3'!$A$20:$K$319,11,FALSE) -> 0 | T73: =K73-R73 -> 0 | U73: =IF(K73=0,0,T73/K73) -> 0
A74: Thermal & Moisture Protection | D74: ='Level 1'!L72 -> 2429272.6 | G74: =VLOOKUP(A74,'Level 1.1 UPDATE A'!$A$20:$L$330,12,FALSE) -> 2256526.5 | H74: =D74-G74 -> 172746.1 | I74: =IF(D74=0,0,H74/D74) -> 0.071110217 | L74: =VLOOKUP(A74,'Level 2 - Transmitted (2)'!$A$21:$L$335,12,FALSE) -> 2237303.8 | N74: =D74-L74 -> 191968.8 | P74: =IF(D74=0,0,N74/D74) -> 0.079023161 | S74: =VLOOKUP(A74,'Level 3'!$A$21:$L$320,12,FALSE) -> 2196003.1 | T74: =L74-S74 -> 41300.668 | U74: =IF(L74=0,0,T74/L74) -> 0.018460018
A75: Dumpsters | C75: ='Level 1'!K85 -> 0 | F75: =VLOOKUP(A75,'Level 1.1 UPDATE A'!$A$21:$K$292,11,FALSE) -> 0 | H75: =C75-F75 -> 0 | I75: =IF(D75=0,0,H75/D75) -> 0 | K75: =VLOOKUP(A75,'Level 2 - Transmitted (2)'!$A$20:$K$335,11,FALSE) -> 0 | N75: =C75-K75 -> 0 | P75: =IF(D75=0,0,N75/D75) -> 0 | R75: =VLOOKUP(A75,'Level 3'!$A$20:$K$319,11,FALSE) -> 0 | T75: =K75-R75 -> 0 | U75: =IF(K75=0,0,T75/K75) -> 0
A76: Entry Doors | C76: ='Level 1'!K86 -> 0 | F76: =VLOOKUP(A76,'Level 1.1 UPDATE A'!$A$21:$K$292,11,FALSE) -> 0 | H76: =C76-F76 -> 0 | I76: =IF(D76=0,0,H76/D76) -> 0 | K76: =VLOOKUP(A76,'Level 2 - Transmitted (2)'!$A$20:$K$335,11,FALSE) -> 0 | N76: =C76-K76 -> 0 | P76: =IF(D76=0,0,N76/D76) -> 0 | R76: =VLOOKUP(A76,'Level 3'!$A$20:$K$319,11,FALSE) -> 0 | T76: =K76-R76 -> 0 | U76: =IF(K76=0,0,T76/K76) -> 0
A77: Common Doors | C77: ='Level 1'!K87 -> 0 | F77: =VLOOKUP(A77,'Level 1.1 UPDATE A'!$A$21:$K$292,11,FALSE) -> 0 | H77: =C77-F77 -> 0 | I77: =IF(D77=0,0,H77/D77) -> 0 | K77: =VLOOKUP(A77,'Level 2 - Transmitted (2)'!$A$20:$K$335,11,FALSE) -> 0 | N77: =C77-K77 -> 0 | P77: =IF(D77=0,0,N77/D77) -> 0 | R77: =VLOOKUP(A77,'Level 3'!$A$20:$K$319,11,FALSE) -> 0 | T77: =K77-R77 -> 0 | U77: =IF(K77=0,0,T77/K77) -> 0
A78: Pocket Doors - 3 Panel | C78: ='Level 1'!K88 -> 0 | F78: =VLOOKUP(A78,'Level 1.1 UPDATE A'!$A$21:$K$292,11,FALSE) -> 0 | H78: =C78-F78 -> 0 | I78: =IF(D78=0,0,H78/D78) -> 0 | K78: =VLOOKUP(A78,'Level 2 - Transmitted (2)'!$A$20:$K$335,11,FALSE) -> 0 | N78: =C78-K78 -> 0 | P78: =IF(D78=0,0,N78/D78) -> 0 | R78: =VLOOKUP(A78,'Level 3'!$A$20:$K$319,11,FALSE) -> 0 | T78: =K78-R78 -> 0 | U78: =IF(K78=0,0,T78/K78) -> 0
A79: Garage Doors | C79: ='Level 1'!K89 -> 0 | F79: =VLOOKUP(A79,'Level 1.1 UPDATE A'!$A$21:$K$292,11,FALSE) -> 0 | H79: =C79-F79 -> 0 | I79: =IF(D79=0,0,H79/D79) -> 0 | K79: =VLOOKUP(A79,'Level 2 - Transmitted (2)'!$A$20:$K$335,11,FALSE) -> 0 | N79: =C79-K79 -> 0 | P79: =IF(D79=0,0,N79/D79) -> 0 | R79: =VLOOKUP(A79,'Level 3'!$A$20:$K$319,11,FALSE) -> 0 | T79: =K79-R79 -> 0 | U79: =IF(K79=0,0,T79/K79) -> 0
A80: Windows and Sliding Glass Doors | C80: ='Level 1'!K90 -> 519315.79 | F80: =VLOOKUP(A80,'Level 1.1 UPDATE A'!$A$21:$K$292,11,FALSE) -> 519315.79 | H80: =C80-F80 -> 0 | I80: =IF(D80=0,0,H80/D80) -> 0 | K80: =VLOOKUP(A80,'Level 2 - Transmitted (2)'!$A$20:$K$335,11,FALSE) -> 573144 | N80: =C80-K80 -> -53828.211 | P80: =IF(D80=0,0,N80/D80) -> 0 | R80: =VLOOKUP(A80,'Level 3'!$A$20:$K$319,11,FALSE) -> 546000 | T80: =K80-R80 -> 27144 | U80: =IF(K80=0,0,T80/K80) -> 0.047359826
A81: Windows Repair and Replacement | C81: ='Level 1'!K91 -> 29250 | F81: =VLOOKUP(A81,'Level 1.1 UPDATE A'!$A$21:$K$292,11,FALSE) -> 29250 | H81: =C81-F81 -> 0 | I81: =IF(D81=0,0,H81/D81) -> 0 | K81: =VLOOKUP(A81,'Level 2 - Transmitted (2)'!$A$20:$K$335,11,FALSE) -> 19500 | N81: =C81-K81 -> 9750 | P81: =IF(D81=0,0,N81/D81) -> 0 | R81: =VLOOKUP(A81,'Level 3'!$A$20:$K$319,11,FALSE) -> 39000 | T81: =K81-R81 -> -19500 | U81: =IF(K81=0,0,T81/K81) -> -1
A82: Pool Equipment Windows | C82: ='Level 1'!K92 -> 0 | F82: =VLOOKUP(A82,'Level 1.1 UPDATE A'!$A$21:$K$292,11,FALSE) -> 0 | H82: =C82-F82 -> 0 | I82: =IF(D82=0,0,H82/D82) -> 0 | K82: =VLOOKUP(A82,'Level 2 - Transmitted (2)'!$A$20:$K$335,11,FALSE) -> 0 | N82: =C82-K82 -> 0 | P82: =IF(D82=0,0,N82/D82) -> 0 | R82: =VLOOKUP(A82,'Level 3'!$A$20:$K$319,11,FALSE) -> 0 | T82: =K82-R82 -> 0 | U82: =IF(K82=0,0,T82/K82) -> 0
A83: Pool Glass Walls | C83: ='Level 1'!K93 -> 0 | F83: =VLOOKUP(A83,'Level 1.1 UPDATE A'!$A$21:$K$292,11,FALSE) -> 0 | H83: =C83-F83 -> 0 | I83: =IF(D83=0,0,H83/D83) -> 0 | K83: =VLOOKUP(A83,'Level 2 - Transmitted (2)'!$A$20:$K$335,11,FALSE) -> 0 | N83: =C83-K83 -> 0 | P83: =IF(D83=0,0,N83/D83) -> 0 | R83: =VLOOKUP(A83,'Level 3'!$A$20:$K$319,11,FALSE) -> 0 | T83: =K83-R83 -> 0 | U83: =IF(K83=0,0,T83/K83) -> 0
A84: Fixed Glass | C84: ='Level 1'!K94 -> 0 | F84: =VLOOKUP(A84,'Level 1.1 UPDATE A'!$A$21:$K$292,11,FALSE) -> 0 | H84: =C84-F84 -> 0 | I84: =IF(D84=0,0,H84/D84) -> 0 | K84: =VLOOKUP(A84,'Level 2 - Transmitted (2)'!$A$20:$K$335,11,FALSE) -> 0 | N84: =C84-K84 -> 0 | P84: =IF(D84=0,0,N84/D84) -> 0 | R84: =VLOOKUP(A84,'Level 3'!$A$20:$K$319,11,FALSE) -> 0 | T84: =K84-R84 -> 0 | U84: =IF(K84=0,0,T84/K84) -> 0
A85: Mirrors - LED | C85: ='Level 1'!K95 -> 0 | F85: =VLOOKUP(A85,'Level 1.1 UPDATE A'!$A$21:$K$292,11,FALSE) -> 0 | H85: =C85-F85 -> 0 | I85: =IF(D85=0,0,H85/D85) -> 0 | K85: =VLOOKUP(A85,'Level 2 - Transmitted (2)'!$A$20:$K$335,11,FALSE) -> 0 | N85: =C85-K85 -> 0 | P85: =IF(D85=0,0,N85/D85) -> 0 | R85: =VLOOKUP(A85,'Level 3'!$A$20:$K$319,11,FALSE) -> 0 | T85: =K85-R85 -> 0 | U85: =IF(K85=0,0,T85/K85) -> 0
A86: Mirrors - LED Install | C86: ='Level 1'!K96 -> 0 | F86: =VLOOKUP(A86,'Level 1.1 UPDATE A'!$A$21:$K$292,11,FALSE) -> 0 | H86: =C86-F86 -> 0 | I86: =IF(D86=0,0,H86/D86) -> 0 | K86: =VLOOKUP(A86,'Level 2 - Transmitted (2)'!$A$20:$K$335,11,FALSE) -> 0 | N86: =C86-K86 -> 0 | P86: =IF(D86=0,0,N86/D86) -> 0 | R86: =VLOOKUP(A86,'Level 3'!$A$20:$K$319,11,FALSE) -> 0 | T86: =K86-R86 -> 0 | U86: =IF(K86=0,0,T86/K86) -> 0
... A89: Mirrors - Polished Edges (Restrooms) | C89: ='Level 1'!K99 -> 1000 | F89: =VLOOKUP(A89,'Level 1.1 UPDATE A'!$A$21:$K$292,11,FALSE) -> 1000 | H89: =C89-F89 -> 0 | I89: =IF(D89=0,0,H89/D89) -> 0 | K89: =VLOOKUP(A89,'Level 2 - Transmitted (2)'!$A$20:$K$335,11,FALSE) -> 1200 | N89: =C89-K89 -> -200 | P89: =IF(D89=0,0,N89/D89) -> 0 | R89: =VLOOKUP(A89,'Level 3'!$A$20:$K$319,11,FALSE) -> 2000 | T89: =K89-R89 -> -800 | U89: =IF(K89=0,0,T89/K89) -> -0.66666667
A90: Openings | D90: ='Level 1'!L84 -> 639799.79 | G90: =VLOOKUP(A90,'Level 1.1 UPDATE A'!$A$20:$L$330,12,FALSE) -> 639151.79 | H90: =D90-G90 -> 648 | I90: =IF(D90=0,0,H90/D90) -> 0.0010128168 | L90: =VLOOKUP(A90,'Level 2 - Transmitted (2)'!$A$21:$L$335,12,FALSE) -> 690619 | N90: =D90-L90 -> -50819.211 | P90: =IF(D90=0,0,N90/D90) -> -0.079429864 | S90: =VLOOKUP(A90,'Level 3'!$A$21:$L$320,12,FALSE) -> 669950 | T90: =L90-S90 -> 20669 | U90: =IF(L90=0,0,T90/L90) -> 0.029928224
A91: Cost Prep Labor | C91: ='Level 1'!K101 -> 0 | F91: =VLOOKUP(A91,'Level 1.1 UPDATE A'!$A$21:$K$292,11,FALSE) -> 0 | H91: =C91-F91 -> 0 | I91: =IF(D91=0,0,H91/D91) -> 0 | K91: =VLOOKUP(A91,'Level 2 - Transmitted (2)'!$A$20:$K$335,11,FALSE) -> 0 | N91: =C91-K91 -> 0 | P91: =IF(D91=0,0,N91/D91) -> 0 | R91: =VLOOKUP(A91,'Level 3'!$A$20:$K$319,11,FALSE) -> 0 | T91: =K91-R91 -> 0 | U91: =IF(K91=0,0,T91/K91) -> 0
A92: Cost Prep Mat | C92: ='Level 1'!K102 -> 25000 | F92: =VLOOKUP(A92,'Level 1.1 UPDATE A'!$A$21:$K$292,11,FALSE) -> 25000 | H92: =C92-F92 -> 0 | I92: =IF(D92=0,0,H92/D92) -> 0 | K92: =VLOOKUP(A92,'Level 2 - Transmitted (2)'!$A$20:$K$335,11,FALSE) -> 25000 | N92: =C92-K92 -> 0 | P92: =IF(D92=0,0,N92/D92) -> 0 | R92: =VLOOKUP(A92,'Level 3'!$A$20:$K$319,11,FALSE) -> 25000 | T92: =K92-R92 -> 0 | U92: =IF(K92=0,0,T92/K92) -> 0
A93: Clean Up - Final | C93: ='Level 1'!K103 -> 367124.35 | F93: =VLOOKUP(A93,'Level 1.1 UPDATE A'!$A$21:$K$292,11,FALSE) -> 362566.65 | H93: =C93-F93 -> 4557.7 | I93: =IF(D93=0,0,H93/D93) -> 0 | K93: =VLOOKUP(A93,'Level 2 - Transmitted (2)'!$A$20:$K$335,11,FALSE) -> 359239.75 | N93: =C93-K93 -> 7884.6 | P93: =IF(D93=0,0,N93/D93) -> 0 | R93: =VLOOKUP(A93,'Level 3'!$A$20:$K$319,11,FALSE) -> 359239.75 | T93: =K93-R93 -> 0 | U93: =IF(K93=0,0,T93/K93) -> 0
A94: Clean Up - During Construction | C94: ='Level 1'!K104 -> 75000 | F94: =VLOOKUP(A94,'Level 1.1 UPDATE A'!$A$21:$K$292,11,FALSE) -> 75000 | H94: =C94-F94 -> 0 | I94: =IF(D94=0,0,H94/D94) -> 0 | K94: =VLOOKUP(A94,'Level 2 - Transmitted (2)'!$A$20:$K$335,11,FALSE) -> 50000 | N94: =C94-K94 -> 25000 | P94: =IF(D94=0,0,N94/D94) -> 0 | R94: =VLOOKUP(A94,'Level 3'!$A$20:$K$319,11,FALSE) -> 50000 | T94: =K94-R94 -> 0 | U94: =IF(K94=0,0,T94/K94) -> 0
A95: Dumpsters | C95: ='Level 1'!K105 -> 30810 | F95: =VLOOKUP(A95,'Level 1.1 UPDATE A'!$A$21:$K$292,11,FALSE) -> 0 | H95: =C95-F95 -> 30810 | I95: =IF(D95=0,0,H95/D95) -> 0 | K95: ='Level 2 - Transmitted (2)'!K105 -> 30810 | N95: =C95-K95 -> 0 | P95: =IF(D95=0,0,N95/D95) -> 0 | R95: ='Level 3'!K98 -> 20000 | T95: =K95-R95 -> 10810 | U95: =IF(K95=0,0,T95/K95) -> 0.35086011
A96: Clean Up - Hauling Exterior | C96: ='Level 1'!K106 -> 10000 | F96: =VLOOKUP(A96,'Level 1.1 UPDATE A'!$A$21:$K$292,11,FALSE) -> 10000 | H96: =C96-F96 -> 0 | I96: =IF(D96=0,0,H96/D96) -> 0 | K96: =VLOOKUP(A96,'Level 2 - Transmitted (2)'!$A$20:$K$335,11,FALSE) -> 10000 | N96: =C96-K96 -> 0 | P96: =IF(D96=0,0,N96/D96) -> 0 | R96: =VLOOKUP(A96,'Level 3'!$A$20:$K$319,11,FALSE) -> 10000 | T96: =K96-R96 -> 0 | U96: =IF(K96=0,0,T96/K96) -> 0
A97: Stucco | C97: ='Level 1'!K107 -> 1061549.7 | F97: =VLOOKUP(A97,'Level 1.1 UPDATE A'!$A$21:$K$292,11,FALSE) -> 1061549.7 | H97: =C97-F97 -> 0 | I97: =IF(D97=0,0,H97/D97) -> 0 | K97: =VLOOKUP(A97,'Level 2 - Transmitted (2)'!$A$20:$K$335,11,FALSE) -> 1150552.6 | N97: =C97-K97 -> -89002.882 | P97: =IF(D97=0,0,N97/D97) -> 0 | R97: =VLOOKUP(A97,'Level 3'!$A$20:$K$319,11,FALSE) -> 1108030 | T97: =K97-R97 -> 42522.602 | U97: =IF(K97=0,0,T97/K97) -> 0.036958416
A98: Stucco - Pump House | C98: ='Level 1'!K108 -> 6000 | F98: =VLOOKUP(A98,'Level 1.1 UPDATE A'!$A$21:$K$292,11,FALSE) -> 6000 | H98: =C98-F98 -> 0 | I98: =IF(D98=0,0,H98/D98) -> 0 | K98: =VLOOKUP(A98,'Level 2 - Transmitted (2)'!$A$20:$K$335,11,FALSE) -> 6000 | N98: =C98-K98 -> 0 | P98: =IF(D98=0,0,N98/D98) -> 0 | R98: =VLOOKUP(A98,'Level 3'!$A$20:$K$319,11,FALSE) -> 6000 | T98: =K98-R98 -> 0 | U98: =IF(K98=0,0,T98/K98) -> 0
A99: Stucco - Walls | C99: ='Level 1'!K109 -> 0 | F99: =VLOOKUP(A99,'Level 1.1 UPDATE A'!$A$21:$K$292,11,FALSE) -> 0 | H99: =C99-F99 -> 0 | I99: =IF(D99=0,0,H99/D99) -> 0 | K99: =VLOOKUP(A99,'Level 2 - Transmitted (2)'!$A$20:$K$335,11,FALSE) -> 0 | N99: =C99-K99 -> 0 | P99: =IF(D99=0,0,N99/D99) -> 0 | R99: =VLOOKUP(A99,'Level 3'!$A$20:$K$319,11,FALSE) -> 0 | T99: =K99-R99 -> 0 | U99: =IF(K99=0,0,T99/K99) -> 0
A100: Stucco - Pool Area | C100: ='Level 1'!K110 -> 2000 | F100: =VLOOKUP(A100,'Level 1.1 UPDATE A'!$A$21:$K$292,11,FALSE) -> 2000 | H100: =C100-F100 -> 0 | I100: =IF(D100=0,0,H100/D100) -> 0 | K100: =VLOOKUP(A100,'Level 2 - Transmitted (2)'!$A$20:$K$335,11,FALSE) -> 5000 | N100: =C100-K100 -> -3000 | P100: =IF(D100=0,0,N100/D100) -> 0 | R100: =VLOOKUP(A100,'Level 3'!$A$20:$K$319,11,FALSE) -> 60000 | T100: =K100-R100 -> -55000 | U100: =IF(K100=0,0,T100/K100) -> -11
A101: Stucco - Cabana | C101: ='Level 1'!K111 -> 0 | F101: =VLOOKUP(A101,'Level 1.1 UPDATE A'!$A$21:$K$292,11,FALSE) -> 0 | H101: =C101-F101 -> 0 | I101: =IF(D101=0,0,H101/D101) -> 0 | K101: =VLOOKUP(A101,'Level 2 - Transmitted (2)'!$A$20:$K$335,11,FALSE) -> 7500 | N101: =C101-K101 -> -7500 | P101: =IF(D101=0,0,N101/D101) -> 0 | R101: =VLOOKUP(A101,'Level 3'!$A$20:$K$319,11,FALSE) -> 10000 | T101: =K101-R101 -> -2500 | U101: =IF(K101=0,0,T101/K101) -> -0.33333333
A102: Stucco - Pool Equipment | C102: ='Level 1'!K112 -> 0 | F102: =VLOOKUP(A102,'Level 1.1 UPDATE A'!$A$21:$K$292,11,FALSE) -> 0 | H102: =C102-F102 -> 0 | I102: =IF(D102=0,0,H102/D102) -> 0 | K102: =VLOOKUP(A102,'Level 2 - Transmitted (2)'!$A$20:$K$335,11,FALSE) -> 0 | N102: =C102-K102 -> 0 | P102: =IF(D102=0,0,N102/D102) -> 0 | R102: =VLOOKUP(A102,'Level 3'!$A$20:$K$319,11,FALSE) -> 0 | T102: =K102-R102 -> 0 | U102: =IF(K102=0,0,T102/K102) -> 0
A103: Stucco - Repairs | C103: ='Level 1'!K113 -> 4500 | F103: =VLOOKUP(A103,'Level 1.1 UPDATE A'!$A$21:$K$292,11,FALSE) -> 4500 | H103: =C103-F103 -> 0 | I103: =IF(D103=0,0,H103/D103) -> 0 | K103: =VLOOKUP(A103,'Level 2 - Transmitted (2)'!$A$20:$K$335,11,FALSE) -> 7500 | N103: =C103-K103 -> -3000 | P103: =IF(D103=0,0,N103/D103) -> 0 | R103: =VLOOKUP(A103,'Level 3'!$A$20:$K$319,11,FALSE) -> 7500 | T103: =K103-R103 -> 0 | U103: =IF(K103=0,0,T103/K103) -> 0
A104: Drywall | C104: ='Level 1'!K114 -> 3463926.2 | F104: =VLOOKUP(A104,'Level 1.1 UPDATE A'!$A$21:$K$292,11,FALSE) -> 3420923 | H104: =C104-F104 -> 43003.24 | I104: =IF(D104=0,0,H104/D104) -> 0 | K104: =VLOOKUP(A104,'Level 2 - Transmitted (2)'!$A$20:$K$335,11,FALSE) -> 3233157.8 | N104: =C104-K104 -> 230768.47 | P104: =IF(D104=0,0,N104/D104) -> 0 | R104: =VLOOKUP(A104,'Level 3'!$A$20:$K$319,11,FALSE) -> 3252904 | T104: =K104-R104 -> -19746.25 | U104: =IF(K104=0,0,T104/K104) -> -0.0061074193
A105: Drywall - Pump House | I105: =IF(D105=0,0,H105/D105) -> 0 | K105: =VLOOKUP(A105,'Level 2 - Transmitted (2)'!$A$20:$K$335,11,FALSE) -> 2000 | P105: =IF(D105=0,0,N105/D105) -> 0 | R105: =VLOOKUP(A105,'Level 3'!$A$20:$K$319,11,FALSE) -> 2000 | T105: =K105-R105 -> 0 | U105: =IF(K105=0,0,T105/K105) -> 0
A106: Drywall - Repairs | C106: ='Level 1'!K115 -> 33150 | F106: =VLOOKUP(A106,'Level 1.1 UPDATE A'!$A$21:$K$292,11,FALSE) -> 33150 | H106: =C106-F106 -> 0 | I106: =IF(D106=0,0,H106/D106) -> 0 | K106: =VLOOKUP(A106,'Level 2 - Transmitted (2)'!$A$20:$K$335,11,FALSE) -> 33150 | N106: =C106-K106 -> 0 | P106: =IF(D106=0,0,N106/D106) -> 0 | R106: =VLOOKUP(A106,'Level 3'!$A$20:$K$319,11,FALSE) -> 33150 | T106: =K106-R106 -> 0 | U106: =IF(K106=0,0,T106/K106) -> 0
...

Sheet Level 2 - Transmitted (2)
A1: Project Details | D1: Unit Breakdown | H1: Breakdown Per Building | P1: List of Take offs | S1: List of Take offs | V1: List of Take offs
A2: Project | B2: West Henderson | D2: Unit Type | E2: Number | F2: % | H2: Bldg. | I2: Levels | J2: Unit | K2: 1 Br - 1 Ba | L2: 2 Br - 1 Ba | M2: 2 Br - 2 Ba | N2: 3 Br - 2 Ba | O2: GSF | P2: Slab SF | Q2: 145399.85 | R2: GSF (Provided in Matrix) | S2: 1 Br - 1 Ba Counter | T2: 9150.98 | U2: SF | V2: Structural | W2: 59616.52 | AP2: Finish Carpentry | AW2: Exhaust Per Building | BE2: Unit Breakdown | BF2: Wire Shelving LF | BG2: Bedrooms | BH2: Bathrooms | BI2: Unit Count | BJ2: Windows
A3: Budget Level | B3: Level 2 | D3: Studios | E3: 0 | F3: 0 | H3: 1 | I3: 3 | J3: 169 | K3: 87 | L3: 17 | M3: 48 | N3: 17 | O3: 185300 | P3: Elevators | Q3: 4 | R3: Count | S3: 2 Br - 1 Ba Counter | T3: 2673.44 | U3: SF | AA3: Railing Estimate | AE3: Building 3 | AF3: =21*7 -> 147 | AH3: Stucco | AJ3: 1.1 | AP3: Unit Type | AQ3: Number | AR3: TP $ | AS3: % | AT3: % | AW3: Building | AX3: Floors | AY3: U / Floor | AZ3: Total Units | BA3: Cost / U | BB3: Total | BE3: A1A | BF3: 41 | BG3: 1 | BH3: 1 | BI3: 9 | BJ3: 3 | BK3: =BJ3*BI3 -> 27
A4: Product | B4: Affordable | D4: 1 Br - 1 Ba | E4: 178 | F4: 0.45641026 | H4: 2 | I4: 2 | J4: 24 | K4: 9 | L4: 7 | M4: 8 | N4: 0 | O4: 24353 | P4: Elevators Stops | Q4: 12 | R4: Count | S4: 2 Br - 2 Ba Counter | T4: 2893.8 | U4: SF | AA4: Building 1 | AF4: =14*7 -> 98 | AH4: Building 1 | AI4: =88591.52+6310.7+12391.66+5996.96 -> 113290.84 | AJ4: =AI4*$AJ$3 -> 124619.92 | AP4: Studios | AQ4: 0 | AR4: 3192.5 | AS4: 0 | AT4: =AR4*(1+AS4) -> 3192.5 | AW4: Building 1 | AX4: 3 | AY4: 9 | AZ4: =AY4*AX4 -> 27 | BA4: =275 -> 275 | BB4: =BA4*AZ4 -> 7425 | BE4: B1A | BF4: 31 | BG4: 1 | BH4: 1 | BI4: 106 | BJ4: 3 | BK4: =BJ4*BI4 -> 318
A5: UPDATED | B5: 45884 | D5: 2 Br - 1 Ba | E5: 49 | F5: 0.12564103 | H5: 3 | I5: 3 | J5: 173 | K5: 73 | L5: 18 | M5: 51 | N5: 31 | O5: 192543 | P5: Trash Encl. | Q5: 13 | R5: Provided in Site Plan | S5: 3 Br - 2 Ba Counter | T5: 3543.36 | U5: SF | AA5: Northwest | AB5: =21*4+8*8+7*6 -> 190 | AF5: =8*22 -> 176 | AH5: Building 2 | AI5: =31183.77/2 -> 15591.885 | AJ5: =AI5*$AJ$3 -> 17151.074 | AP5: 1 Br - 1 Ba | AQ5: 171 | AR5: 3192.5 | AS5: 0 | AT5: =AR5*(1+AS5) -> 3192.5 | AW5: Building 2 | AX5: 2 | AY5: 2 | AZ5: =AY5*AX5 -> 4 | BA5: =275 -> 275 | BB5: =BA5*AZ5 -> 1100 | BE5: B1AE | BF5: 31 | BG5: 1 | BH5: 1 | BI5: 3 | BJ5: 3 | BK5: =BJ5*BI5 -> 9
A6: Timeline | B6: 26 | D6: 2 Br - 2 Ba | E6: 115 | F6: 0.29487179 | H6: 4 | I6: 2 | J6: 24 | K6: 9 | L6: 7 | M6: 8 | N6: 0 | O6: 24353 | P6: Stairs | Q6: 17 | R6: Count | S6: 1x1 Decks | T6: 3440 | U6: SF | AA6: Southwest | AB6: =14*4+21*2+8*6 -> 146 | AF6: =7*10 -> 70 | AH6: Building 3 | AI6: =65053.99+12730.03+12624.72 -> 90408.74 | AJ6: =AI6*$AJ$3 -> 99449.614 | AP6: 2 Br - 1 Ba | AQ6: 52 | AR6: 3192.5 | AS6: 0 | AT6: =AR6*(1+AS6) -> 3192.5 | AW6: Building 3 | AX6: 2 | AY6: 9 | AZ6: =AY6*AX6 -> 18 | BA6: =275 -> 275 | BB6: =BA6*AZ6 -> 4950 | BE6: B1B | BF6: 19 | BG6: 1 | BH6: 1 | BI6: 60 | BJ6: 2 | BK6: =BJ6*BI6 -> 120
A7: Floors | B7: 2 & 3 Levels | D7: 3 Br - 2 Ba | E7: 48 | F7: 0.12307692 | P7: Pool | Q7: 1 | S7: 2x1 Decks | U7: SF | AA7: Northeast | AB7: =21*2+14*2+8*6 -> 118 | AF7: =SUM(AF3:AF6) -> 491 | AH7: Building 4 | AI7: =31183.77/2 -> 15591.885 | AJ7: =AI7*$AJ$3 -> 17151.074 | AP7: 2 Br - 2 Ba | AQ7: 118 | AR7: 3192.5 | AS7: 0.1 | AT7: =AR7*(1+AS7) -> 3511.75 | AW7: Building 4 | AX7: 3 | AY7: 3 | AZ7: =AY7*AX7 -> 9 | BA7: =275 -> 275 | BB7: =BA7*AZ7 -> 2475 | BE7: A2B | BF7: 66 | BG7: 2 | BH7: 2 | BI7: 8 | BJ7: 3 | BK7: =BJ7*BI7 -> 24
A8: Bldg. SF | B8: 422635 | D8: Totals | E8: 390 | F8: 1 | H8: Totals | I8: 10 | J8: 390 | K8: 178 | L8: 49 | M8: 115 | N8: 48 | O8: 426549 | P8: Gym | Q8: 2 | S8: Lightweight | T8: 261305.65 | U8: SF | AA8: Southeast | AB8: =21*2+14*8+8*12+7*8 -> 306 | AJ8: =SUM(AJ4:AJ7) -> 258371.69 | AK8: sf | AP8: 3 Br - 2 Ba | AQ8: 49 | AR8: 3192.5 | AS8: 0.2 | AT8: =AR8*(1+AS8) -> 3831 | AW8: Building 5 | AX8: 2 | AY8: 2 | AZ8: =AY8*AX8 -> 4 | BA8: 275 | BB8: =BA8*AZ8 -> 1100 | BE8: B2A | BF8: 45 | BG8: 2 | BH8: 1 | BI8: 6 | BJ8: 3 | BK8: =BJ8*BI8 -> 18
A9: Acres | B9: 15.826 | D9: Parking | P9: Iron Rail | Q9: 3074.7 | R9: LF | S9: Pavers | T9: 900 | U9: SF | AA9: More | AB9: =21*4+8*6 -> 132 | AC9: =SUM(AB5:AB9) -> 892 | AJ9: =AJ8/9 -> 28707.965 | AK9: sy | AP9: Totals | AQ9: =SUM(AQ4:AQ8) -> 390 | AT9: =SUMPRODUCT(AQ4:AQ8,AT4:AT8)/AQ9 -> 3369.3154 | BB9: =SUM(BB4:BB8) -> 17050 | BE9: B2B | BF9: 68 | BG9: 2 | BH9: 2 | BI9: 107 | BJ9: 3 | BK9: =BJ9*BI9 -> 321
A10: Site SF | B10: 689380.56 | D10: Garage Parking | F10: 0 | P10: Roofing | Q10: 1734.0111 | R10: Square | S10: Pool Deck | T10: 7964 | U10: SF | AT10: =AT9-AR8 -> 176.81538 | BE10: B2C | BF10: 44 | BG10: 2 | BH10: 1 | BI10: 43 | BJ10: 6 | BK10: =BJ10*BI10 -> 258
A11: Buildings | B11: 4 | D11: Cover Parking | F11: 375 | P11: Stucco | Q11: 28186.002 | R11: Square Yard | S11: Pool Fence | T11: 372 | U11: LF | V11: Corridor Bldg. 1 | W11: 19288 | X11: SF | AA11: Building 2 & 5 | AE11: Building 4 | AF11: =14*8 -> 112 | AT11: =AT10/AR8 -> 0.055384615 | BE11: A3A | BF11: 48 | BG11: 3 | BH11: 2 | BI11: 3 | BJ11: 4 | BK11: =BJ11*BI11 -> 12
A12: Reports Available | D12: Open Parking | F12: 320 | P12: Liav GSF | Q12: 329873 | R12: SF | S12: Dog Park Fence | T12: 400 | U12: LF | V12: Corridor Bldg. 2 | W12: 2159 | X12: SF | AA12: Northwest | AF12: =20*8 -> 160 | BE12: B3A | BF12: 55 | BG12: 3 | BH12: 2 | BI12: 45 | BJ12: 4 | BK12: =BJ12*BI12 -> 180
A13: Site Evaluation Report (GCW) | B13: 45062 | D13: Accessible Parking | F13: 16 | P13: Carports | Q13: 375 | R13: Count | S13: Common Bldg. 1 | T13: 7476 | U13: SF | V13: Corridor Bldg. 3 | W13: 20355 | X13: SF | AA13: Southwest | AF13: =8*18 -> 144 | BF13: =SUMPRODUCT(BF3:BF12,BI3:BI12) -> 17473 | BI13: =SUM(BI3:BI12) -> 390 | BK13: =SUM(BK3:BK12) -> 1287
A14: Soils Report (Universal) | B14: 45848 | D14: Private Garages | F14: 0 | J14: TOTAL COST | L14: 79847909 | P14: Stairs Landings | Q14: 47 | R14: Landings | S14: Common Bldg. 2 | T14: 0 | U14: SF | V14: Corridor Bldg. 4 | W14: 2159 | X14: SF | AA14: Northeast | AF14: =7*12 -> 84 | BK14: =(6+7)*2+4 -> 30
A15: Alta Survey (Wallace) | B15: 45583 | D15: Total Parking Provided | F15: 711 | J15: PER UNIT | L15: 204738.23 | P15: Pump House | Q15: 1 | R15: EA | S15: Common Bldg. 3 | T15: 1888 | U15: SF | V15: TOTAL | W15: 43961 | X15: SF | AA15: Southeast | AB15: =21*2+14*2+8*6+7*6 -> 160 | AC15: =AB15*2 -> 320 | AF15: =SUM(AF11:AF14) -> 500 | BK15: 7 | BL15: 10
A16: Plans | B16: 45825 | D16: Parking Ratio | F16: 1.8230769 | J16: PER GSF | L16: 188.92877 | P16: Lock Boxes | Q16: 10 | R16: EA | S16: Common Bldg. 4 | T16: 1557 | U16: SF | V16: BBQ | W16: 8 | X16: Count | BK16: 13 | BL16: 6
A17: NVE Planning Memo | B17: 45043 | P17: Awning Small | Q17: 58 | R17: EA | S17: Common Bldg. 5 | T17: 0 | U17: SF | V17: Fire Pumps | W17: 1 | X17: Count | AA17: B1B Railings | AB17: =12.5*62 -> 775 | BK17: 22 | BL17: 3
P18: Awning Large | Q18: 10 | R18: EA | S18: HVAC ADD Count | T18: 135.25641 | V18: Asphalt | W18: 256408.47 | BL18: =BK13+BK14+BK15+BK16+BK17+BL15+BL16+BL17 -> 1378
A19: Description | B19: Cost Code | C19: Cost Category | D19: Sub job | E19: Source | F19: Unit Meas. | G19: QTY | H19: Unit Cost | I19: Escalation % | J19: T. Unit Cost | K19: Sub Total | L19: Total | M19: Description / Details | BL19: =BL18*368 -> 507104
A20: General Requirements | B20: 01 | L20: 3849810.3
A21: General Requirements | B21: 01 | C21: S | F21: Mo | G21: 26 | H21: 148069.63 | I21: 0 | J21: 148069.63 | K21: 3849810.3 | AX21: Slab | AY21: Lightweight | AZ21: Roofing
A22: Existing Conditions | B22: 02 | L22: 12000 | AW22: Building 1 | AX22: 59487.01 | AY22: =58247.42+58464.84 -> 116712.26 | AZ22: =62310.84+10234.24 -> 72545.08 | BE22: 15 | BG22: 2
A23: Potholing | B23: 02-3213 | C23: S | D23: ON-SITE | E23: Allowance | G23: 1 | H23: 12000 | I23: 0 | J23: 12000 | K23: 12000 | AW23: Building 2 | AX23: 11996.7 | AY23: 11552.49 | AZ23: =12091.16+2030.7 -> 14121.86 | BE23: 5 | BG23: 2
A24: Concrete | B24: 03 | L24: 2546599.2 | AW24: Building 3 | AX24: 61844.96 | AY24: =60632.4+60507.06 -> 121139.46 | AZ24: =62164.89+10362.59 -> 72527.48 | BE24: 8 | BG24: 3
A25: Slabs | B25: 03-3101 | C25: S | D25: BUILDING | E25: Torrey Pines | F25: SF | G25: 145399.85 | H25: 11.5 | I25: 0 | J25: 11.5 | K25: 1672098.3 | M25: Proposal from NRC at $9.16. Conversation with NRC said he would at $11 to 11.50 if he wasn't aggressive. | AW25: Building 4 | AX25: 12071.18 | AY25: 11901.44 | AZ25: =12174.39+2032.3 -> 14206.69 | BE25: 22 | BG25: 1
A26: Deepened Footings | B26: 03-3101 | C26: S | D26: BUILDING | E26: N/A | J26: 0 | K26: 0 | AW26: Total | AX26: =SUM(AX22:AX25) -> 145399.85 | AY26: =SUM(AY22:AY25) -> 261305.65 | AZ26: =SUM(AZ22:AZ25) -> 173401.11 | BE26: 8 | BG26: 1
A27: Concrete Slab Repairs | B27: 03-3101 | C27: RR | D27: BUILDING | E27: Allowance | F27: LS | G27: 1 | H27: 7500 | I27: 0 | J27: 7500 | K27: 7500 | AF27: =1800+1350+1350+360+900+360+900+1080+360+450 -> 8910
A28: Pump House Concrete | B28: 03-3101 | C28: S | D28: PUMPHOUSE | E28: Allowance | F28: LS | G28: 1 | H28: 10000 | I28: 0 | J28: 10000 | K28: 10000
A29: Trash Enclosure Concrete | B29: 03-3102 | C29: S | D29: OTHER SITE | E29: Bruner | F29: Count | G29: 14 | H29: 5500 | I29: 0 | J29: 5500 | K29: 77000
A30: Pool Area Shower Concrete | B30: 03-3105 | C30: S | D30: POOL AREA | E30: Allowance | F30: LS | G30: 1 | H30: 2500 | I30: 0 | J30: 2500 | K30: 2500
A31: Cabana Concrete | B31: 03-3107 | C31: S | D31: POOL AREA | E31: Allowance | F31: LS | G31: 1 | H31: 23500 | I31: 0 | J31: 23500 | K31: 23500 | AA31: Railings | AD31: Length Ea | AE31: Bldg 1 | AF31: Bldg 2 | AG31: Bldg 3 | AH31: Bldg 4 | AI31: Bldg 5
A32: Pool Equipment Foundation | B32: 03-3108 | C32: S | D32: POOL EQUIP | E32: Allowance | F32: LS | G32: 1 | H32: 4000 | I32: 0 | J32: 4000 | K32: 4000 | AB32: Outside Corner Units | AD32: =(21+15) -> 36 | AE32: =AD32*7*2 -> 504 | AF32: =AD32*2 -> 72 | AG32: =AD32*7 -> 252 | AH32: =AD32*8 -> 288 | AI32: 0
A33: Lightweight Concrete | B33: 03-3116 | C33: S | D33: BUILDING | E33: Bruner | F33: SF | G33: 261305.65 | H33: 2.6 | I33: 0 | J33: 2.6 | K33: 679394.69 | M33: NV Gypsum proposal at Bruner. | AB33: Inside Corner Units | AD33: 13 | AE33: =AD33*10*2 -> 260 | AF33: N/A | AG33: 260 | AH33: N/A | AI33: N/A | AL33: =AG33+AE33 -> 520
A34: Deck Concrete | B34: 03-5001 | C34: S | D34: BUILDING | E34: Bruner | F34: SF | G34: 3440 | H34: 20.525068 | I34: 0 | J34: 20.525068 | K34: 70606.233 | AB34: Small Railings | AD34: 8 | AE34: =AD34*52 -> 416 | AF34: =AD34*12 -> 96 | AG34: =AD34*28 -> 224 | AH34: =AD34*30 -> 240 | AI34: 0 | AL34: =AL33/AJ35 -> 0.19908116
A35: Parking Garage | B35: 03-G | L35: 0 | AE35: =SUM(AE32:AE34) -> 1180 | AF35: =SUM(AF32:AF34) -> 168 | AG35: =SUM(AG32:AG34) -> 736 | AH35: =SUM(AH32:AH34) -> 528 | AI35: =SUM(AI32:AI34) -> 0 | AJ35: =SUM(AE35:AI35) -> 2612
A36: Parking Garage Structure | C36: S | E36: N/A | G36: 0 | J36: 0 | K36: 0
A37: Core Slab Precast Concrete | C37: S | E37: N/A | J37: 0 | K37: 0 | AA37: Lightweight | AE37: Bldg 1 | AF37: Bldg 2 | AG37: Bldg 3 | AH37: Bldg 4 | AI37: Bldg 5
A38: Concrete Slab on Grade | C38: S | E38: N/A | J38: 0 | K38: 0 | AB38: Level 2 | AD38: SF | AE38: =62029-860-2726 -> 58443 | AF38: =12359-669 -> 11690 | AG38: =64481-860-2888 -> 60733 | AH38: =12359-669 -> 11690 | AI38: 0
A39: Concrete Topping Slab 4" / Level | C39: S | E39: N/A | J39: 0 | K39: 0 | AB39: Level 3 | AD39: SF | AE39: =62109-860-2827 -> 58422 | AF39: N/A | AG39: 60733 | AH39: N/A | AI39: 0
A40: Electrical | C40: S | E40: N/A | J40: 0 | K40: 0 | AB40: Total | AD40: SF | AE40: =SUM(AE38:AE39) -> 116865 | AF40: =SUM(AF38:AF39) -> 11690 | AG40: =SUM(AG38:AG39) -> 121466 | AH40: =SUM(AH38:AH39) -> 11690 | AI40: =SUM(AI38:AI39) -> 0 | AJ40: =SUM(AE40:AI40) -> 261711
A41: Dry Sprinklers | C41: S | E41: N/A | J41: 0 | K41: 0
A42: Mechanical Ventilation | C42: S | E42: N/A | J42: 0 | K42: 0
A43: Stairs and Railings | C43: S | E43: N/A | J43: 0 | K43: 0
A44: Masonry | B44: 04 | L44: 275600
A45: Elevator Shaft | B45: 04-2201 | C45: S | D45: BUILDING | E45: Bruner | F45: Per Stop | G45: 12 | H45: 10800 | I45: 0 | J45: 10800 | K45: 129600 | M45: Ave 2 Bidders Bruner | AY45: 145637 | BE45: Building 1 | BG45: Building 2 | BH45: Building 3 | BI45: Building 4
A46: Trash Enclosure | B46: 04-2202 | C46: S | D46: OTHER SITE | E46: Bruner | F46: Count | G46: 14 | H46: 6500 | I46: 0 | J46: 6500 | K46: 91000 | AY46: 505788 | BE46: =26738+14573 -> 41311 | BG46: 9811 | BH46: =28098+20414 -> 48512 | BI46: 9811
A47: Masonry Veneer | B47: 04-4301 | C47: S | D47: ON-SITE | E47: Allowance | F47: LS | G47: 1 | J47: 0 | K47: 0 | AY47: =AY46/AY45 -> 3.4729361 | BE47: =28744+20323 -> 49067 | BG47: 10036 | BH47: =28888+22223 -> 51111 | BI47: 10036
A48: Masonry Veneer Pool Area | B48: 04-4305 | C48: S | D48: POOL AREA | E48: Allowance | F48: LS | G48: 4 | H48: 10000 | I48: 0 | J48: 10000 | K48: 40000 | BE48: =28744+20323 -> 49067 | BH48: =28888+22223 -> 51111
A49: Pool Eq. Shower Stone | B49: 04-4306 | C49: A | D49: POOL EQUIP | E49: Allowance | F49: LS | G49: 1 | H49: 15000 | I49: 0 | J49: 15000 | K49: 15000 | BE49: =SUM(BE46:BE48) -> 139445 | BG49: =SUM(BG46:BG48) -> 19847 | BH49: =SUM(BH46:BH48) -> 150734 | BI49: =SUM(BI46:BI48) -> 19847 | BJ49: =SUM(BE49:BI49) -> 329873
A50: Metals | B50: 05 | L50: 609026.98
A51: Structural Steel | B51: 05-1201 | C51: S | D51: BUILDING | E51: Allowance | F51: LSB | G51: 59616.52 | H51: 4.03 | I51: 0 | J51: 4.03 | K51: 240254.58
A52: Elevator Shaft Iron | B52: 05-1202 | C52: S | D52: BUILDING | E52: Budget | F52: Elevators | G52: 4 | H52: 4100 | I52: 0 | J52: 4100 | K52: 16400
A53: Stair Handrails | B53: 05-5201 | C53: S | D53: BUILDING | E53: Bruner | F53: EA | G53: 30 | H53: 2250 | I53: 0 | J53: 2250 | K53: 67500
A54: Garage Stair Railings | B54: 05-5201 | C54: S | D54: BUILDING | E54: N/A | H54: 0 | I54: 0 | J54: 0 | K54: 0
A55: Cabana Iron | B55: 05-7004 | C55: S | D55: POOL AREA | E55: N/A | H55: 0 | I55: 0 | J55: 0 | K55: 0
A56: Pool Equipment Gate | B56: 05-7005 | C56: S | D56: POOL EQUIP | E56: Bruner | F56: Count | G56: 1 | H56: 2000 | I56: 0 | J56: 2000 | K56: 2000
A57: Iron Railings | B57: 05-7300 | C57: S | D57: BUILDING | E57: Bruner | F57: LF | G57: 3074.7 | H57: 92 | I57: 0 | J57: 92 | K57: 282872.4 | M57: Updated take off.
A58: Cable Railings | B58: 05-7316 | C58: S | D58: COMMON AREA | E58: N/A | H58: 0 | I58: 0 | J58: 0 | K58: 0 | BE58: Common Area SF
A59: Wood, Plastics, & Composites | B59: 06 | L59: 9324491 | BE59: Building 1 | BG59: Building 2 | BH59: Building 3 | BI59: Building 4
A60: Dumpsters | B60: 06-0111 | C60: S | D60: DUMPSTERS | H60: 0 | I60: 0 | J60: 0 | K60: 0 | BE60: =34267-26738 -> 7529 | BG60: =24339-9711-10036 -> 4592 | BH60: =108549-28098-28888-28888 -> 22675 | BI60: =24339-9711-10036 -> 4592
A61: Framing | B61: 06-1100 | C61: S | D61: BUILDING | E61: Proposals | F61: SF | G61: 422635 | H61: 18 | I61: 0 | J61: 18 | K61: 7607430 | M61: Gilmore proposal including pump house and shade structure came up to $17.36 psf building. | BE61: =35267-28744 -> 6523 | BH61: =26740-20414+27152-22223+27170-22223 -> 16202
A62: Framing - Crane | B62: 06-1100 | C62: S | D62: BUILDING | E62: N/A | I62: 0 | J62: 0 | K62: 0 | BE62: =35321-28744 -> 6577
A63: Cabana Framing | B63: 06-1109 | C63: S | D63: COMMON AREA | E63: Allowance | F63: LS | G63: 1 | H63: 15000 | I63: 0 | J63: 15000 | K63: 15000 | BE63: =25934-14573 -> 11361
A64: BBQ Framing | B64: 06-1110 | C64: S | D64: COMMON AREA | E64: Allowance | F64: LS | G64: 8 | H64: 2500 | I64: 0 | J64: 2500 | K64: 20000 | BE64: =26745-20323 -> 6422
A65: Fireplace Framing | B65: 06-1111 | C65: S | D65: COMMON AREA | E65: N/A | I65: 0 | J65: 0 | K65: 0
A66: Trellis | B66: 06-1114 | C66: S | D66: BUILDING | E66: N/A | I66: 0 | J66: 0 | K66: 0
A67: Pool Equipment Framing | B67: 06-1114 | C67: S | D67: POOL EQUIP | E67: N/A | I67: 0 | J67: 0 | K67: 0
A68: Finish Carpentry - Units | B68: 06-2001 | C68: S | D68: BUILDING | E68: Proposal | F68: Liav GSF | G68: 329873 | H68: 3.5481958 | I68: 0 | J68: 3.5481958 | K68: 1170454 | M68: Door & Milwood Proposal. Rystin proposal is lower at $1,064,161 | BE68: =26781-20323 -> 6458
A69: Finish Carpentry - Common | B69: 06-2001 | C69: S | D69: COMMON AREA | E69: Proposal | F69: Common SF | G69: 87842 | H69: 5.7148858 | I69: 0 | J69: 5.7148858 | K69: 502007 | M69: Door & Milwood Proposal. Rystin proposal is lower at $419K | BE69: =SUM(BE60:BE68) -> 44870 | BG69: =SUM(BG60:BG68) -> 4592 | BH69: =SUM(BH60:BH68) -> 38877 | BI69: =SUM(BI60:BI68) -> 4592 | BJ69: =SUM(BE69:BI69) -> 92931
A70: BBQ Trim | B70: 06-2006 | C70: S | D70: COMMON AREA | E70: Allowance | F70: LS | G70: 8 | H70: 1200 | I70: 0 | J70: 1200 | K70: 9600
A71: Shutters | B71: 06-4919 | C71: S | D71: BUILDING | E71: N/A | I71: 0 | J71: 0 | K71: 0
A72: Thermal & Moisture Protection | B72: 07 | C72: Jason | L72: 2237303.8
A73: Insulation | B73: 07-2101 | C73: S | D73: BUILDING | E73: Bruner | F73: SF | G73: 422635 | H73: 2.5 | I73: 0 | J73: 2.5 | K73: 1056587.5 | M73: Red Rock contract per SF at Bruner.
A74: Roofing | B74: 07-3001 | C74: S | D74: BUILDING | E74: Proposals | F74: Square | G74: 1734.0111 | H74: 565 | I74: 0 | J74: 565 | K74: 979716.27 | M74: We have 2 proposal under $565/square (Xbuilt and Deset Roofing)
A75: Cabana Roofing | B75: 07-3002 | C75: S | D75: COMMON AREA | E75: Allowance | F75: LS | G75: 1 | H75: 5500 | I75: 0 | J75: 5500 | K75: 5500
A76: Pump House Roofing | B76: 07-3002 | C76: S | D76: PUMPHOUSE | E76: Allowance | F76: LS | G76: 1 | H76: 9500 | I76: 0 | J76: 9500 | K76: 9500
A77: Pool Equipment Roofing | B77: 07-3003 | C77: S | D77: POOL EQUIP | E77: Allowance | F77: LS | G77: 0 | H77: 7500 | I77: 0 | J77: 7500 | K77: 0
A78: Trash Enclosure Cover | B78: 07-6101 | C78: S | D78: OTHER SITE | E78: Bruner | F78: Count | G78: 14 | H78: 6500 | I78: 0 | J78: 6500 | K78: 91000
A79: Pigeon Proofing | B79: 07-7001 | C79: S | D79: BUILDING | E79: Allowance | F79: LS | G79: 1 | H79: 25000 | I79: 0 | J79: 25000 | K79: 25000
A80: Gutters and Downspouts | B80: 07-7124 | C80: S | D80: BUILDING | E80: Allowance | F80: LS | G80: 1 | H80: 25000 | I80: 0 | J80: 25000 | K80: 25000
A81: Roof Ladders | B81: 07-7210 | C81: S | D81: BUILDING | E81: Bruner | F81: Count | G81: 10 | H81: 1750 | I81: 0 | J81: 1750 | K81: 17500 | M81: 2 Per building
A82: Roof Access Doors | B82: 07-7233 | C82: S | D82: BUILDING | E82: Bruner | F82: Count | G82: 10 | H82: 2750 | I82: 0 | J82: 2750 | K82: 27500 | M82: 2 Per building
A83: Roof Winch | B83: 07-7250 | C83: S | D83: BUILDING | E83: N/A | I83: 0 | J83: 0 | K83: 0
A84: Openings | B84: 08 | C84: Jason | L84: 690619
A85: Dumpsters | B85: 08-0151 | C85: S | D85: DUMPSTERS | H85: 79 | I85: 0 | J85: 79 | K85: 0
A86: Entry Doors | B86: 08-1001 | C86: S | D86: COMMON AREA | E86: N/A | I86: 0 | J86: 0 | K86: 0
A87: Common Doors | B87: 08-1002 | C87: S | D87: COMMON AREA | E87: Included | I87: 0 | J87: 0 | K87: 0
A88: Pocket Doors - 3 Panel | B88: 08-1002 | C88: S | D88: BUILDING | E88: N/A | I88: 0 | J88: 0 | K88: 0
A89: Garage Doors | B89: 08-3619 | C89: S | D89: BUILDING | E89: N/A | I89: 0 | J89: 0 | K89: 0
A90: Windows and Sliding Glass Doors | B90: 08-5301 | C90: S | D90: BUILDING | E90: Bruner | F90: Per Unit | G90: 390 | H90: 1336 | I90: 0.1 | J90: 1469.6 | K90: 573144 | M90: Bruner approved cost per sf + 10% escalation to account for the extra bedrooms
A91: Windows Repair and Replacement | B91: 08-5301 | C91: RR | D91: BUILDING | E91: Allowance | F91: Per Unit | G91: 390 | H91: 50 | I91: 0 | J91: 50 | K91: 19500
A92: Pool Equipment Windows | B92: 08-5303 | C92: S | D92: POOL EQUIP | E92: N/A | I92: 0 | J92: 0 | K92: 0
A93: Pool Glass Walls | B93: 08-8001 | C93: S | D93: POOL AREA | E93: N/A | I93: 0 | J93: 0 | K93: 0
A94: Fixed Glass | B94: 08-8002 | C94: S | D94: BUILDING | E94: N/A | I94: 0 | J94: 0 | K94: 0
A95: Mirrors - LED | B95: 08-8301 | C95: S | D95: BUILDING | E95: N/A | I95: 0 | J95: 0 | K95: 0
A96: Mirrors - LED Install | B96: 08-8302 | C96: S | D96: BUILDING | E96: N/A | I96: 0 | J96: 0 | K96: 0
A97: Mirrors - Framed | B97: 08-8301 | C97: S | D97: BUILDING | E97: N/A | I97: 0 | J97: 0 | K97: 0
A98: Mirrors - Polished Edges (Units) | B98: 08-8301 | C98: S | D98: BUILDING | E98: Bruner | F98: Bathrooms | G98: 553 | H98: 175 | I98: 0 | J98: 175 | K98: 96775
A99: Mirrors - Polished Edges (Restrooms) | B99: 08-8301 | C99: S | D99: BUILDING | E99: Allowance | F99: Count | G99: 4 | H99: 300 | I99: 0 | J99: 300 | K99: 1200
A100: Finishes | B100: 09 | C100: Jason | L100: 6934652.6
...

Sheet Level 1.1 UPDATE B
A1: Project Details | D1: Unit Breakdown | H1: Breakdown Per Building | P1: List of Take offs | S1: List of Take offs | V1: List of Take offs
A2: Project | B2: West Henderson | D2: Unit Type | E2: Number | F2: % | H2: Bldg. | I2: Levels | J2: Unit | K2: 1 Br - 1 Ba | L2: 2 Br - 1 Ba | M2: 2 Br - 2 Ba | N2: 3 Br - 2 Ba | O2: GSF | P2: Slab SF | Q2: ='Level 1.1 UPDATE A'!Q2 -> 149760 | R2: GSF (Provided in Matrix) | S2: 1 Br - 1 Ba Counter | T2: =(14.42+12.35+13.12+11.52)*K8 -> 9150.98 | U2: SF | V2: 1 Br - 1 Ba Cab | X2: SF | AP2: Finish Carpentry | AW2: Exhaust Per Building
A3: Budget Level | B3: Level 1 | D3: Studios | E3: 0 | F3: =E3/$E$8 -> 0 | H3: 1 | I3: 3 | J3: =SUM(K3:N3) -> 169 | K3: 87 | L3: 17 | M3: 48 | N3: 17 | O3: 185300 | P3: Elevators | Q3: 4 | R3: Count | S3: 2 Br - 1 Ba Counter | T3: =L8*(43.46+3.6+7.5) -> 2673.44 | U3: SF | V3: 2 Br - 1 Ba Cab | X3: SF | AA3: Railing Estimate | AE3: Building 3 | AF3: =21*7 -> 147 | AH3: Stucco | AL3: Building 3 | AM3: =15000+6560+6500+15400+4570+4635+4540+4250 -> 61455 | AP3: Unit Type | AQ3: Number | AR3: TP $ | AS3: % | AT3: % | AW3: Building | AX3: Floors | AY3: U / Floor | AZ3: Total Units | BA3: Cost / U | BB3: Total
A4: Product | B4: Affordable | D4: 1 Br - 1 Ba | E4: =K8 -> 178 | F4: =E4/$E$8 -> 0.45641026 | H4: 2 | I4: 2 | J4: =SUM(K4:N4) -> 24 | K4: 9 | L4: 7 | M4: 8 | N4: 0 | O4: 24353 | P4: Elevators Stops | Q4: 12 | R4: Count | S4: 2 Br - 2 Ba Counter | T4: =(13+13+12+12.5+6.3)*6+(8.5+16+13+7+11)*46 -> 2893.8 | U4: SF | V4: 2 Br - 2 Ba Cab | X4: SF | AA4: Building 1 | AF4: =14*7 -> 98 | AH4: Building 1 | AP4: Studios | AQ4: 0 | AR4: 3192.5 | AS4: 0 | AT4: =AR4*(1+AS4) -> 3192.5 | AW4: Building 1 | AX4: 3 | AY4: 9 | AZ4: =AY4*AX4 -> 27 | BA4: =275 -> 275 | BB4: =BA4*AZ4 -> 7425
A5: UPDATED | B5: 45748 | D5: 2 Br - 1 Ba | E5: =L8 -> 49 | F5: =E5/$E$8 -> 0.12564103 | H5: 3 | I5: 3 | J5: 173 | K5: 73 | L5: 18 | M5: 51 | N5: 31 | O5: 192543 | P5: Trash Encl. | Q5: 14 | R5: Provided in Site Plan | S5: 3 Br - 2 Ba Counter | T5: =(15+7+4+16.82+31)*N8 -> 3543.36 | U5: SF | V5: 3 Br - 2 Ba Cab | X5: SF | AA5: Northwest | AB5: =21*4+8*8+7*6 -> 190 | AF5: =8*22 -> 176 | AH5: Northwest | AI5: 19256 | AP5: 1 Br - 1 Ba | AQ5: 171 | AR5: 3192.5 | AS5: 0 | AT5: =AR5*(1+AS5) -> 3192.5 | AW5: Building 2 | AX5: 2 | AY5: 2 | AZ5: =AY5*AX5 -> 4 | BA5: =275 -> 275 | BB5: =BA5*AZ5 -> 1100
A6: Timeline | B6: 26 | D6: 2 Br - 2 Ba | E6: =M8 -> 115 | F6: =E6/$E$8 -> 0.29487179 | H6: 4 | I6: 2 | J6: 24 | K6: 9 | L6: 7 | M6: 8 | N6: 0 | O6: 24353 | P6: Stairs | Q6: 16 | R6: Count | S6: 1x1 Decks | T6: =86*38 -> 3268 | U6: SF | V6: Landscaping Bldg. 1 | X6: SF | AA6: Southwest | AB6: =14*4+21*2+8*6 -> 146 | AF6: =7*10 -> 70 | AH6: Southwest | AI6: 8980 | AP6: 2 Br - 1 Ba | AQ6: 52 | AR6: 3192.5 | AS6: 0 | AT6: =AR6*(1+AS6) -> 3192.5 | AW6: Building 3 | AX6: 2 | AY6: 9 | AZ6: =AY6*AX6 -> 18 | BA6: =275 -> 275 | BB6: =BA6*AZ6 -> 4950
A7: Floors | B7: 2 & 3 Levels | D7: 3 Br - 2 Ba | E7: =N8 -> 48 | F7: =E7/$E$8 -> 0.12307692 | P7: Pool | Q7: 1 | S7: 2x1 Decks | U7: SF | V7: Landscaping Bldg. 2 | X7: SF | AA7: Northeast | AB7: =21*2+14*2+8*6 -> 118 | AF7: =SUM(AF3:AF6) -> 491 | AH7: Northeast | AI7: 8850 | AP7: 2 Br - 2 Ba | AQ7: 118 | AR7: 3192.5 | AS7: 0.1 | AT7: =AR7*(1+AS7) -> 3511.75 | AW7: Building 4 | AX7: 3 | AY7: 3 | AZ7: =AY7*AX7 -> 9 | BA7: =275 -> 275 | BB7: =BA7*AZ7 -> 2475
A8: Bldg. SF | B8: =O8 -> 426549 | D8: Totals | E8: =SUM(E3:E7) -> 390 | F8: =E8/$E$8 -> 1 | H8: Totals | I8: =SUM(I3:I7) -> 10 | J8: =SUM(J3:J7) -> 390 | K8: =SUM(K3:K7) -> 178 | L8: =SUM(L3:L7) -> 49 | M8: =SUM(M3:M7) -> 115 | N8: =SUM(N3:N7) -> 48 | O8: =SUM(O3:O7) -> 426549 | P8: Gym | Q8: 1 | S8: Lightweight | T8: =AJ40 -> 261711 | U8: SF | V8: Landscaping Bldg. 3 | X8: SF | AA8: Southeast | AB8: =21*2+14*8+8*12+7*8 -> 306 | AH8: Southeast | AI8: 19965 | AP8: 3 Br - 2 Ba | AQ8: 49 | AR8: 3192.5 | AS8: 0.2 | AT8: =AR8*(1+AS8) -> 3831 | AW8: Building 5 | AX8: 2 | AY8: 2 | AZ8: =AY8*AX8 -> 4 | BA8: 275 | BB8: =BA8*AZ8 -> 1100
A9: Acres | B9: 15.826 | D9: Parking | P9: Iron Rail | Q9: =AJ35 -> 2612 | R9: LF | S9: Pavers | T9: 900 | U9: SF | V9: Landscaping Bldg. 4 | X9: SF | AA9: More | AB9: =21*4+8*6 -> 132 | AC9: =SUM(AB5:AB9) -> 892 | AH9: More | AI9: =5870+6250+6290+5915 -> 24325 | AJ9: =SUM(AI5:AI9) -> 81376 | AP9: Totals | AQ9: =SUM(AQ4:AQ8) -> 390 | AT9: =SUMPRODUCT(AQ4:AQ8,AT4:AT8)/AQ9 -> 3369.3154 | BB9: =SUM(BB4:BB8) -> 17050
A10: Site SF | B10: =B9*43560 -> 689380.56 | D10: Garage Parking | F10: 0 | P10: Roofing | Q10: ='Level 1.1 UPDATE A'!Q10 -> 1497.6 | R10: Square | S10: Pool Deck | T10: =10114-1655-215-35*8 -> 7964 | U10: SF | V10: Landscaping Bldg. 5 | X10: SF | AT10: =AT9-AR8 -> 176.81538
A11: Buildings | B11: 4 | D11: Cover Parking | F11: 388 | P11: Stucco | Q11: 22444 | R11: Square Yard | S11: Pool Fence | T11: 372 | U11: LF | V11: Corridor Bldg. 1 | W11: 19607 | X11: SF | AA11: Building 2 & 5 | AE11: Building 4 | AF11: =14*8 -> 112 | AH11: Building 2 & 5 | AL11: Building 4 | AM11: =5782+5760+8825+9150 -> 29517 | AT11: =AT10/AR8 -> 0.055384615
A12: Reports Available | D12: Open Parking | F12: 403 | P12: Livable Area | Q12: 332276 | R12: SF | S12: Dog Park Fence | T12: =200*2 -> 400 | U12: LF | V12: Corridor Bldg. 2 | W12: 2180 | X12: SF | AA12: Northwest | AF12: =20*8 -> 160 | AH12: Northwest
A13: Site Evaluation Report (GCW) | B13: 45062 | D13: Accessible Parking | F13: 16 | P13: Carports | Q13: 388 | R13: Count | S13: Common Bldg. 1 | T13: 7476 | U13: SF | V13: Corridor Bldg. 3 | W13: 21000 | X13: SF | AA13: Southwest | AF13: =8*18 -> 144 | AH13: Southwest
A14: Soils Report (Universal) | B14: N | D14: Private Garages | F14: 0 | J14: TOTAL COST | L14: =L335 -> 78131623 | P14: Stairs Landings | Q14: 44 | R14: Landings | S14: Common Bldg. 2 | T14: 0 | U14: SF | V14: Corridor Bldg. 4 | W14: 2180 | X14: SF | AA14: Northeast | AF14: =7*12 -> 84 | AH14: Northeast
A15: Alta Survey (Wallace) | B15: N | D15: Total Parking Provided | F15: =SUM(F10:F14) -> 807 | J15: PER UNIT | L15: =L14/E8 -> 200337.49 | P15: Pump House | Q15: 1 | R15: EA | S15: Common Bldg. 3 | T15: =748+1140 -> 1888 | U15: SF | V15: Corridor Bldg. 5 | W15: 0 | X15: SF | AA15: Southeast | AB15: =21*2+14*2+8*6+7*6 -> 160 | AC15: =AB15*2 -> 320 | AF15: =SUM(AF11:AF14) -> 500 | AH15: Southeast | AI15: =5035+5775+1960+1960 -> 14730 | AJ15: =AI15*2 -> 29460
A16: Plans | B16: N | D16: Parking Ratio | F16: =SUM(F10:F13)/E8 -> 2.0692308 | J16: PER GSF | L16: =L14/B8 -> 183.17151 | N16: =K68/Q12 -> 5.22095 | P16: Lock Boxes | Q16: 10 | R16: EA | S16: Common Bldg. 4 | T16: 1557 | U16: SF | V16: BBQ | W16: 4 | X16: Count
A17: NVE Planning Memo | B17: 45043 | P17: Awning Small | Q17: 58 | R17: EA | S17: Common Bldg. 5 | T17: 0 | U17: SF | V17: Fire Pumps | W17: 1 | X17: Count | AA17: B1B Railings | AB17: =12.5*62 -> 775 | AH17: B1B Railings | AI17: =12.5*62 -> 775
P18: Awning Large | Q18: 10 | R18: EA | S18: HVAC ADD Count | T18: =(E6*250+E7*500)/E8 -> 135.25641 | V18: Asphalt | W18: =119500+43500+114500 -> 277500
A19: Description | B19: Cost Code | C19: Cost Category | D19: Sub job | E19: Source | F19: Unit Meas. | G19: Quantity | H19: Unit Cost | I19: Escalation % | J19: T. Unit Cost | K19: Sub Total | L19: Total | M19: Description / Details
A20: General Requirements | B20: 01 | L20: =K21 -> 3747174.6
A21: General Requirements | B21: 01 | C21: S | F21: Mo | G21: =$B$6 -> 26 | H21: 144122.1 | I21: 0 | J21: =H21*(1+I21) -> 144122.1 | K21: =J21*G21 -> 3747174.6
A22: Existing Conditions | B22: 02 | L22: =K23 -> 12000
A23: Potholing | B23: 02-3213 | C23: S | D23: ON-SITE | E23: Allowance | G23: 1 | H23: 12000 | I23: 0 | J23: =H23*(1+I23) -> 12000 | K23: =J23*G23 -> 12000
A24: Concrete | B24: 03 | L24: =SUM(K25:K34) -> 2705484.9
A25: Slabs | B25: 03-3101 | C25: S | D25: BUILDING | E25: Torrey Pines | F25: SF | G25: =Q2 -> 149760 | H25: 11.99 | I25: 0 | J25: =H25*(1+I25) -> 11.99 | K25: =J25*G25 -> 1795622.4
A26: Deepened Footings | B26: 03-3101 | C26: S | D26: BUILDING | E26: N/A | J26: =H26*(1+I26) -> 0 | K26: =J26*G26 -> 0
A27: Concrete Slab Repairs | B27: 03-3101 | C27: RR | D27: BUILDING | E27: Allowance | F27: LS | G27: 1 | H27: =2500*3 -> 7500 | I27: 0 | J27: =H27*(1+I27) -> 7500 | K27: =J27*G27 -> 7500 | AF27: =1800+1350+1350+360+900+360+900+1080+360+450 -> 8910
A28: Pump House Concrete | B28: 03-3101 | C28: S | D28: PUMPHOUSE | E28: Torrey Pines | F28: SF | G28: 300 | H28: 11.99 | I28: 0 | J28: =H28*(1+I28) -> 11.99 | K28: =J28*G28 -> 3597
A29: Trash Enclosure Concrete | B29: 03-3102 | C29: S | D29: OTHER SITE | E29: Torrey Pines | F29: Count | G29: =Q5 -> 14 | H29: 5500 | I29: 0 | J29: =H29*(1+I29) -> 5500 | K29: =J29*G29 -> 77000
A30: Pool Area Shower Concrete | B30: 03-3105 | C30: S | D30: POOL AREA | E30: Torrey Pines | F30: LS | G30: =$Q$7 -> 1 | H30: 2500 | I30: 0 | J30: =H30*(1+I30) -> 2500 | K30: =J30*G30 -> 2500
A31: Cabana Concrete | B31: 03-3107 | C31: S | D31: POOL AREA | E31: Budget | F31: LS | G31: 1 | H31: 18399 | I31: 0 | J31: =H31*(1+I31) -> 18399 | K31: =J31*G31 -> 18399 | AA31: Railings | AD31: Length Ea | AE31: Bldg 1 | AF31: Bldg 2 | AG31: Bldg 3 | AH31: Bldg 4 | AI31: Bldg 5
A32: Pool Equipment Foundation | B32: 03-3108 | C32: S | D32: POOL EQUIP | E32: Budget | F32: LS | G32: 1 | H32: 3500 | I32: 0 | J32: =H32*(1+I32) -> 3500 | K32: =J32*G32 -> 3500 | AB32: Outside Corner Units | AD32: =(21+15) -> 36 | AE32: =AD32*7*2 -> 504 | AF32: =AD32*2 -> 72 | AG32: =AD32*7 -> 252 | AH32: =AD32*8 -> 288 | AI32: 0
A33: Lightweight Concrete | B33: 03-3116 | C33: S | D33: BUILDING | E33: Bruner | F33: SF | G33: =T8 -> 261711 | H33: 2.8 | I33: 0 | J33: =H33*(1+I33) -> 2.8 | K33: =J33*G33 -> 732790.8 | M33: NV Gypsum proposal at Bruner. | AB33: Inside Corner Units | AD33: 13 | AE33: =AD33*10*2 -> 260 | AF33: N/A | AG33: 260 | AH33: N/A | AI33: N/A | AL33: =AG33+AE33 -> 520
A34: Deck Concrete | B34: 03-5001 | C34: S | D34: BUILDING | E34: Torrey Pines | F34: SF | G34: =SUM($T$6:$T$7) -> 3268 | H34: 19.76 | I34: 0 | J34: =H34*(1+I34) -> 19.76 | K34: =J34*G34 -> 64575.68 | AB34: Small Railings | AD34: 8 | AE34: =AD34*52 -> 416 | AF34: =AD34*12 -> 96 | AG34: =AD34*28 -> 224 | AH34: =AD34*30 -> 240 | AI34: 0 | AL34: =AL33/AJ35 -> 0.19908116
A35: Parking Garage | B35: 03-G | L35: =SUM(K36:K43) -> 0 | AE35: =SUM(AE32:AE34) -> 1180 | AF35: =SUM(AF32:AF34) -> 168 | AG35: =SUM(AG32:AG34) -> 736 | AH35: =SUM(AH32:AH34) -> 528 | AI35: =SUM(AI32:AI34) -> 0 | AJ35: =SUM(AE35:AI35) -> 2612
A36: Parking Garage Structure | C36: S | E36: N/A | G36: 0 | J36: 0 | K36: =J36*G36 -> 0
A37: Core Slab Precast Concrete | C37: S | E37: N/A | J37: =H37*(1+I37) -> 0 | K37: =J37*G37 -> 0 | AA37: Lightweight | AE37: Bldg 1 | AF37: Bldg 2 | AG37: Bldg 3 | AH37: Bldg 4 | AI37: Bldg 5
A38: Concrete Slab on Grade | C38: S | E38: N/A | J38: =H38*(1+I38) -> 0 | K38: =J38*G38 -> 0 | AB38: Level 2 | AD38: SF | AE38: =62029-860-2726 -> 58443 | AF38: =12359-669 -> 11690 | AG38: =64481-860-2888 -> 60733 | AH38: =12359-669 -> 11690 | AI38: 0
A39: Concrete Topping Slab 4" / Level | C39: S | E39: N/A | J39: =H39*(1+I39) -> 0 | K39: =J39*G39 -> 0 | AB39: Level 3 | AD39: SF | AE39: =62109-860-2827 -> 58422 | AF39: N/A | AG39: 60733 | AH39: N/A | AI39: 0
A40: Electrical | C40: S | E40: N/A | J40: =H40*(1+I40) -> 0 | K40: =J40*G40 -> 0 | AB40: Total | AD40: SF | AE40: =SUM(AE38:AE39) -> 116865 | AF40: =SUM(AF38:AF39) -> 11690 | AG40: =SUM(AG38:AG39) -> 121466 | AH40: =SUM(AH38:AH39) -> 11690 | AI40: =SUM(AI38:AI39) -> 0 | AJ40: =SUM(AE40:AI40) -> 261711
A41: Dry Sprinklers | C41: S | E41: N/A | J41: =H41*(1+I41) -> 0 | K41: =J41*G41 -> 0
A42: Mechanical Ventilation | C42: S | E42: N/A | J42: =H42*(1+I42) -> 0 | K42: =J42*G42 -> 0 | AE42: 112658 | AF42: 11201 | AG42: 117080 | AH42: 11201
A43: Stairs and Railings | C43: S | E43: N/A | J43: =H43*(1+I43) -> 0 | K43: =J43*G43 -> 0 | AE43: =AE40-AE42 -> 4207 | AF43: =AF40-AF42 -> 489 | AG43: =AG40-AG42 -> 4386 | AH43: =AH40-AH42 -> 489
A44: Masonry | B44: 04 | L44: =SUM(K45:K49) -> 212500 | AE44: =AE43/AE40 -> 0.035998802
A45: Elevator Shaft | B45: 04-2201 | C45: S | D45: BUILDING | E45: Torrey Pines | F45: Per Stop | G45: =Q4 -> 12 | H45: 10000 | I45: 0 | J45: =H45*(1+I45) -> 10000 | K45: =J45*G45 -> 120000
A46: Trash Enclosure | B46: 04-2202 | C46: S | D46: OTHER SITE | E46: Torrey Pines | F46: Count | G46: =$Q$5 -> 14 | H46: 5500 | I46: 0 | J46: =H46*(1+I46) -> 5500 | K46: =J46*G46 -> 77000
A47: Masonry Veneer | B47: 04-4301 | C47: S | D47: ON-SITE | E47: N/A | J47: =H47*(1+I47) -> 0 | K47: =J47*G47 -> 0
A48: Masonry Veneer Pool Area | B48: 04-4305 | C48: S | D48: POOL AREA | E48: Russell IV | F48: LS | G48: =$Q$7 -> 1 | H48: 6000 | I48: 0 | J48: =H48*(1+I48) -> 6000 | K48: =J48*G48 -> 6000
A49: Pool Eq. Shower Stone | B49: 04-4306 | C49: A | D49: POOL EQUIP | E49: Torrey Pines | F49: LS | G49: =$Q$7 -> 1 | H49: 9500 | I49: 0 | J49: =H49*(1+I49) -> 9500 | K49: =J49*G49 -> 9500
A50: Metals | B50: 05 | L50: =SUM(K51:K58) -> 496414
A51: Structural Steel | B51: 05-1201 | C51: S | D51: BUILDING | E51: Allowance | F51: LS | G51: 1 | H51: 150000 | I51: 0 | J51: =H51*(1+I51) -> 150000 | K51: =J51*G51 -> 150000
A52: Elevator Shaft Iron | B52: 05-1202 | C52: S | D52: BUILDING | E52: Budget | F52: LS | G52: 1 | H52: 16160 | I52: 0 | J52: =H52*(1+I52) -> 16160 | K52: =J52*G52 -> 16160
A53: Stair Handrails | B53: 05-5201 | C53: S | D53: BUILDING | E53: Torrey Pines | F53: Per Level | G53: =Q14 -> 44 | H53: 2000 | I53: 0 | J53: =H53*(1+I53) -> 2000 | K53: =J53*G53 -> 88000
A54: Garage Stair Railings | B54: 05-5201 | C54: S | D54: BUILDING | E54: N/A | H54: 0 | I54: 0 | J54: =H54*(1+I54) -> 0 | K54: =J54*G54 -> 0
A55: Cabana Iron | B55: 05-7004 | C55: S | D55: POOL AREA | E55: N/A | H55: 0 | I55: 0 | J55: =H55*(1+I55) -> 0 | K55: =J55*G55 -> 0
A56: Pool Equipment Gate | B56: 05-7005 | C56: S | D56: POOL EQUIP | E56: Torrey Pines | F56: Count | G56: 1 | H56: 1950 | I56: 0 | J56: =H56*(1+I56) -> 1950 | K56: =J56*G56 -> 1950
A57: Iron Railings | B57: 05-7300 | C57: S | D57: BUILDING | E57: Bruner Proposal | F57: LF | G57: =$Q$9 -> 2612 | H57: 92 | I57: 0 | J57: =H57*(1+I57) -> 92 | K57: =J57*G57 -> 240304 | M57: Increase based on Bruner Proposal by Desert.
A58: Cable Railings | B58: 05-7316 | C58: S | D58: COMMON AREA | E58: N/A | H58: 0 | I58: 0 | J58: =H58*(1+I58) -> 0 | K58: =J58*G58 -> 0
A59: Wood, Plastics, & Composites | B59: 06 | L59: =SUM(K60:K71) -> 10109886
A60: Dumpsters | B60: 06-0111 | C60: S | D60: DUMPSTERS | H60: 79 | I60: 0 | J60: =H60*(1+I60) -> 79 | K60: =J60*G60 -> 0
A61: Framing | B61: 06-1100 | C61: S | D61: BUILDING | E61: Bruner Proposal | F61: SF | G61: =B8 -> 426549 | H61: 18.9 | I61: 0 | J61: =H61*(1+I61) -> 18.9 | K61: =J61*G61 -> 8061776.1 | M61: Average of all 3 bids at Bruner ($3.67M Gilmore, $3.7M National and$3.78M Focus.)
A62: Framing - Crane | B62: 06-1100 | C62: S | D62: BUILDING | E62: N/A | I62: 0 | J62: =H62*(1+I62) -> 0 | K62: =J62*G62 -> 0
A63: Cabana Framing | B63: 06-1109 | C63: S | D63: COMMON AREA | E63: N/A | I63: 0 | J63: =H63*(1+I63) -> 0 | K63: =J63*G63 -> 0
A64: BBQ Framing | B64: 06-1110 | C64: S | D64: COMMON AREA | E64: Allowance | F64: LS | G64: =$W$16 -> 4 | H64: 2500 | I64: 0 | J64: =H64*(1+I64) -> 2500 | K64: =J64*G64 -> 10000
A65: Fireplace Framing | B65: 06-1111 | C65: S | D65: COMMON AREA | E65: N/A | I65: 0 | J65: =H65*(1+I65) -> 0 | K65: =J65*G65 -> 0
A66: Trellis | B66: 06-1114 | C66: S | D66: BUILDING | E66: N/A | I66: 0 | J66: =H66*(1+I66) -> 0 | K66: =J66*G66 -> 0
A67: Pool Equipment Framing | B67: 06-1114 | C67: S | D67: POOL EQUIP | E67: N/A | I67: 0 | J67: =H67*(1+I67) -> 0 | K67: =J67*G67 -> 0
A68: Finish Carpentry - Units | B68: 06-2001 | C68: S | D68: BUILDING | E68: Bruner | F68: Units | G68: =$E$8 -> 390 | H68: 4043.8144 | I68: 0.1 | J68: =H68*(1+I68) -> 4448.1959 | K68: =J68*G68 -> 1734796.4 | M68: 10% Escalation due to 3 bedroom and 2nd bathroom units.
A69: Finish Carpentry - Common | B69: 06-2001 | C69: S | D69: COMMON AREA | E69: Torrey Pines | F69: Common SF | G69: =B8-Q12 -> 94273 | H69: 3.1664785 | I69: 0 | J69: =H69*(1+I69) -> 3.1664785 | K69: =J69*G69 -> 298513.43
A70: BBQ Trim | B70: 06-2006 | C70: S | D70: COMMON AREA | E70: Allowance | F70: LS | G70: =$W$16 -> 4 | H70: 1200 | I70: 0 | J70: =H70*(1+I70) -> 1200 | K70: =J70*G70 -> 4800
A71: Shutters | B71: 06-4919 | C71: S | D71: BUILDING | E71: N/A | I71: 0 | J71: =H71*(1+I71) -> 0 | K71: =J71*G71 -> 0
A72: Thermal & Moisture Protection | B72: 07 | L72: =SUM(K73:K83) -> 2151524.5
A73: Insulation | B73: 07-2101 | C73: S | D73: BUILDING | E73: Bruner Proposal | F73: SF | G73: =B8 -> 426549 | H73: 2.52 | I73: 0 | J73: =H73*(1+I73) -> 2.52 | K73: =J73*G73 -> 1074903.5 | M73: Average of the 2 low bids at Bruner (Batttle Born at $2.33 and Red Rock $2.71)
A74: Roofing | B74: 07-3001 | C74: S | D74: BUILDING | E74: Bruner | F74: Square | G74: =Q10 -> 1497.6 | H74: 596 | I74: 0 | J74: =H74*(1+I74) -> 596 | K74: =J74*G74 -> 892569.6 | M74: TORC Proposal.
A75: Cabana Roofing | B75: 07-3002 | C75: S | D75: COMMON AREA | E75: N/A | I75: 0 | J75: =H75*(1+I75) -> 0 | K75: =J75*G75 -> 0
A76: Pump House Roofing | B76: 07-3002 | C76: S | D76: PUMPHOUSE | E76: Allowance | F76: LS | G76: 1 | H76: 7500 | I76: 0 | J76: =H76*(1+I76) -> 7500 | K76: =J76*G76 -> 7500
A77: Pool Equipment Roofing | B77: 07-3003 | C77: S | D77: POOL EQUIP | E77: Allowance | F77: LS | G77: =Q7 -> 1 | H77: 7500 | I77: 0 | J77: =H77*(1+I77) -> 7500 | K77: =J77*G77 -> 7500 | M77: (DELETED) Baja Cover. Added 20% escalation due to Baja company sold to equity firm.
A78: Trash Enclosure Cover | B78: 07-6101 | C78: S | D78: OTHER SITE | E78: Decatur | F78: Count | G78: =$Q$5 -> 14 | H78: 5800 | I78: 0 | J78: =H78*(1+I78) -> 5800 | K78: =J78*G78 -> 81200 | M78: (DELETED) Baja Cover. Added 20% escalation due to Baja company sold to equity firm.
A79: Pigeon Proofing | B79: 07-7001 | C79: S | D79: BUILDING | E79: Torrey Pines | F79: SF | G79: =$B$8 -> 426549 | H79: 0.08 | I79: 0 | J79: =H79*(1+I79) -> 0.08 | K79: =J79*G79 -> 34123.92
A80: Gutters and Downspouts | B80: 07-7124 | C80: S | D80: BUILDING | E80: Torrey Pines | F80: SF | G80: =$B$8 -> 426549 | H80: 0.05 | I80: 0 | J80: =H80*(1+I80) -> 0.05 | K80: =J80*G80 -> 21327.45
A81: Roof Ladders | B81: 07-7210 | C81: S | D81: BUILDING | E81: Torrey Pines | F81: Count | G81: =2*$B$11 -> 8 | H81: 1550 | I81: 0 | J81: =H81*(1+I81) -> 1550 | K81: =J81*G81 -> 12400 | M81: 2 Per building
A82: Roof Access Doors | B82: 07-7233 | C82: S | D82: BUILDING | E82: Torrey Pines | F82: Count | G82: =2*$B$11 -> 8 | H82: 2500 | I82: 0 | J82: =H82*(1+I82) -> 2500 | K82: =J82*G82 -> 20000 | M82: 2 Per building
A83: Roof Winch | B83: 07-7250 | C83: S | D83: BUILDING | E83: N/A | I83: 0 | J83: =H83*(1+I83) -> 0 | K83: =J83*G83 -> 0
A84: Openings | B84: 08 | L84: =SUM(K85:K99) -> 712714
A85: Dumpsters | B85: 08-0151 | C85: S | D85: DUMPSTERS | H85: 79 | I85: 0 | J85: =H85*(1+I85) -> 79 | K85: =J85*G85 -> 0
A86: Entry Doors | B86: 08-1001 | C86: S | D86: COMMON AREA | E86: N/A | I86: 0 | J86: =H86*(1+I86) -> 0 | K86: =J86*G86 -> 0
A87: Common Doors | B87: 08-1002 | C87: S | D87: COMMON AREA | E87: Included | I87: 0 | J87: =H87*(1+I87) -> 0 | K87: =J87*G87 -> 0
A88: Pocket Doors - 3 Panel | B88: 08-1002 | C88: S | D88: BUILDING | E88: N/A | I88: 0 | J88: =H88*(1+I88) -> 0 | K88: =J88*G88 -> 0
A89: Garage Doors | B89: 08-3619 | C89: S | D89: BUILDING | E89: N/A | I89: 0 | J89: =H89*(1+I89) -> 0 | K89: =J89*G89 -> 0
A90: Windows and Sliding Glass Doors | B90: 08-5301 | C90: S | D90: BUILDING | E90: Torrey Pines | F90: Per Unit | G90: =$E$8 -> 390 | H90: 1382 | I90: 0.1 | J90: =H90*(1+I90) -> 1520.2 | K90: =J90*G90 -> 592878 | M90: 10% escalation to account for the extra bedrooms
A91: Windows Repair and Replacement | B91: 08-5301 | C91: RR | D91: BUILDING | E91: Allowance | F91: Per Unit | G91: =$E$8 -> 390 | H91: 75 | I91: 0 | J91: =H91*(1+I91) -> 75 | K91: =J91*G91 -> 29250
A92: Pool Equipment Windows | B92: 08-5303 | C92: S | D92: POOL EQUIP | E92: N/A | I92: 0 | J92: =H92*(1+I92) -> 0 | K92: =J92*G92 -> 0
A93: Pool Glass Walls | B93: 08-8001 | C93: S | D93: POOL AREA | E93: N/A | I93: 0 | J93: =H93*(1+I93) -> 0 | K93: =J93*G93 -> 0
A94: Fixed Glass | B94: 08-8002 | C94: S | D94: BUILDING | E94: N/A | I94: 0 | J94: =H94*(1+I94) -> 0 | K94: =J94*G94 -> 0
A95: Mirrors - LED | B95: 08-8301 | C95: S | D95: BUILDING | E95: N/A | I95: 0 | J95: =H95*(1+I95) -> 0 | K95: =J95*G95 -> 0
A96: Mirrors - LED Install | B96: 08-8302 | C96: S | D96: BUILDING | E96: N/A | I96: 0 | J96: =H96*(1+I96) -> 0 | K96: =J96*G96 -> 0
A97: Mirrors - Framed | B97: 08-8301 | C97: S | D97: BUILDING | E97: N/A | I97: 0 | J97: =H97*(1+I97) -> 0 | K97: =J97*G97 -> 0
A98: Mirrors - Polished Edges (Units) | B98: 08-8301 | C98: S | D98: BUILDING | E98: Pebble | F98: Unit | G98: =J8+M8+N8 -> 553 | H98: 162 | I98: 0 | J98: =H98*(1+I98) -> 162 | K98: =J98*G98 -> 89586
A99: Mirrors - Polished Edges (Restrooms) | B99: 08-8301 | C99: S | D99: BUILDING | E99: Allowance | F99: Count | G99: 4 | H99: 250 | I99: 0 | J99: =H99*(1+I99) -> 250 | K99: =J99*G99 -> 1000
A100: Finishes | B100: 09 | L100: =SUM(K101:K138) -> 6929507.4
...

Sheet Level 1.1 UPDATE A
A1: Project Details | D1: Unit Breakdown | H1: Breakdown Per Building | P1: List of Take offs | S1: List of Take offs | V1: List of Take offs
A2: Project | B2: West Henderson | D2: Unit Type | E2: Number | F2: % | H2: Bldg. | I2: Levels | J2: Unit | K2: 1 Br - 1 Ba | L2: 2 Br - 1 Ba | M2: 2 Br - 2 Ba | N2: 3 Br - 2 Ba | O2: GSF | P2: Slab SF | Q2: ='Level 1'!Q2-22352 -> 149760 | R2: GSF (Provided in Matrix) | S2: 1 Br - 1 Ba Counter | T2: =(14.42+12.35+13.12+11.52)*K8 -> 9150.98 | U2: SF | V2: 1 Br - 1 Ba Cab | X2: SF | AP2: Finish Carpentry | AW2: Exhaust Per Building
A3: Budget Level | B3: Level 1 | D3: Studios | E3: 0 | F3: =E3/$E$8 -> 0 | H3: 1 | I3: 3 | J3: =SUM(K3:N3) -> 169 | K3: 87 | L3: 17 | M3: 48 | N3: 17 | O3: 185300 | P3: Elevators | Q3: 4 | R3: Count | S3: 2 Br - 1 Ba Counter | T3: =L8*(43.46+3.6+7.5) -> 2673.44 | U3: SF | V3: 2 Br - 1 Ba Cab | X3: SF | AA3: Railing Estimate | AE3: Building 3 | AF3: =21*7 -> 147 | AH3: Stucco | AL3: Building 3 | AM3: =15000+6560+6500+15400+4570+4635+4540+4250 -> 61455 | AP3: Unit Type | AQ3: Number | AR3: TP $ | AS3: % | AT3: % | AW3: Building | AX3: Floors | AY3: U / Floor | AZ3: Total Units | BA3: Cost / U | BB3: Total
A4: Product | B4: Affordable | D4: 1 Br - 1 Ba | E4: =K8 -> 178 | F4: =E4/$E$8 -> 0.45641026 | H4: 2 | I4: 2 | J4: =SUM(K4:N4) -> 24 | K4: 9 | L4: 7 | M4: 8 | N4: 0 | O4: 24353 | P4: Elevators Stops | Q4: =Q3*3 -> 12 | R4: Count | S4: 2 Br - 2 Ba Counter | T4: =(13+13+12+12.5+6.3)*6+(8.5+16+13+7+11)*46 -> 2893.8 | U4: SF | V4: 2 Br - 2 Ba Cab | X4: SF | AA4: Building 1 | AF4: =14*7 -> 98 | AH4: Building 1 | AP4: Studios | AQ4: 0 | AR4: 3192.5 | AS4: 0 | AT4: =AR4*(1+AS4) -> 3192.5 | AW4: Building 1 | AX4: 3 | AY4: 9 | AZ4: =AY4*AX4 -> 27 | BA4: =275 -> 275 | BB4: =BA4*AZ4 -> 7425
A5: UPDATED | B5: 45748 | D5: 2 Br - 1 Ba | E5: =L8 -> 49 | F5: =E5/$E$8 -> 0.12564103 | H5: 3 | I5: 3 | J5: 173 | K5: 73 | L5: 18 | M5: 51 | N5: 31 | O5: 192543 | P5: Trash Encl. | Q5: 14 | R5: Provided in Site Plan | S5: 3 Br - 2 Ba Counter | T5: =(15+7+4+16.82+31)*N8 -> 3543.36 | U5: SF | V5: 3 Br - 2 Ba Cab | X5: SF | AA5: Northwest | AB5: =21*4+8*8+7*6 -> 190 | AF5: =8*22 -> 176 | AH5: Northwest | AI5: 19256 | AP5: 1 Br - 1 Ba | AQ5: 171 | AR5: 3192.5 | AS5: 0 | AT5: =AR5*(1+AS5) -> 3192.5 | AW5: Building 2 | AX5: 2 | AY5: 2 | AZ5: =AY5*AX5 -> 4 | BA5: =275 -> 275 | BB5: =BA5*AZ5 -> 1100
A6: Timeline | B6: 26 | D6: 2 Br - 2 Ba | E6: =M8 -> 115 | F6: =E6/$E$8 -> 0.29487179 | H6: 4 | I6: 2 | J6: 24 | K6: 9 | L6: 7 | M6: 8 | N6: 0 | O6: 24353 | P6: Stairs | Q6: =4+6+6 -> 16 | R6: Count | S6: 1x1 Decks | T6: =86*38 -> 3268 | U6: SF | V6: Landscaping Bldg. 1 | X6: SF | AA6: Southwest | AB6: =14*4+21*2+8*6 -> 146 | AF6: =7*10 -> 70 | AH6: Southwest | AI6: 8980 | AP6: 2 Br - 1 Ba | AQ6: 52 | AR6: 3192.5 | AS6: 0 | AT6: =AR6*(1+AS6) -> 3192.5 | AW6: Building 3 | AX6: 2 | AY6: 9 | AZ6: =AY6*AX6 -> 18 | BA6: =275 -> 275 | BB6: =BA6*AZ6 -> 4950
A7: Floors | B7: 2 & 3 Levels | D7: 3 Br - 2 Ba | E7: =N8 -> 48 | F7: =E7/$E$8 -> 0.12307692 | P7: Pool | Q7: 1 | S7: 2x1 Decks | U7: SF | V7: Landscaping Bldg. 2 | X7: SF | AA7: Northeast | AB7: =21*2+14*2+8*6 -> 118 | AF7: =SUM(AF3:AF6) -> 491 | AH7: Northeast | AI7: 8850 | AP7: 2 Br - 2 Ba | AQ7: 118 | AR7: 3192.5 | AS7: 0.1 | AT7: =AR7*(1+AS7) -> 3511.75 | AW7: Building 4 | AX7: 3 | AY7: 3 | AZ7: =AY7*AX7 -> 9 | BA7: =275 -> 275 | BB7: =BA7*AZ7 -> 2475
A8: Bldg. SF | B8: =O8 -> 426549 | D8: Totals | E8: =SUM(E3:E7) -> 390 | F8: =E8/$E$8 -> 1 | H8: Totals | I8: =SUM(I3:I7) -> 10 | J8: =SUM(J3:J7) -> 390 | K8: =SUM(K3:K7) -> 178 | L8: =SUM(L3:L7) -> 49 | M8: =SUM(M3:M7) -> 115 | N8: =SUM(N3:N7) -> 48 | O8: =SUM(O3:O7) -> 426549 | P8: Gym | Q8: 1 | S8: Lightweight | T8: =AJ40 -> 261711 | U8: SF | V8: Landscaping Bldg. 3 | X8: SF | AA8: Southeast | AB8: =21*2+14*8+8*12+7*8 -> 306 | AH8: Southeast | AI8: 19965 | AP8: 3 Br - 2 Ba | AQ8: 49 | AR8: 3192.5 | AS8: 0.2 | AT8: =AR8*(1+AS8) -> 3831 | AW8: Building 5 | AX8: 2 | AY8: 2 | AZ8: =AY8*AX8 -> 4 | BA8: 275 | BB8: =BA8*AZ8 -> 1100
A9: Acres | B9: 15.826 | D9: Parking | P9: Iron Rail | Q9: =AJ35 -> 2932 | R9: LF | S9: Pavers | T9: 900 | U9: SF | V9: Landscaping Bldg. 4 | X9: SF | AA9: More | AB9: =21*4+8*6 -> 132 | AC9: =SUM(AB5:AB9) -> 892 | AH9: More | AI9: =5870+6250+6290+5915 -> 24325 | AJ9: =SUM(AI5:AI9) -> 81376 | AP9: Totals | AQ9: =SUM(AQ4:AQ8) -> 390 | AT9: =SUMPRODUCT(AQ4:AQ8,AT4:AT8)/AQ9 -> 3369.3154 | BB9: =SUM(BB4:BB8) -> 17050
A10: Site SF | B10: =B9*43560 -> 689380.56 | D10: Garage Parking | F10: 0 | P10: Roofing | Q10: =Q2/100 -> 1497.6 | R10: Square | S10: Pool Deck | T10: =10114-1655-215-35*8 -> 7964 | U10: SF | V10: Landscaping Bldg. 5 | X10: SF | AT10: =AT9-AR8 -> 176.81538
A11: Buildings | B11: 4 | D11: Cover Parking | F11: 388 | P11: Stucco | Q11: ='Level 1'!Q11 -> 26012 | R11: Square Yard | S11: Pool Fence | T11: =67+148+90+132 -> 437 | U11: LF | V11: Corridor Bldg. 1 | W11: 19607 | X11: SF | AA11: Building 2 & 5 | AE11: Building 4 | AF11: =14*8 -> 112 | AH11: Building 2 & 5 | AL11: Building 4 | AM11: =5782+5760+8825+9150 -> 29517 | AT11: =AT10/AR8 -> 0.055384615
A12: Reports Available | D12: Open Parking | F12: 403 | P12: Livable Area | Q12: =139051+19843+101286+52253+19843 -> 332276 | R12: SF | S12: Dog Park Fence | T12: =200*2 -> 400 | U12: LF | V12: Corridor Bldg. 2 | W12: 2180 | X12: SF | AA12: Northwest | AF12: =20*8 -> 160 | AH12: Northwest
A13: Site Evaluation Report (GCW) | B13: 45062 | D13: Accessible Parking | F13: 16 | P13: Carports | Q13: =F11 -> 388 | R13: Count | S13: Common Bldg. 1 | T13: 7476 | U13: SF | V13: Corridor Bldg. 3 | W13: 21000 | X13: SF | AA13: Southwest | AF13: =8*18 -> 144 | AH13: Southwest
A14: Soils Report (Universal) | B14: N | D14: Private Garages | F14: 0 | J14: TOTAL COST | L14: =L331 -> 82551538 | P14: Stairs Landings | Q14: =4*2+12*3 -> 44 | R14: Landings | S14: Common Bldg. 2 | T14: 0 | U14: SF | V14: Corridor Bldg. 4 | W14: 2180 | X14: SF | AA14: Northeast | AF14: =7*12 -> 84 | AH14: Northeast
A15: Alta Survey (Wallace) | B15: N | D15: Total Parking Provided | F15: =SUM(F10:F14) -> 807 | J15: PER UNIT | L15: =L14/E8 -> 211670.61 | P15: Pump House | Q15: 1 | R15: EA | S15: Common Bldg. 3 | T15: =748+1140+800 -> 2688 | U15: SF | V15: Corridor Bldg. 5 | W15: 0 | X15: SF | AA15: Southeast | AB15: =21*2+14*2+8*6+7*6 -> 160 | AC15: =AB15*2 -> 320 | AF15: =SUM(AF11:AF14) -> 500 | AH15: Southeast | AI15: =5035+5775+1960+1960 -> 14730 | AJ15: =AI15*2 -> 29460
A16: Plans | B16: N | D16: Parking Ratio | F16: =SUM(F10:F13)/E8 -> 2.0692308 | J16: PER GSF | L16: =L14/B8 -> 193.53354 | P16: Lock Boxes | Q16: 10 | R16: EA | S16: Common Bldg. 4 | T16: 1557 | U16: SF | V16: BBQ | W16: 4 | X16: Count
A17: NVE Planning Memo | B17: 45043 | P17: Awning Small | Q17: 58 | R17: EA | S17: Common Bldg. 5 | T17: 0 | U17: SF | V17: Fire Pumps | W17: 1 | X17: Count | AA17: B1B Railings | AB17: =12.5*62 -> 775 | AH17: B1B Railings | AI17: =12.5*62 -> 775
P18: Awning Large | Q18: 10 | R18: EA | S18: HVAC ADD Count | T18: =(E6*250+E7*500)/E8 -> 135.25641 | V18: Asphalt | W18: =119500+43500+114500 -> 277500
A19: Description | B19: Cost Code | C19: Cost Category | D19: Sub job | E19: Source | F19: Unit Meas. | G19: Quantity | H19: Unit Cost | I19: Escalation % | J19: T. Unit Cost | K19: Sub Total | L19: Total | M19: Description / Details
A20: General Requirements | B20: 01 | L20: =K21 -> 4080000 | M20: Hard coded number
A21: General Requirements | B21: 01 | C21: S | F21: Mo | G21: =$B$6 -> 26 | H21: =4080000/26 -> 156923.08 | I21: 0 | J21: =H21*(1+I21) -> 156923.08 | K21: =J21*G21 -> 4080000 | AA21: =Q11*9 -> 234108
A22: Existing Conditions | B22: 02 | L22: =K23 -> 12000
A23: Potholing | B23: 02-3213 | C23: S | D23: ON-SITE | E23: Allowance | G23: 1 | H23: 12000 | I23: 0 | J23: =H23*(1+I23) -> 12000 | K23: =J23*G23 -> 12000
A24: Concrete | B24: 03 | L24: =SUM(K25:K34) -> 2681833.9
A25: Slabs | B25: 03-3101 | C25: S | D25: BUILDING | E25: Torrey Pines | F25: SF | G25: =Q2 -> 149760 | H25: 11.99 | I25: 0 | J25: =H25*(1+I25) -> 11.99 | K25: =J25*G25 -> 1795622.4 | M25: Conventional slab
A26: Deepened Footings | B26: 03-3101 | C26: S | D26: BUILDING | E26: N/A | J26: =H26*(1+I26) -> 0 | K26: =J26*G26 -> 0
A27: Concrete Slab Repairs | B27: 03-3101 | C27: RR | D27: BUILDING | E27: Allowance | F27: LS | G27: 1 | H27: =2500*3 -> 7500 | I27: 0 | J27: =H27*(1+I27) -> 7500 | K27: =J27*G27 -> 7500 | AF27: =1800+1350+1350+360+900+360+900+1080+360+450 -> 8910
A28: Pump House Concrete | B28: 03-3101 | C28: S | D28: PUMPHOUSE | E28: Torrey Pines | F28: SF | G28: 300 | H28: 11.99 | J28: =H28*(1+I28) -> 11.99 | K28: =J28*G28 -> 3597
A29: Trash Enclosure Concrete | B29: 03-3102 | C29: S | D29: OTHER SITE | E29: Torrey Pines | F29: Count | G29: =Q5 -> 14 | H29: =11031/4 -> 2757.75 | I29: 0 | J29: =H29*(1+I29) -> 2757.75 | K29: =J29*G29 -> 38608.5
A30: Pool Area Shower Concrete | B30: 03-3105 | C30: S | D30: POOL AREA | E30: Torrey Pines | F30: LS | G30: =$Q$7 -> 1 | H30: 2500 | I30: 0 | J30: =H30*(1+I30) -> 2500 | K30: =J30*G30 -> 2500
A31: Cabana Concrete | B31: 03-3107 | C31: S | D31: POOL AREA | E31: N/A | J31: =H31*(1+I31) -> 0 | K31: =J31*G31 -> 0 | AA31: Railings | AD31: Length Ea | AE31: Bldg 1 | AF31: Bldg 2 | AG31: Bldg 3 | AH31: Bldg 4 | AI31: Bldg 5
A32: Pool Equipment Foundation | B32: 03-3108 | C32: S | D32: POOL EQUIP | E32: N/A | J32: =H32*(1+I32) -> 0 | K32: =J32*G32 -> 0 | AB32: Outside Corner Units | AD32: =(21+15) -> 36 | AE32: =AD32*7*2 -> 504 | AF32: =AD32*2 -> 72 | AG32: =AD32*7 -> 252 | AH32: 500 | AI32: 0
A33: Lightweight Concrete | B33: 03-3116 | C33: S | D33: BUILDING | E33: Torrey Pines | F33: SF | G33: =T8 -> 261711 | H33: 2.94 | I33: 0 | J33: =H33*(1+I33) -> 2.94 | K33: =J33*G33 -> 769430.34 | AB33: Inside Corner Units | AD33: 13 | AE33: =AD33*10*2 -> 260 | AF33: N/A | AG33: =AD33*8 -> 104 | AH33: =AD33*8 -> 104 | AI33: N/A
A34: Deck Concrete | B34: 03-5001 | C34: S | D34: BUILDING | E34: Torrey Pines | F34: SF | G34: =SUM($T$6:$T$7) -> 3268 | H34: 19.76 | I34: 0 | J34: =H34*(1+I34) -> 19.76 | K34: =J34*G34 -> 64575.68 | AB34: Small Railings | AD34: 8 | AE34: =AD34*52 -> 416 | AF34: =AD34*12 -> 96 | AG34: =AD34*28 -> 224 | AH34: 400 | AI34: 0
A35: Parking Garage | B35: 03-G | L35: =SUM(K36:K43) -> 0 | AE35: =SUM(AE32:AE34) -> 1180 | AF35: =SUM(AF32:AF34) -> 168 | AG35: =SUM(AG32:AG34) -> 580 | AH35: =SUM(AH32:AH34) -> 1004 | AI35: =SUM(AI32:AI34) -> 0 | AJ35: =SUM(AE35:AI35) -> 2932
A36: Parking Garage Structure | C36: S | E36: N/A | G36: 0 | H36: 1 | J36: 0 | K36: =J36*G36 -> 0
A37: Core Slab Precast Concrete | C37: S | E37: N/A | J37: =H37*(1+I37) -> 0 | K37: =J37*G37 -> 0 | AA37: Lightweight | AE37: Bldg 1 | AF37: Bldg 2 | AG37: Bldg 3 | AH37: Bldg 4 | AI37: Bldg 5
A38: Concrete Slab on Grade | C38: S | E38: N/A | J38: =H38*(1+I38) -> 0 | K38: =J38*G38 -> 0 | AB38: Level 2 | AD38: SF | AE38: =62029-860-2726 -> 58443 | AF38: =12359-669 -> 11690 | AG38: =64481-860-2888 -> 60733 | AH38: =12359-669 -> 11690 | AI38: 0
A39: Concrete Topping Slab 4" / Level | C39: S | E39: N/A | J39: =H39*(1+I39) -> 0 | K39: =J39*G39 -> 0 | AB39: Level 3 | AD39: SF | AE39: =62109-860-2827 -> 58422 | AF39: N/A | AG39: 60733 | AH39: N/A | AI39: 0
A40: Electrical | C40: S | E40: N/A | J40: =H40*(1+I40) -> 0 | K40: =J40*G40 -> 0 | AB40: Total | AD40: SF | AE40: =SUM(AE38:AE39) -> 116865 | AF40: =SUM(AF38:AF39) -> 11690 | AG40: =SUM(AG38:AG39) -> 121466 | AH40: =SUM(AH38:AH39) -> 11690 | AI40: =SUM(AI38:AI39) -> 0 | AJ40: =SUM(AE40:AI40) -> 261711
A41: Dry Sprinklers | C41: S | E41: N/A | J41: =H41*(1+I41) -> 0 | K41: =J41*G41 -> 0
A42: Mechanical Ventilation | C42: S | E42: N/A | J42: =H42*(1+I42) -> 0 | K42: =J42*G42 -> 0
A43: Stairs and Railings | C43: S | E43: N/A | J43: =H43*(1+I43) -> 0 | K43: =J43*G43 -> 0
A44: Masonry | B44: 04 | L44: =SUM(K45:K49) -> 208800
A45: Elevator Shaft | B45: 04-2201 | C45: S | D45: BUILDING | E45: Torrey Pines | F45: Per Stop | G45: =Q4 -> 12 | H45: 9500 | I45: 0 | J45: =H45*(1+I45) -> 9500 | K45: =J45*G45 -> 114000
A46: Trash Enclosure | B46: 04-2202 | C46: S | D46: OTHER SITE | E46: Torrey Pines | F46: Count | G46: =$Q$5 -> 14 | H46: 5700 | I46: 0 | J46: =H46*(1+I46) -> 5700 | K46: =J46*G46 -> 79800
A47: Masonry Veneer | B47: 04-4301 | C47: S | D47: ON-SITE | E47: N/A | J47: =H47*(1+I47) -> 0 | K47: =J47*G47 -> 0
A48: Masonry Veneer Pool Area | B48: 04-4305 | C48: S | D48: POOL AREA | E48: Russell IV | F48: LS | G48: =$Q$7 -> 1 | H48: 6000 | I48: 0 | J48: =H48*(1+I48) -> 6000 | K48: =J48*G48 -> 6000
A49: Pool Eq. Shower Stone | B49: 04-4306 | C49: A | D49: POOL EQUIP | E49: Torrey Pines | F49: LS | G49: =$Q$7 -> 1 | H49: 9000 | I49: 0 | J49: =H49*(1+I49) -> 9000 | K49: =J49*G49 -> 9000
A50: Metals | B50: 05 | L50: =SUM(K51:K58) -> 500854
A51: Structural Steel | B51: 05-1201 | C51: S | D51: BUILDING | E51: Allowance | F51: LS | G51: 1 | H51: 125000 | I51: 0 | J51: =H51*(1+I51) -> 125000 | K51: =J51*G51 -> 125000 | M51: Bldg 1 only
A52: Elevator Shaft Iron | B52: 05-1202 | C52: S | D52: BUILDING | E52: Torrey Pines | F52: Count | G52: =$Q$3 -> 4 | H52: 4040 | I52: 0 | J52: =H52*(1+I52) -> 4040 | K52: =J52*G52 -> 16160
A53: Stair Handrails | B53: 05-5201 | C53: S | D53: BUILDING | E53: Torrey Pines | F53: Per Level | G53: =Q14 -> 44 | H53: 2000 | I53: 0 | J53: =H53*(1+I53) -> 2000 | K53: =J53*G53 -> 88000
A54: Garage Stair Railings | B54: 05-5201 | C54: S | D54: BUILDING | E54: N/A | H54: 0 | I54: 0 | J54: =H54*(1+I54) -> 0 | K54: =J54*G54 -> 0
A55: Cabana Iron | B55: 05-7004 | C55: S | D55: POOL AREA | E55: N/A | H55: 0 | I55: 0 | J55: =H55*(1+I55) -> 0 | K55: =J55*G55 -> 0
A56: Pool Equipment Gate | B56: 05-7005 | C56: S | D56: POOL EQUIP | E56: Torrey Pines | F56: Count | G56: =$Q$7 -> 1 | H56: 1950 | I56: 0 | J56: =H56*(1+I56) -> 1950 | K56: =J56*G56 -> 1950
A57: Iron Railings | B57: 05-7300 | C57: S | D57: BUILDING | E57: Torrey Pines | F57: LF | G57: =$Q$9 -> 2932 | H57: 92 | I57: 0 | J57: =H57*(1+I57) -> 92 | K57: =J57*G57 -> 269744
A58: Cable Railings | B58: 05-7316 | C58: S | D58: COMMON AREA | E58: N/A | H58: 0 | I58: 0 | J58: =H58*(1+I58) -> 0 | K58: =J58*G58 -> 0
A59: Wood, Plastics, & Composites | B59: 06 | L59: =SUM(K60:K71) -> 10684047
A60: Dumpsters | B60: 06-0111 | C60: S | D60: DUMPSTERS | H60: 79 | I60: 0 | J60: =H60*(1+I60) -> 79 | K60: =J60*G60 -> 0
A61: Framing | B61: 06-1100 | C61: S | D61: BUILDING | E61: See Note | F61: SF | G61: =B8 -> 426549 | H61: 20.96 | I61: 0 | J61: =H61*(1+I61) -> 20.96 | K61: =J61*G61 -> 8940467 | M61: 12 Month Moving Average
A62: Framing - Crane | B62: 06-1100 | C62: S | D62: BUILDING | E62: N/A | I62: 0 | J62: =H62*(1+I62) -> 0 | K62: =J62*G62 -> 0
A63: Cabana Framing | B63: 06-1109 | C63: S | D63: COMMON AREA | E63: N/A | I63: 0 | J63: =H63*(1+I63) -> 0 | K63: =J63*G63 -> 0
A64: BBQ Framing | B64: 06-1110 | C64: S | D64: COMMON AREA | E64: Allowance | F64: LS | G64: =$W$16 -> 4 | H64: 2500 | I64: 0 | J64: =H64*(1+I64) -> 2500 | K64: =J64*G64 -> 10000
A65: Fireplace Framing | B65: 06-1111 | C65: S | D65: COMMON AREA | E65: N/A | I65: 0 | J65: =H65*(1+I65) -> 0 | K65: =J65*G65 -> 0
A66: Trellis | B66: 06-1114 | C66: S | D66: BUILDING | E66: N/A | I66: 0 | J66: =H66*(1+I66) -> 0 | K66: =J66*G66 -> 0
A67: Pool Equipment Framing | B67: 06-1114 | C67: S | D67: POOL EQUIP | E67: N/A | I67: 0 | J67: =H67*(1+I67) -> 0 | K67: =J67*G67 -> 0
A68: Finish Carpentry - Units | B68: 06-2001 | C68: S | D68: BUILDING | E68: Torrey Pines | F68: LSF | G68: =Q12 -> 332276 | H68: 4.3044537 | I68: 0 | J68: =H68*(1+I68) -> 4.3044537 | K68: =J68*G68 -> 1430266.6
A69: Finish Carpentry - Common | B69: 06-2001 | C69: S | D69: COMMON AREA | E69: Torrey Pines | F69: Common SF | G69: =B8-Q12 -> 94273 | H69: 3.1664785 | I69: 0 | J69: =H69*(1+I69) -> 3.1664785 | K69: =J69*G69 -> 298513.43
A70: BBQ Trim | B70: 06-2006 | C70: S | D70: COMMON AREA | E70: Allowance | F70: LS | G70: =$W$16 -> 4 | H70: 1200 | I70: 0 | J70: =H70*(1+I70) -> 1200 | K70: =J70*G70 -> 4800
A71: Shutters | B71: 06-4919 | C71: S | D71: BUILDING | E71: N/A | I71: 0 | J71: =H71*(1+I71) -> 0 | K71: =J71*G71 -> 0
A72: Thermal & Moisture Protection | B72: 07 | L72: =SUM(K73:K83) -> 2256526.5
A73: Insulation | B73: 07-2101 | C73: S | D73: BUILDING | E73: Torrey Pines | F73: SF | G73: =B8 -> 426549 | H73: 2.7 | I73: 0 | J73: =H73*(1+I73) -> 2.7 | K73: =J73*G73 -> 1151682.3
A74: Roofing | B74: 07-3001 | C74: S | D74: BUILDING | E74: Torrey Pines | F74: Square | G74: =Q10 -> 1497.6 | H74: 603 | I74: 0 | J74: =H74*(1+I74) -> 603 | K74: =J74*G74 -> 903052.8
A75: Cabana Roofing | B75: 07-3002 | C75: S | D75: COMMON AREA | E75: N/A | I75: 0 | J75: =H75*(1+I75) -> 0 | K75: =J75*G75 -> 0
A76: Pump House Roofing | B76: 07-3002 | C76: S | D76: PUMPHOUSE | E76: Allowance | F76: LS | G76: 1 | H76: 7500 | I76: 0 | J76: =H76*(1+I76) -> 7500 | K76: =J76*G76 -> 7500
A77: Pool Equipment Roofing | B77: 07-3003 | C77: S | D77: POOL EQUIP | E77: Allowance | F77: LS | G77: =Q7 -> 1 | H77: 7500 | I77: 0.2 | J77: =H77*(1+I77) -> 9000 | K77: =J77*G77 -> 9000 | M77: Baja Cover. Added 20% escalation due to Baja company sold to equity firm.
A78: Trash Enclosure Cover | B78: 07-6101 | C78: S | D78: OTHER SITE | E78: Decatur | F78: Count | G78: =$Q$5 -> 14 | H78: 5800 | I78: 0.2 | J78: =H78*(1+I78) -> 6960 | K78: =J78*G78 -> 97440 | M78: Baja Cover. Added 20% escalation due to Baja company sold to equity firm.
A79: Pigeon Proofing | B79: 07-7001 | C79: S | D79: BUILDING | E79: Torrey Pines | F79: SF | G79: =$B$8 -> 426549 | H79: 0.08 | I79: 0 | J79: =H79*(1+I79) -> 0.08 | K79: =J79*G79 -> 34123.92
A80: Gutters and Downspouts | B80: 07-7124 | C80: S | D80: BUILDING | E80: Torrey Pines | F80: SF | G80: =$B$8 -> 426549 | H80: 0.05 | I80: 0 | J80: =H80*(1+I80) -> 0.05 | K80: =J80*G80 -> 21327.45
A81: Roof Ladders | B81: 07-7210 | C81: S | D81: BUILDING | E81: Torrey Pines | F81: Count | G81: =2*$B$11 -> 8 | H81: 1550 | I81: 0 | J81: =H81*(1+I81) -> 1550 | K81: =J81*G81 -> 12400 | M81: 2 Per building
A82: Roof Access Doors | B82: 07-7233 | C82: S | D82: BUILDING | E82: Torrey Pines | F82: Count | G82: =2*$B$11 -> 8 | H82: 2500 | I82: 0 | J82: =H82*(1+I82) -> 2500 | K82: =J82*G82 -> 20000 | M82: 2 Per building
A83: Roof Winch | B83: 07-7250 | C83: S | D83: BUILDING | E83: N/A | I83: 0 | J83: =H83*(1+I83) -> 0 | K83: =J83*G83 -> 0
A84: Openings | B84: 08 | L84: =SUM(K85:K99) -> 639151.79
A85: Dumpsters | B85: 08-0151 | C85: S | D85: DUMPSTERS | H85: 79 | I85: 0 | J85: =H85*(1+I85) -> 79 | K85: =J85*G85 -> 0
A86: Entry Doors | B86: 08-1001 | C86: S | D86: COMMON AREA | E86: N/A | I86: 0 | J86: =H86*(1+I86) -> 0 | K86: =J86*G86 -> 0
A87: Common Doors | B87: 08-1002 | C87: S | D87: COMMON AREA | E87: Included | I87: 0 | J87: =H87*(1+I87) -> 0 | K87: =J87*G87 -> 0
A88: Pocket Doors - 3 Panel | B88: 08-1002 | C88: S | D88: BUILDING | E88: N/A | I88: 0 | J88: =H88*(1+I88) -> 0 | K88: =J88*G88 -> 0
A89: Garage Doors | B89: 08-3619 | C89: S | D89: BUILDING | E89: N/A | I89: 0 | J89: =H89*(1+I89) -> 0 | K89: =J89*G89 -> 0
A90: Windows and Sliding Glass Doors | B90: 08-5301 | C90: S | D90: BUILDING | E90: Torrey Pines | F90: Per Unit | G90: =$E$8 -> 390 | H90: 1157.8947 | I90: 0.15 | J90: =H90*(1+I90) -> 1331.5789 | K90: =J90*G90 -> 519315.79 | M90: Included the latest efficiency requirement. 15% escalation with more bedrooms/windows expected.
A91: Windows Repair and Replacement | B91: 08-5301 | C91: RR | D91: BUILDING | E91: Allowance | F91: Per Unit | G91: =$E$8 -> 390 | H91: 75 | I91: 0 | J91: =H91*(1+I91) -> 75 | K91: =J91*G91 -> 29250
A92: Pool Equipment Windows | B92: 08-5303 | C92: S | D92: POOL EQUIP | E92: N/A | I92: 0 | J92: =H92*(1+I92) -> 0 | K92: =J92*G92 -> 0
A93: Pool Glass Walls | B93: 08-8001 | C93: S | D93: POOL AREA | E93: N/A | I93: 0 | J93: =H93*(1+I93) -> 0 | K93: =J93*G93 -> 0
A94: Fixed Glass | B94: 08-8002 | C94: S | D94: BUILDING | E94: N/A | I94: 0 | J94: =H94*(1+I94) -> 0 | K94: =J94*G94 -> 0
A95: Mirrors - LED | B95: 08-8301 | C95: S | D95: BUILDING | E95: N/A | I95: 0 | J95: =H95*(1+I95) -> 0 | K95: =J95*G95 -> 0
A96: Mirrors - LED Install | B96: 08-8302 | C96: S | D96: BUILDING | E96: N/A | I96: 0 | J96: =H96*(1+I96) -> 0 | K96: =J96*G96 -> 0
A97: Mirrors - Framed | B97: 08-8301 | C97: S | D97: BUILDING | E97: N/A | I97: 0 | J97: =H97*(1+I97) -> 0 | K97: =J97*G97 -> 0
A98: Mirrors - Polished Edges (Units) | B98: 08-8301 | C98: S | D98: BUILDING | E98: Pebble | F98: Unit | G98: =J8+M8+N8 -> 553 | H98: 162 | I98: 0 | J98: =H98*(1+I98) -> 162 | K98: =J98*G98 -> 89586
A99: Mirrors - Polished Edges (Restrooms) | B99: 08-8301 | C99: S | D99: BUILDING | E99: Allowance | F99: Count | G99: 4 | H99: 250 | I99: 0 | J99: =H99*(1+I99) -> 250 | K99: =J99*G99 -> 1000
A100: Finishes | B100: 09 | L100: =SUM(K101:K136) -> 6962391.7
...

Sheet Level 1
A1: Project Details | D1: Unit Breakdown | H1: Breakdown Per Building | P1: List of Take offs | S1: List of Take offs | V1: List of Take offs
A2: Project | B2: West Henderson | D2: Unit Type | E2: Number | F2: % | H2: Bldg. | I2: Levels | J2: Unit | K2: 1 Br - 1 Ba | L2: 2 Br - 1 Ba | M2: 2 Br - 2 Ba | N2: 3 Br - 2 Ba | O2: GSF | P2: Slab SF | Q2: =12033+22510+64020+12033+61516 -> 172112 | R2: GSF (Provided in Matrix) | S2: 1 Br - 1 Ba Counter | T2: =(14.42+12.35+13.12+11.52)*K8 -> 8791.11 | U2: SF | V2: 1 Br - 1 Ba Cab | X2: SF | AP2: Finish Carpentry | AW2: Exhaust Per Building
A3: Budget Level | B3: Level 1 | D3: Studios | E3: 0 | F3: =E3/$E$8 -> 0 | H3: 1 | I3: 3 | J3: =SUM(K3:N3) -> 169 | K3: 87 | L3: 17 | M3: 48 | N3: 17 | O3: 185654 | P3: Elevators | Q3: 6 | R3: Count | S3: 2 Br - 1 Ba Counter | T3: =L8*(43.46+3.6+7.5) -> 2837.12 | U3: SF | V3: 2 Br - 1 Ba Cab | X3: SF | AA3: Railing Estimate | AE3: Building 3 | AF3: =21*7 -> 147 | AH3: Stucco | AL3: Building 3 | AM3: =15000+6560+6500+15400+4570+4635+4540+4250 -> 61455 | AP3: Unit Type | AQ3: Number | AR3: TP $ | AS3: % | AT3: % | AW3: Building | AX3: Floors | AY3: U / Floor | AZ3: Total Units | BA3: Cost / U | BB3: Total
A4: Product | B4: Affordable | D4: 1 Br - 1 Ba | E4: =K8 -> 171 | F4: =E4/$E$8 -> 0.43846154 | H4: 2 | I4: 2 | J4: =SUM(K4:N4) -> 24 | K4: 9 | L4: 7 | M4: 8 | N4: 0 | O4: 24392 | P4: Elevators Stops | Q4: =2*3+2*3+2*2 -> 16 | R4: Count | S4: 2 Br - 2 Ba Counter | T4: =(13+13+12+12.5+6.3)*6+(8.5+16+13+7+11)*46 -> 2893.8 | U4: SF | V4: 2 Br - 2 Ba Cab | X4: SF | AA4: Building 1 | AF4: =14*7 -> 98 | AH4: Building 1 | AP4: Studios | AQ4: 0 | AR4: 3192.5 | AS4: 0 | AT4: =AR4*(1+AS4) -> 3192.5 | AW4: Building 1 | AX4: 3 | AY4: 9 | AZ4: =AY4*AX4 -> 27 | BA4: =275 -> 275 | BB4: =BA4*AZ4 -> 7425
A5: UPDATED | B5: 45630 | D5: 2 Br - 1 Ba | E5: =L8 -> 52 | F5: =E5/$E$8 -> 0.13333333 | H5: 3 | I5: 2 | J5: =SUM(K5:N5) -> 116 | K5: 52 | L5: 11 | M5: 32 | N5: 21 | O5: 128501 | P5: Trash Encl. | Q5: 14 | R5: Provided in Site Plan | S5: 3 Br - 2 Ba Counter | T5: =(15+7+4+16.82+31)*N8 -> 3617.18 | U5: SF | V5: 3 Br - 2 Ba Cab | X5: SF | AA5: Northwest | AB5: =21*4+8*8+7*6 -> 190 | AF5: =8*22 -> 176 | AH5: Northwest | AI5: 19256 | AP5: 1 Br - 1 Ba | AQ5: 171 | AR5: 3192.5 | AS5: 0 | AT5: =AR5*(1+AS5) -> 3192.5 | AW5: Building 2 | AX5: 2 | AY5: 2 | AZ5: =AY5*AX5 -> 4 | BA5: =275 -> 275 | BB5: =BA5*AZ5 -> 1100
A6: Timeline | B6: 26 | D6: 2 Br - 2 Ba | E6: =M8 -> 118 | F6: =E6/$E$8 -> 0.3025641 | H6: 4 | I6: 3 | J6: =SUM(K6:N6) -> 57 | K6: 14 | L6: 10 | M6: 22 | N6: 11 | O6: 68972 | P6: Stairs | Q6: 21 | R6: Count | S6: 1x1 Decks | T6: =86*38 -> 3268 | U6: SF | V6: Landscaping Bldg. 1 | X6: SF | AA6: Southwest | AB6: =14*4+21*2+8*6 -> 146 | AF6: =7*10 -> 70 | AH6: Southwest | AI6: 8980 | AP6: 2 Br - 1 Ba | AQ6: 52 | AR6: 3192.5 | AS6: 0 | AT6: =AR6*(1+AS6) -> 3192.5 | AW6: Building 3 | AX6: 2 | AY6: 9 | AZ6: =AY6*AX6 -> 18 | BA6: =275 -> 275 | BB6: =BA6*AZ6 -> 4950
A7: Floors | B7: 2 & 3 Levels | D7: 3 Br - 2 Ba | E7: =N8 -> 49 | F7: =E7/$E$8 -> 0.12564103 | H7: 5 | I7: 2 | J7: =SUM(K7:N7) -> 24 | K7: 9 | L7: 7 | M7: 8 | N7: 0 | O7: 24392 | P7: Pool | Q7: 1 | S7: 2x1 Decks | U7: SF | V7: Landscaping Bldg. 2 | X7: SF | AA7: Northeast | AB7: =21*2+14*2+8*6 -> 118 | AF7: =SUM(AF3:AF6) -> 491 | AH7: Northeast | AI7: 8850 | AP7: 2 Br - 2 Ba | AQ7: 118 | AR7: 3192.5 | AS7: 0.1 | AT7: =AR7*(1+AS7) -> 3511.75 | AW7: Building 4 | AX7: 3 | AY7: 3 | AZ7: =AY7*AX7 -> 9 | BA7: =275 -> 275 | BB7: =BA7*AZ7 -> 2475
A8: Bldg. SF | B8: =O8 -> 431911 | D8: Totals | E8: =SUM(E3:E7) -> 390 | F8: =E8/$E$8 -> 1 | H8: Totals | I8: =SUM(I3:I7) -> 12 | J8: =SUM(J3:J7) -> 390 | K8: =SUM(K3:K7) -> 171 | L8: =SUM(L3:L7) -> 52 | M8: =SUM(M3:M7) -> 118 | N8: =SUM(N3:N7) -> 49 | O8: =SUM(O3:O7) -> 431911 | P8: Gym | Q8: 1 | S8: Lightweight | T8: 256531 | U8: SF | V8: Landscaping Bldg. 3 | X8: SF | AA8: Southeast | AB8: =21*2+14*8+8*12+7*8 -> 306 | AH8: Southeast | AI8: 19965 | AP8: 3 Br - 2 Ba | AQ8: 49 | AR8: 3192.5 | AS8: 0.2 | AT8: =AR8*(1+AS8) -> 3831 | AW8: Building 5 | AX8: 2 | AY8: 2 | AZ8: =AY8*AX8 -> 4 | BA8: 275 | BB8: =BA8*AZ8 -> 1100
A9: Acres | B9: 15.826 | D9: Parking | P9: Iron Rail | Q9: 2728 | R9: LF | S9: Pavers | T9: 900 | U9: SF | V9: Landscaping Bldg. 4 | X9: SF | AA9: More | AB9: =21*4+8*6 -> 132 | AC9: =SUM(AB5:AB9) -> 892 | AH9: More | AI9: =5870+6250+6290+5915 -> 24325 | AJ9: =SUM(AI5:AI9) -> 81376 | AP9: Totals | AQ9: =SUM(AQ4:AQ8) -> 390 | AT9: =SUMPRODUCT(AQ4:AQ8,AT4:AT8)/AQ9 -> 3369.3154 | BB9: =SUM(BB4:BB8) -> 17050
A10: Site SF | B10: =B9*43560 -> 689380.56 | D10: Garage Parking | F10: 0 | P10: Roofing | Q10: =(62109+12359+64481+23240+12359)/100 -> 1745.48 | R10: Square | S10: Pool Deck | T10: =10114-1655-215-35*8 -> 7964 | U10: SF | V10: Landscaping Bldg. 5 | X10: SF | AT10: =AT9-AR8 -> 176.81538
A11: Buildings | B11: 5 | D11: Cover Parking | F11: 388 | P11: Stucco | Q11: 26012 | R11: Square Yard | S11: Pool Fence | T11: =67+148+90+132 -> 437 | U11: LF | V11: Corridor Bldg. 1 | W11: 19607 | X11: SF | AA11: Building 2 & 5 | AE11: Building 4 | AF11: =14*8 -> 112 | AH11: Building 2 & 5 | AL11: Building 4 | AM11: =5782+5760+8825+9150 -> 29517 | AT11: =AT10/AR8 -> 0.055384615
A12: Reports Available | D12: Open Parking | F12: 403 | P12: Livable Area | Q12: =139051+19843+101286+52253+19843 -> 332276 | R12: SF | S12: Dog Park Fence | T12: =200*2 -> 400 | U12: LF | V12: Corridor Bldg. 2 | W12: 2180 | X12: SF | AA12: Northwest | AF12: =20*8 -> 160 | AH12: Northwest
A13: Site Evaluation Report (GCW) | B13: 45062 | D13: Accessible Parking | F13: 16 | P13: Carports | Q13: =F11 -> 388 | R13: Count | S13: Common Bldg. 1 | T13: 7476 | U13: SF | V13: Corridor Bldg. 3 | W13: 14333 | X13: SF | AA13: Southwest | AF13: =8*18 -> 144 | AH13: Southwest
A14: Soils Report (Universal) | B14: N | D14: Private Garages | F14: 0 | J14: TOTAL COST | L14: =L329 -> 84590981 | P14: Stairs Landings | Q14: 60 | R14: Landings | S14: Common Bldg. 2 | T14: 0 | U14: SF | V14: Corridor Bldg. 4 | W14: 6594 | X14: SF | AA14: Northeast | AF14: =7*12 -> 84 | AH14: Northeast
A15: Alta Survey (Wallace) | B15: N | D15: Total Parking Provided | F15: =SUM(F10:F14) -> 807 | J15: PER UNIT | L15: =L14/E8 -> 216899.95 | P15: Pump House | Q15: 1 | R15: EA | S15: Common Bldg. 3 | T15: =748+1140 -> 1888 | U15: SF | V15: Corridor Bldg. 5 | W15: 2180 | X15: SF | AA15: Southeast | AB15: =21*2+14*2+8*6+7*6 -> 160 | AC15: =AB15*2 -> 320 | AF15: =SUM(AF11:AF14) -> 500 | AH15: Southeast | AI15: =5035+5775+1960+1960 -> 14730 | AJ15: =AI15*2 -> 29460
A16: Plans | B16: N | D16: Parking Ratio | F16: =SUM(F10:F13)/E8 -> 2.0692308 | J16: PER GSF | L16: =L14/B8 -> 195.85281 | P16: Lock Boxes | Q16: 10 | R16: EA | S16: Common Bldg. 4 | T16: 1557 | U16: SF | V16: BBQ | W16: 6 | X16: Count
A17: NVE Planning Memo | B17: 45043 | P17: Awning Small | Q17: 72 | R17: EA | S17: Common Bldg. 5 | T17: 0 | U17: SF | V17: Fire Pumps | W17: 1 | X17: Count | AA17: B1B Railings | AB17: =12.5*62 -> 775 | AH17: B1B Railings | AI17: =12.5*62 -> 775
P18: Awning Large | Q18: 11 | R18: EA | S18: HVAC ADD Count | T18: =(E6*250+E7*500)/E8 -> 138.46154 | V18: Asphalt | W18: =119500+43500+114500 -> 277500
A19: Description | B19: Cost Code | C19: Cost Category | D19: Sub job | E19: Source | F19: Unit Meas. | G19: Quantity | H19: Unit Cost | I19: Escalation % | J19: T. Unit Cost | K19: Sub Total | L19: Total | M19: Description / Details
A20: General Requirements | B20: 01 | L20: =K21 -> 4240149 | M20: Hard coded number
A21: General Requirements | B21: 01 | C21: S | F21: Mo | G21: =$B$6 -> 26 | H21: =4240149/26 -> 163082.65 | I21: 0 | J21: =H21*(1+I21) -> 163082.65 | K21: =J21*G21 -> 4240149
A22: Existing Conditions | B22: 02 | L22: =K23 -> 12000
A23: Potholing | B23: 02-3213 | C23: S | D23: ON-SITE | E23: Allowance | G23: 1 | H23: 12000 | I23: 0 | J23: =H23*(1+I23) -> 12000 | K23: =J23*G23 -> 12000
A24: Concrete | B24: 03 | L24: =SUM(K25:K34) -> 2934605.2
A25: Slabs | B25: 03-3101 | C25: S | D25: BUILDING | E25: Torrey Pines | F25: SF | G25: =Q2 -> 172112 | H25: 11.99 | I25: 0 | J25: =H25*(1+I25) -> 11.99 | K25: =J25*G25 -> 2063622.9 | M25: Conventional slab
A26: Deepened Footings | B26: 03-3101 | C26: S | D26: BUILDING | E26: N/A | J26: =H26*(1+I26) -> 0 | K26: =J26*G26 -> 0
A27: Concrete Slab Repairs | B27: 03-3101 | C27: RR | D27: BUILDING | E27: Allowance | F27: LS | G27: 1 | H27: =2500*3 -> 7500 | I27: 0 | J27: =H27*(1+I27) -> 7500 | K27: =J27*G27 -> 7500 | AF27: =1800+1350+1350+360+900+360+900+1080+360+450 -> 8910
A28: Pump House Concrete | B28: 03-3101 | C28: S | D28: PUMPHOUSE | E28: Torrey Pines | F28: SF | G28: 300 | H28: 11.99 | J28: =H28*(1+I28) -> 11.99 | K28: =J28*G28 -> 3597
A29: Trash Enclosure Concrete | B29: 03-3102 | C29: S | D29: OTHER SITE | E29: Torrey Pines | F29: Count | G29: =Q5 -> 14 | H29: =11031/4 -> 2757.75 | I29: 0 | J29: =H29*(1+I29) -> 2757.75 | K29: =J29*G29 -> 38608.5
A30: Pool Area Shower Concrete | B30: 03-3105 | C30: S | D30: POOL AREA | E30: Torrey Pines | F30: LS | G30: =$Q$7 -> 1 | H30: 2500 | I30: 0 | J30: =H30*(1+I30) -> 2500 | K30: =J30*G30 -> 2500
A31: Cabana Concrete | B31: 03-3107 | C31: S | D31: POOL AREA | E31: N/A | J31: =H31*(1+I31) -> 0 | K31: =J31*G31 -> 0 | AA31: Railings | AD31: Length Ea | AE31: Bldg 1 | AF31: Bldg 2 | AG31: Bldg 3 | AH31: Bldg 4 | AI31: Bldg 5
A32: Pool Equipment Foundation | B32: 03-3108 | C32: S | D32: POOL EQUIP | E32: N/A | J32: =H32*(1+I32) -> 0 | K32: =J32*G32 -> 0 | AB32: Outside Corner Units | AD32: =(21+15) -> 36 | AE32: =AD32*7*2 -> 504 | AF32: =AD32*2 -> 72 | AG32: =AD32*7 -> 252 | AH32: =AD32*8 -> 288 | AI32: 72
A33: Lightweight Concrete | B33: 03-3116 | C33: S | D33: BUILDING | E33: Torrey Pines | F33: SF | G33: =T8 -> 256531 | H33: 2.94 | I33: 0 | J33: =H33*(1+I33) -> 2.94 | K33: =J33*G33 -> 754201.14 | AB33: Inside Corner Units | AD33: 13 | AE33: =AD33*10*2 -> 260 | AF33: N/A | AG33: =AD33*8 -> 104 | AH33: =AD33*8 -> 104 | AI33: N/A
A34: Deck Concrete | B34: 03-5001 | C34: S | D34: BUILDING | E34: Torrey Pines | F34: SF | G34: =SUM($T$6:$T$7) -> 3268 | H34: 19.76 | I34: 0 | J34: =H34*(1+I34) -> 19.76 | K34: =J34*G34 -> 64575.68 | AB34: Small Railings | AD34: 8 | AE34: =AD34*52 -> 416 | AF34: =AD34*12 -> 96 | AG34: =AD34*28 -> 224 | AH34: =AD34*30 -> 240 | AI34: 96
A35: Parking Garage | B35: 03-G | L35: =SUM(K36:K43) -> 0 | AE35: =SUM(AE32:AE34) -> 1180 | AF35: =SUM(AF32:AF34) -> 168 | AG35: =SUM(AG32:AG34) -> 580 | AH35: =SUM(AH32:AH34) -> 632 | AI35: =SUM(AI32:AI34) -> 168 | AJ35: =SUM(AE35:AI35) -> 2728
A36: Parking Garage Structure | C36: S | E36: N/A | J36: =H36*(1+I36) -> 0 | K36: =J36*G36 -> 0
A37: Core Slab Precast Concrete | C37: S | E37: N/A | J37: =H37*(1+I37) -> 0 | K37: =J37*G37 -> 0 | AA37: Lightweight | AE37: Bldg 1 | AF37: Bldg 2 | AG37: Bldg 3 | AH37: Bldg 4 | AI37: Bldg 5
A38: Concrete Slab on Grade | C38: S | E38: N/A | J38: =H38*(1+I38) -> 0 | K38: =J38*G38 -> 0 | AB38: Level 2 | AD38: SF | AE38: =62029-860-2726 -> 58443 | AF38: =12359-669 -> 11690 | AG38: =64481-860-2888 -> 60733 | AH38: =23222-344-1206 -> 21672 | AI38: =12359-669 -> 11690
A39: Concrete Topping Slab 4" / Level | C39: S | E39: N/A | J39: =H39*(1+I39) -> 0 | K39: =J39*G39 -> 0 | AB39: Level 3 | AD39: SF | AE39: =62109-860-2827 -> 58422 | AF39: N/A | AG39: N/A | AH39: =23240-344-1224 -> 21672 | AI39: N/A
A40: Electrical | C40: S | E40: N/A | J40: =H40*(1+I40) -> 0 | K40: =J40*G40 -> 0 | AB40: Total | AD40: SF | AE40: =SUM(AE38:AE39) -> 116865 | AF40: =SUM(AF38:AF39) -> 11690 | AG40: =SUM(AG38:AG39) -> 60733 | AH40: =SUM(AH38:AH39) -> 43344 | AI40: =SUM(AI38:AI39) -> 11690 | AJ40: =SUM(AE40:AI40) -> 244322
A41: Dry Sprinklers | C41: S | E41: N/A | J41: =H41*(1+I41) -> 0 | K41: =J41*G41 -> 0
A42: Mechanical Ventilation | C42: S | E42: N/A | J42: =H42*(1+I42) -> 0 | K42: =J42*G42 -> 0
A43: Stairs and Railings | C43: S | E43: N/A | J43: =H43*(1+I43) -> 0 | K43: =J43*G43 -> 0
A44: Masonry | B44: 04 | L44: =SUM(K45:K49) -> 246800
A45: Elevator Shaft | B45: 04-2201 | C45: S | D45: BUILDING | E45: Torrey Pines | F45: Per Stop | G45: =Q4 -> 16 | H45: 9500 | I45: 0 | J45: =H45*(1+I45) -> 9500 | K45: =J45*G45 -> 152000
A46: Trash Enclosure | B46: 04-2202 | C46: S | D46: OTHER SITE | E46: Torrey Pines | F46: Count | G46: =$Q$5 -> 14 | H46: 5700 | I46: 0 | J46: =H46*(1+I46) -> 5700 | K46: =J46*G46 -> 79800
A47: Masonry Veneer | B47: 04-4301 | C47: S | D47: ON-SITE | E47: N/A | J47: =H47*(1+I47) -> 0 | K47: =J47*G47 -> 0
A48: Masonry Veneer Pool Area | B48: 04-4305 | C48: S | D48: POOL AREA | E48: Russell IV | F48: LS | G48: =$Q$7 -> 1 | H48: 6000 | I48: 0 | J48: =H48*(1+I48) -> 6000 | K48: =J48*G48 -> 6000
A49: Pool Eq. Shower Stone | B49: 04-4306 | C49: A | D49: POOL EQUIP | E49: Torrey Pines | F49: LS | G49: =$Q$7 -> 1 | H49: 9000 | I49: 0 | J49: =H49*(1+I49) -> 9000 | K49: =J49*G49 -> 9000
A50: Metals | B50: 05 | L50: =SUM(K51:K58) -> 522166
A51: Structural Steel | B51: 05-1201 | C51: S | D51: BUILDING | E51: Allowance | F51: LS | G51: 1 | H51: 125000 | I51: 0 | J51: =H51*(1+I51) -> 125000 | K51: =J51*G51 -> 125000 | M51: Bldg 1 only
A52: Elevator Shaft Iron | B52: 05-1202 | C52: S | D52: BUILDING | E52: Torrey Pines | F52: Count | G52: =$Q$3 -> 6 | H52: 4040 | I52: 0 | J52: =H52*(1+I52) -> 4040 | K52: =J52*G52 -> 24240
A53: Stair Handrails | B53: 05-5201 | C53: S | D53: BUILDING | E53: Torrey Pines | F53: Per Level | G53: =Q14 -> 60 | H53: 2000 | I53: 0 | J53: =H53*(1+I53) -> 2000 | K53: =J53*G53 -> 120000
A54: Garage Stair Railings | B54: 05-5201 | C54: S | D54: BUILDING | E54: N/A | H54: 0 | I54: 0 | J54: =H54*(1+I54) -> 0 | K54: =J54*G54 -> 0
A55: Cabana Iron | B55: 05-7004 | C55: S | D55: POOL AREA | E55: N/A | H55: 0 | I55: 0 | J55: =H55*(1+I55) -> 0 | K55: =J55*G55 -> 0
A56: Pool Equipment Gate | B56: 05-7005 | C56: S | D56: POOL EQUIP | E56: Torrey Pines | F56: Count | G56: =$Q$7 -> 1 | H56: 1950 | I56: 0 | J56: =H56*(1+I56) -> 1950 | K56: =J56*G56 -> 1950
A57: Iron Railings | B57: 05-7300 | C57: S | D57: BUILDING | E57: Torrey Pines | F57: LF | G57: =$Q$9 -> 2728 | H57: 92 | I57: 0 | J57: =H57*(1+I57) -> 92 | K57: =J57*G57 -> 250976
A58: Cable Railings | B58: 05-7316 | C58: S | D58: COMMON AREA | E58: N/A | H58: 0 | I58: 0 | J58: =H58*(1+I58) -> 0 | K58: =J58*G58 -> 0
A59: Wood, Plastics, & Composites | B59: 06 | L59: =SUM(K60:K71) -> 10820813
A60: Dumpsters | B60: 06-0111 | C60: S | D60: DUMPSTERS | H60: 79 | I60: 0 | J60: =H60*(1+I60) -> 79 | K60: =J60*G60 -> 0
A61: Framing | B61: 06-1100 | C61: S | D61: BUILDING | E61: See Note | F61: SF | G61: =B8 -> 431911 | H61: 20.96 | I61: 0 | J61: =H61*(1+I61) -> 20.96 | K61: =J61*G61 -> 9052854.6 | M61: 12 Month Moving Average
A62: Framing - Crane | B62: 06-1100 | C62: S | D62: BUILDING | E62: N/A | I62: 0 | J62: =H62*(1+I62) -> 0 | K62: =J62*G62 -> 0
A63: Cabana Framing | B63: 06-1109 | C63: S | D63: COMMON AREA | E63: N/A | I63: 0 | J63: =H63*(1+I63) -> 0 | K63: =J63*G63 -> 0
A64: BBQ Framing | B64: 06-1110 | C64: S | D64: COMMON AREA | E64: Allowance | F64: LS | G64: =$W$16 -> 6 | H64: 2500 | I64: 0 | J64: =H64*(1+I64) -> 2500 | K64: =J64*G64 -> 15000
A65: Fireplace Framing | B65: 06-1111 | C65: S | D65: COMMON AREA | E65: N/A | I65: 0 | J65: =H65*(1+I65) -> 0 | K65: =J65*G65 -> 0
A66: Trellis | B66: 06-1114 | C66: S | D66: BUILDING | E66: N/A | I66: 0 | J66: =H66*(1+I66) -> 0 | K66: =J66*G66 -> 0
A67: Pool Equipment Framing | B67: 06-1114 | C67: S | D67: POOL EQUIP | E67: N/A | I67: 0 | J67: =H67*(1+I67) -> 0 | K67: =J67*G67 -> 0
A68: Finish Carpentry - Units | B68: 06-2001 | C68: S | D68: BUILDING | E68: Torrey Pines | F68: LSF | G68: =Q12 -> 332276 | H68: 4.3044537 | I68: 0 | J68: =H68*(1+I68) -> 4.3044537 | K68: =J68*G68 -> 1430266.6
A69: Finish Carpentry - Common | B69: 06-2001 | C69: S | D69: COMMON AREA | E69: Torrey Pines | F69: Common SF | G69: =B8-Q12 -> 99635 | H69: 3.1664785 | I69: 0 | J69: =H69*(1+I69) -> 3.1664785 | K69: =J69*G69 -> 315492.08
A70: BBQ Trim | B70: 06-2006 | C70: S | D70: COMMON AREA | E70: Allowance | F70: LS | G70: =$W$16 -> 6 | H70: 1200 | I70: 0 | J70: =H70*(1+I70) -> 1200 | K70: =J70*G70 -> 7200
A71: Shutters | B71: 06-4919 | C71: S | D71: BUILDING | E71: N/A | I71: 0 | J71: =H71*(1+I71) -> 0 | K71: =J71*G71 -> 0
A72: Thermal & Moisture Protection | B72: 07 | L72: =SUM(K73:K83) -> 2429272.6
A73: Insulation | B73: 07-2101 | C73: S | D73: BUILDING | E73: Torrey Pines | F73: SF | G73: =B8 -> 431911 | H73: 2.7 | I73: 0 | J73: =H73*(1+I73) -> 2.7 | K73: =J73*G73 -> 1166159.7
A74: Roofing | B74: 07-3001 | C74: S | D74: BUILDING | E74: Torrey Pines | F74: Square | G74: =Q10 -> 1745.48 | H74: 603 | I74: 0 | J74: =H74*(1+I74) -> 603 | K74: =J74*G74 -> 1052524.4
A75: Cabana Roofing | B75: 07-3002 | C75: S | D75: COMMON AREA | E75: N/A | I75: 0 | J75: =H75*(1+I75) -> 0 | K75: =J75*G75 -> 0
A76: Pump House Roofing | B76: 07-3002 | C76: S | D76: PUMPHOUSE | E76: Allowance | F76: LS | G76: 1 | H76: 7500 | I76: 0 | J76: =H76*(1+I76) -> 7500 | K76: =J76*G76 -> 7500
A77: Pool Equipment Roofing | B77: 07-3003 | C77: S | D77: POOL EQUIP | E77: Allowance | F77: LS | G77: =Q7 -> 1 | H77: 7500 | I77: 0.2 | J77: =H77*(1+I77) -> 9000 | K77: =J77*G77 -> 9000 | M77: Baja Cover. Added 20% escalation due to Baja company sold to equity firm.
A78: Trash Enclosure Cover | B78: 07-6101 | C78: S | D78: OTHER SITE | E78: Decatur | F78: Count | G78: =$Q$5 -> 14 | H78: 5800 | I78: 0.2 | J78: =H78*(1+I78) -> 6960 | K78: =J78*G78 -> 97440 | M78: Baja Cover. Added 20% escalation due to Baja company sold to equity firm.
A79: Pigeon Proofing | B79: 07-7001 | C79: S | D79: BUILDING | E79: Torrey Pines | F79: SF | G79: =$B$8 -> 431911 | H79: 0.08 | I79: 0 | J79: =H79*(1+I79) -> 0.08 | K79: =J79*G79 -> 34552.88
A80: Gutters and Downspouts | B80: 07-7124 | C80: S | D80: BUILDING | E80: Torrey Pines | F80: SF | G80: =$B$8 -> 431911 | H80: 0.05 | I80: 0 | J80: =H80*(1+I80) -> 0.05 | K80: =J80*G80 -> 21595.55
A81: Roof Ladders | B81: 07-7210 | C81: S | D81: BUILDING | E81: Torrey Pines | F81: Count | G81: =2*$B$11 -> 10 | H81: 1550 | I81: 0 | J81: =H81*(1+I81) -> 1550 | K81: =J81*G81 -> 15500 | M81: 2 Per building
A82: Roof Access Doors | B82: 07-7233 | C82: S | D82: BUILDING | E82: Torrey Pines | F82: Count | G82: =2*$B$11 -> 10 | H82: 2500 | I82: 0 | J82: =H82*(1+I82) -> 2500 | K82: =J82*G82 -> 25000 | M82: 2 Per building
A83: Roof Winch | B83: 07-7250 | C83: S | D83: BUILDING | E83: N/A | I83: 0 | J83: =H83*(1+I83) -> 0 | K83: =J83*G83 -> 0
A84: Openings | B84: 08 | L84: =SUM(K85:K99) -> 639799.79
A85: Dumpsters | B85: 08-0151 | C85: S | D85: DUMPSTERS | H85: 79 | I85: 0 | J85: =H85*(1+I85) -> 79 | K85: =J85*G85 -> 0
A86: Entry Doors | B86: 08-1001 | C86: S | D86: COMMON AREA | E86: N/A | I86: 0 | J86: =H86*(1+I86) -> 0 | K86: =J86*G86 -> 0
A87: Common Doors | B87: 08-1002 | C87: S | D87: COMMON AREA | E87: Included | I87: 0 | J87: =H87*(1+I87) -> 0 | K87: =J87*G87 -> 0
A88: Pocket Doors - 3 Panel | B88: 08-1002 | C88: S | D88: BUILDING | E88: N/A | I88: 0 | J88: =H88*(1+I88) -> 0 | K88: =J88*G88 -> 0
A89: Garage Doors | B89: 08-3619 | C89: S | D89: BUILDING | E89: N/A | I89: 0 | J89: =H89*(1+I89) -> 0 | K89: =J89*G89 -> 0
A90: Windows and Sliding Glass Doors | B90: 08-5301 | C90: S | D90: BUILDING | E90: Torrey Pines | F90: Per Unit | G90: =$E$8 -> 390 | H90: 1157.8947 | I90: 0.15 | J90: =H90*(1+I90) -> 1331.5789 | K90: =J90*G90 -> 519315.79 | M90: Included the latest efficiency requirement. 15% escalation with more bedrooms/windows expected.
A91: Windows Repair and Replacement | B91: 08-5301 | C91: RR | D91: BUILDING | E91: Allowance | F91: Per Unit | G91: =$E$8 -> 390 | H91: 75 | I91: 0 | J91: =H91*(1+I91) -> 75 | K91: =J91*G91 -> 29250
A92: Pool Equipment Windows | B92: 08-5303 | C92: S | D92: POOL EQUIP | E92: N/A | I92: 0 | J92: =H92*(1+I92) -> 0 | K92: =J92*G92 -> 0
A93: Pool Glass Walls | B93: 08-8001 | C93: S | D93: POOL AREA | E93: N/A | I93: 0 | J93: =H93*(1+I93) -> 0 | K93: =J93*G93 -> 0
A94: Fixed Glass | B94: 08-8002 | C94: S | D94: BUILDING | E94: N/A | I94: 0 | J94: =H94*(1+I94) -> 0 | K94: =J94*G94 -> 0
A95: Mirrors - LED | B95: 08-8301 | C95: S | D95: BUILDING | E95: N/A | I95: 0 | J95: =H95*(1+I95) -> 0 | K95: =J95*G95 -> 0
A96: Mirrors - LED Install | B96: 08-8302 | C96: S | D96: BUILDING | E96: N/A | I96: 0 | J96: =H96*(1+I96) -> 0 | K96: =J96*G96 -> 0
A97: Mirrors - Framed | B97: 08-8301 | C97: S | D97: BUILDING | E97: N/A | I97: 0 | J97: =H97*(1+I97) -> 0 | K97: =J97*G97 -> 0
A98: Mirrors - Polished Edges (Units) | B98: 08-8301 | C98: S | D98: BUILDING | E98: Pebble | F98: Unit | G98: =J8+M8+N8 -> 557 | H98: 162 | I98: 0 | J98: =H98*(1+I98) -> 162 | K98: =J98*G98 -> 90234
A99: Mirrors - Polished Edges (Restrooms) | B99: 08-8301 | C99: S | D99: BUILDING | E99: Allowance | F99: Count | G99: 4 | H99: 250 | I99: 0 | J99: =H99*(1+I99) -> 250 | K99: =J99*G99 -> 1000
A100: Finishes | B100: 09 | L100: =SUM(K101:K136) -> 7023592.8
...

Sheet What changed
A1: West Henderon
A2: Summary of Budget Changes
A4: Line Item | B4: Level 2 | C4: Level 3 | D4: Difference | E4: UC | F4: Budget Change | G4: Details
A6: Concrete
A7: Concrete Slab | B7: ='Level 1.1 UPDATE B'!Q2 -> 149760 | C7: ='Level 3'!Q2 -> 145399.85 | D7: =B7-C7 -> 4360.15 | E7: ='Level 3'!H24 -> 9.5 | F7: =E7*D7 -> 41421.425 | G7: New Take Off
A8: Concrete Slab | B8: ='Level 1.1 UPDATE B'!H25 -> 11.99 | C8: ='Level 3'!H24 -> 9.5 | D8: =B8-C8 -> 2.49 | E8: ='Level 3'!Q2 -> 145399.85 | F8: =E8*D8 -> 362045.63 | G8: Proposal from NRC at $9.16 (aggressive proposal)
A9: Cabana Concrete -Sunked Seating | B9: ='Level 1.1 UPDATE B'!K31 -> 18399 | C9: ='Level 3'!K30 -> 35000 | D9: =B9-C9 -> -16601 | E9: 1 | F9: =E9*D9 -> -16601 | G9: Added Sunked Seating $25k per area (3).
A10: Lightweight SF | B10: ='Level 1.1 UPDATE B'!H33 -> 2.8 | C10: ='Level 3'!H32 -> 2.6 | D10: =B10-C10 -> 0.2 | E10: ='Level 3'!G32 -> 261305.65 | F10: =E10*D10 -> 52261.13 | G10: Based on NV Gypsum proposal.
A11: Deck | B11: ='Level 1.1 UPDATE B'!H34 -> 19.76 | C11: ='Level 3'!H33 -> 20.525068 | D11: =B11-C11 -> -0.76506775 | E11: ='Level 3'!G33 -> 3440 | F11: =E11 -> 3440 | G11: Latest Bruner pricing
F12: =SUM(F7:F11) -> 442567.18
A14: Wood, Plastics, & Composites
A15: Framing SF | B15: ='Level 1.1 UPDATE B'!B8 -> 426549 | C15: ='Level 3'!B8 -> 422635 | D15: =B15-C15 -> 3914 | E15: ='Level 3'!H52 -> 17.716624 | F15: =E15*D15 -> 69342.866 | G15: Change in total buildgs SF in new plan.
A16: Framing $ | B16: ='Level 1.1 UPDATE B'!H61 -> 18.9 | C16: ='Level 3'!H52 -> 17.716624 | D16: =B16-C16 -> 1.1833761 | E16: ='Level 3'!B8 -> 422635 | F16: =E16*D16 -> 500136.17 | G16: Proposal from Gilmore at $17.36
A17: ='Level 3'!A59 -> Finish Carpentry - Units | B17: 5.22095 | C17: ='Level 3'!H59 -> 3.55 | D17: =B17-C17 -> 1.67095 | E17: ='Level 3'!G59 -> 329873 | F17: =E17*D17 -> 551201.3 | G17: Original price was Bruner/unit + 10% for extra rooms. New pricing is based on 2 proposals.
A18: ='Level 3'!A60 -> Finish Carpentry - Common | B18: ='Level 1.1 UPDATE B'!H69 -> 3.1664785 | C18: ='Level 3'!H60 -> 5.7148858 | D18: =B18-C18 -> -2.5484073 | E18: ='Level 3'!G60 -> 87842 | F18: =E18*D18 -> -223857.2 | G18: New pricing is based on proposal cost / sf.
F19: =SUM(F15:F18) -> 896823.13
A21: Thermal & Moisture Protection
A22: Roofing | B22: ='Level 1.1 UPDATE B'!G74 -> 1497.6 | C22: ='Level 3'!G67 -> 1734.0111 | D22: =B22-C22 -> -236.4111 | E22: ='Level 3'!H67 -> 572.53228 | F22: =E22*D22 -> -135352.99 | G22: New plans take off with parapet walls included.
A23: Roofing % | B23: ='Level 1.1 UPDATE B'!H74 -> 596 | C23: ='Level 3'!H67 -> 572.53228 | D23: =B23-C23 -> 23.467717 | E23: ='Level 3'!Q10 -> 1734.0111 | F23: =E23*D23 -> 40693.282
F24: =F22+F23 -> -94659.704
A26: Finishes
A27: Stucco SF | B27: ='Level 1.1 UPDATE B'!G107 -> 22444 | C27: ='Level 3'!G100 -> 28186.002 | D27: =B27-C27 -> -5742.002 | E27: ='Level 3'!H100 -> 39.311357 | F27: =E27*D27 -> -225725.89 | G27: Takeoff based on plans yielded 5,742 sf more than previous.
A28: Drywall SF | B28: =B15 -> 426549 | C28: =C15 -> 422635 | D28: =B28-C28 -> 3914 | E28: ='Level 1.1 UPDATE A'!H114 -> 8.02 | F28: =E28*D28 -> 31390.28 | G28: Efficiency on change of Bldg SF
A29: Drywall $ | B29: ='Level 1.1 UPDATE B'!H114 -> 7.7 | C29: ='Level 3'!H107 -> 7.6967218 | D29: =B29-C29 -> 0.0032782425 | E29: 422635 | F29: =E29*D29 -> 1385.5 | G29: Change in Pricing Based on Bruner
A30: Flooring - Units | B30: ='Level 1.1 UPDATE B'!H121 -> 20.97 | C30: ='Level 3'!H114 -> 17.1 | D30: =B30-C30 -> 3.87 | E30: ='Level 3'!G114 -> 36652.556 | F30: =E30*D30 -> 141845.39
F31: =SUM(F27:F30) -> -51104.723
A33: Specialties
A34: Mail Boxes | B34: ='Level 1.1 UPDATE B'!H152 -> 153 | C34: ='Level 3'!H145 -> 230.28205 | D34: =B34-C34 -> -77.282051 | E34: ='Level 3'!G145 -> 390 | F34: =E34*D34 -> -30140 | G34: Took off 10% for color upgrade
A35: Closet Shelving | B35: ='Level 1.1 UPDATE B'!H153 -> 220 | C35: ='Level 3'!H146 -> 425.64103 | D35: =B35-C35 -> -205.64103 | E35: ='Level 3'!G146 -> 390 | F35: =E35*D35 -> -80200 | G35: Level 1 TP vs Level 2 based on proposal.
F36: =SUM(F34:F35) -> -110340
A38: Equipment
A39: Appliances | B39: ='Level 1.1 UPDATE B'!H157 -> 3044 | C39: ='Level 3'!H150 -> 3169.7043 | D39: =B39-C39 -> -125.70433 | E39: ='Level 3'!E8 -> 390 | F39: =E39*D39 -> -49024.689 | G39: Based on Torrey Pines pricing.
A41: Conveying Equipment
A42: Elevators Stops | B42: ='Level 1.1 UPDATE B'!H175 -> 35546.667 | C42: ='Level 3'!H167 -> 41250 | D42: =B42-C42 -> -5703.3333 | E42: 12 | F42: =E42*D42 -> -68440 | G42: Otis proposal.
A44: Plumbing
A45: 2 Bathroom Unit | B45: ='Level 1.1 UPDATE B'!H183 -> 13089.7 | C45: ='Level 3'!H175 -> 15600 | D45: =B45-C45 -> -2510.3 | E45: ='Level 3'!G175 -> 163 | F45: =E45*D45 -> -409178.9 | G45: Original calculated cost based on historical. Initial proposal indicates significantly higher.
A47: Electrical
A48: Electrical | B48: ='Level 1.1 UPDATE B'!H191 -> 10.06 | C48: ='Level 3'!J183 -> 11.327125 | D48: =B48-C48 -> -1.2671255 | E48: ='Level 3'!B8 -> 422635 | F48: =E48*D48 -> -535531.57 | G48: Added 5% due to Sigma reported prince increase in Romex for Bruner.
A49: Street Lights | B49: ='Level 1.1 UPDATE B'!K200 -> 275000 | C49: ='Level 3'!K191 -> 315398.25 | D49: =B49-C49 -> -40398.25 | E49: 1 | F49: =E49*D49 -> -40398.25 | G49: Plan calls for 16 rather than 11 original budgeted.
F50: =F49+F48 -> -575929.82
A52: Communications
A53: Fire Alarm / Two Way Com | B53: ='Level 1.1 UPDATE B'!H216 -> 1.9380121 | C53: ='Level 3'!H206 -> 2.25 | D53: =B53-C53 -> -0.31198791 | E53: ='Level 3'!G206 -> 422635 | F53: =E53*D53 -> -131857.01 | G53: Updated to Proposal. Per NFP Henderson carries significatly ($100K) higher fees for permit.
A55: Exterior Improvements
A56: Concrete Flatwork | B56: ='Level 1.1 UPDATE B'!K237 -> 213532 | C56: ='Level 3'!K228 -> 318423 | D56: =B56-C56 -> -104891 | E56: 1 | F56: =E56*D56 -> -104891 | G56: Plan takeoff yieled significant more (4' sidewalk vs 3.5" sidewalk.)
A57: Retaining Walls | B57: ='Level 1.1 UPDATE B'!K254 -> 192605 | C57: ='Level 3'!K245 -> 100231.34 | D57: =B57-C57 -> 92373.658 | E57: 1 | F57: =E57*D57 -> 92373.658 | G57: Based on take offs and updated pricing.
A58: Landscaping SF | B58: ='Level 1.1 UPDATE B'!G257 -> 172517 | C58: ='Level 3'!G248 -> 304972.92 | D58: =B58-C58 -> -132455.92 | E58: ='Level 3'!H248 -> 7.5062348 | F58: =E58*D58 -> -994245.23 | G58: Latest Torrey Pines pricing. Alpha proposal is at $2.5M or $8.43 $/sf
A59: Offsite Paving | B59: ='Level 1.1 UPDATE B'!K261 -> 1646980.5 | C59: ='Level 3'!K252 -> 1006389.8 | D59: =B59-C59 -> 640590.7 | E59: 1 | F59: =E59*D59 -> 640590.7 | G59: Removed 1" UTAC $600k (not in the plans or bids), 12k lf less in paving at Larson $200k.
A60: Offsite Concrete Flatwork | B60: ='Level 1.1 UPDATE B'!K263 -> 84819 | C60: ='Level 3'!K254 -> 173092 | D60: =B60-C60 -> -88273 | E60: 1 | F60: =E60*D60 -> -88273 | G60: 10" sidewalk at offsites.
F61: =SUM(F56:F60) -> -454444.87
A63: Utilities
A64: Offsite Water | B64: ='Level 1.1 UPDATE B'!K277 -> 1538312.2 | C64: ='Level 3'!K270 -> 1635293.3 | D64: =B64-C64 -> -96981.119 | E64: =D64*'Level 1'!G254 -> -96981.119 | F64: =E64 -> -96981.119 | G64: 2 above ground Turbine ($120k) + 1,275 LF line for future use Larson/LV Blvd.
A65: Offsite Sewer | B65: ='Level 1.1 UPDATE B'!K278 -> 731659 | C65: ='Level 3'!K271 -> 436684.18 | D65: =B65-C65 -> 294974.82 | E65: =D65*'Level 1'!G255 -> 294974.82 | F65: =E65 -> 294974.82 | G65: Plan shows 72" Manhole versus 48" previous concensus.
F66: =F65+F64 -> 197993.7
A68: Percentages Items
A69: General Conditions | B69: ='Level 1.1 UPDATE B'!K21 -> 3747174.6 | C69: ='Level 3'!K20 -> 3857213.7 | D69: =B69-C69 -> -110039.08 | F69: =D69 -> -110039.08
A70: Bid Risk | B70: ='Level 1.1 UPDATE B'!K308 -> 1228606 | C70: ='Level 3'!K292 -> 632953.91 | D70: =B70-C70 -> 595652.09 | F70: =D70 -> 595652.09
A71: Contingency | B71: ='Level 1.1 UPDATE B'!K325 -> 3747174.6 | C71: ='Level 3'!K309 -> 3389277.9 | D71: =B71-C71 -> 357896.71 | F71: =D71 -> 357896.71
A72: Bonds and GL | B72: ='Level 1.1 UPDATE B'!L326+'Level 1.1 UPDATE B'!L328 -> 1370860 | C72: ='Level 3'!K311+'Level 3'!L316 -> 1007077.9 | D72: =B72-C72 -> 363782.07 | F72: =D72 -> 363782.07
A73: Overhead | B73: ='Level 1.1 UPDATE B'!K333 -> 1308097.7 | C73: ='Level 3'!K317 -> 1298708.5 | D73: =B73-C73 -> 9389.2123 | F73: =D73 -> 9389.2123
A74: Contractor Fee | B74: ='Level 1.1 UPDATE B'!K334 -> 3924293 | C74: ='Level 3'!K318 -> 3896125.4 | D74: =B74-C74 -> 28167.637 | F74: =D74 -> 28167.637
F75: =SUM(F69:F74) -> 1244848.6
A77: Explained Difference | F77: =F12+F19+F24+F31+F36+F39+F42+F45+F50+F53+F61+F66+F75 -> 837252.94

Sheet Comparison to Other
M1: SENIOR / AFFORABLE PROJECTS
C2: West Henderson | M2: Bruner | N2: South Nellis | O2: Torrey Pines | P2: Decatur | Q2: Pebble
A3: Budget | E3: Units | F3: ='Level 3'!$E$8 -> 390 | M3: 194 | N3: 50 | O3: 190 | P3: 276 | Q3: 195
A4: Proposal | E4: GSF | F4: ='Level 3'!$B$8 -> 422635 | M4: 196289 | N4: 34388 | O4: 188825 | P4: 258464 | Q4: 184108
A5: Contract | E5: Acres | F5: ='Level 3'!$B$9 -> 15.826 | M5: 4.9 | N5: 1.3 | O5: 5 | P5: 9.45 | Q5: 5
E6: Site SF | F6: =F5*43560 -> 689380.56 | H6: Proposals | M6: =M5*43560 -> 213444 | N6: =N5*43560 -> 56628 | O6: =O5*43560 -> 217800 | P6: 411642 | Q6: 217800
A7: Description | B7: % | C7: Cost | D7: UOM | E7: U | F7: PU | H7: Low | I7: 2nd | J7: 3rd | K7: Ave | M7: PU | N7: PU | O7: PU | P7: PU | Q7: PU
A8: Framing | B8: =C8/$C$30 -> 0.096768933 | C8: =VLOOKUP(A8,'Level 3'!$A$20:$K$318,11,FALSE) -> 7487665.3 | D8: SF | E8: =$F$4 -> 422635 | F8: =C8/E8 -> 17.716624 | H8: =7079693/F4 -> 16.751317 | I8: =7552189/F4 -> 17.869294 | J8: =7831114/F4 -> 18.52926 | K8: =AVERAGE(H8:J8) -> 17.716624 | M8: 18.68 | N8: 20.075375 | O8: 19.921525 | P8: 22.888453 | Q8: 19.011015
A9: Electrical | B9: =C9/$C$30 -> 0.061869228 | C9: =VLOOKUP(A9,'Level 3'!$A$24:$K$289,11,FALSE) -> 4787239.7 | D9: SF (Bldg) | E9: =$F$4 -> 422635 | F9: =C9/E9 -> 11.327125 | H9: =4522456/F4 -> 10.700619 | I9: =4885000/F4 -> 11.558437 | J9: =4954263/F4 -> 11.722321 | K9: =AVERAGE(H9:J9) -> 11.327125 | M9: 10.06 | N9: 12.504362 | O9: 9.2699537 | P9: 10.176018 | Q9: 12.13429
A10: HVAC Standard | B10: =C10/$C$30 -> 0.053216756 | C10: =VLOOKUP(A10,'Level 3'!$A$24:$K$289,11,FALSE) -> 4117739.5 | D10: Unit | E10: =$F$3 -> 390 | F10: =C10/E10 -> 10558.306 | H10: =3956000/F3 -> 10143.59 | I10: =4279479/F3 -> 10973.023 | J10: =5843500/F3 -> 14983.333 | K10: =AVERAGE(H10:J10) -> 12033.315 | M10: 9875 | N10: 10148.68 | O10: 9739.2737 | P10: 10104.674 | Q10: 9218.2513
A11: Drywall | B11: =C11/$C$30 -> 0.042039813 | C11: =VLOOKUP(A11,'Level 3'!$A$24:$K$289,11,FALSE) -> 3252904 | D11: SF (Bldg) | E11: =$F$4 -> 422635 | F11: =C11/E11 -> 7.6967218 | H11: =2957435/F4 -> 6.9976102 | I11: =3230728/F4 -> 7.6442509 | J11: =3570549/F4 -> 8.4483041 | K11: =AVERAGE(H11:J11) -> 7.6967218 | M11: 7.2940664 | N11: 7.7384864 | O11: 8.0157077 | P11: 7.3585311 | Q11: 8.0768353
A12: Plumbing | B12: =C12/$C$30 -> 0.062932989 | C12: ='Level 3'!K174+'Level 3'!K175 -> 4869550 | D12: Unit | E12: =F3 -> 390 | F12: =C12/E12 -> 12486.026 | H12: =4712570/F3 -> 12083.513 | I12: =4819464/F3 -> 12357.6 | J12: =5300761/F3 -> 13591.695 | K12: =AVERAGE(H12:J12) -> 12677.603 | M12: 10069 | N12: 10196.24 | O12: 10526.311 | P12: 11042.514 | Q12: =1959791/$Q$3 -> 10050.21
A13: Site Landscaping | B13: =C13/$C$30 -> 0.029585094 | C13: =VLOOKUP(A13,'Level 3'!$A$24:$K$289,11,FALSE) -> 2289198.3 | D13: Lands SF | E13: ='Level 3'!$G$248 -> 304972.92 | F13: =C13/$E$13 -> 7.5062348 | H13: =2066905/E13 -> 6.7773394 | I13: =2326357/E13 -> 7.6280773 | J13: =2474333/E13 -> 8.1132876 | K13: =AVERAGE(H13:J13) -> 7.5062348 | M13: 13.681367 | N13: 10.5 | O13: 12.007558 | P13: 13.483701 | Q13: 21.389001
A14: Slabs | B14: =C14/$C$30 -> 0.017851598 | C14: =VLOOKUP(A14,'Level 3'!$A$24:$K$289,11,FALSE) -> 1381298.6 | D14: SF (Slab) | E14: ='Level 3'!$Q$2 -> 145399.85 | F14: =C14/E14 -> 9.5 | H14: =1332040/E14 -> 9.1612199 | I14: =1842669/E14 -> 12.673115 | J14: =1985086/E14 -> 13.6526 | K14: =AVERAGE(H14:J14) -> 11.828978 | M14: 11.11 | N14: 16.778816 | O14: 11.989967 | P14: 15.882903 | Q14: 16.060895
A15: Appliances | B15: =C15/$C$30 -> 0.016774987 | C15: =VLOOKUP(A15,'Level 3'!$A$24:$K$289,11,FALSE) -> 1297993.9 | D15: Unit | E15: =$F$3 -> 390 | F15: =C15/E15 -> 3328.1895 | M15: =614922.64/194 -> 3169.7043 | N15: 3064.485 | O15: 3488.5 | P15: 3454.4783 | Q15: 3201.4974
A16: Cabinets Units | B16: =C16/$C$30 -> 0.015486048 | C16: =VLOOKUP(A16,'Level 3'!$A$24:$K$289,11,FALSE) -> 1198260 | D16: Unit | E16: =$F$3 -> 390 | F16: =C16/E16 -> 3072.4615 | M16: =805148/194 -> 4150.2474 | N16: 1985.2 | O16: 3778.0053 | P16: 3705.4275 | Q16: 3113.7333
A17: Finish Carpentry - Units | B17: =C17/$C$30 -> 0.015134381 | C17: =VLOOKUP(A17,'Level 3'!$A$24:$K$289,11,FALSE) -> 1171049.1 | D17: Unit | E17: =F3 -> 390 | F17: =C17/F3 -> 3002.6901 | H17: =1064161/E17 -> 2728.6179 | I17: =1170454/E17 -> 3001.1641 | J17: =2091068/E17 -> 5361.7128 | K17: =AVERAGE(H17:J17) -> 3697.165 | M17: 2607.1546 | N17: 2710.9005 | O17: 3210.0359 | P17: 2983.3587 | Q17: 3081.2324
A18: Insulation | B18: =C18/$C$30 -> 0.012996863 | C18: =VLOOKUP(A18,'Level 3'!$A$24:$K$289,11,FALSE) -> 1005655 | D18: SF (Bldg) | E18: =$F$4 -> 422635 | F18: =C18/E18 -> 2.3794882 | H18: =939882/E18 -> 2.2238622 | I18: =998750/E18 -> 2.3631502 | J18: =1078333/E18 -> 2.5514522 | K18: =AVERAGE(H18:J18) -> 2.3794882 | M18: 2.5 | N18: 2.5423113 | O18: 2.6983715 | P18: 2.2715182 | Q18: 2.5011406
A19: Stucco | B19: =C19/$C$30 -> 0.014319935 | C19: =VLOOKUP(A19,'Level 3'!$A$24:$K$289,11,FALSE) -> 1108030 | D19: SY (Bldg) | E19: ='Level 3'!$Q$11 -> 28186.002 | F19: =C19/E19 -> 39.311357 | H19: =1093950/E19 -> 38.811819 | I19: =1122110/E19 -> 39.810896 | J19: =1313532/E19 -> 46.602282 | K19: =AVERAGE(H19:J19) -> 41.741665 | M19: 39.836808 | N19: 39.371016 | O19: 40.818674 | P19: 42.234692 | Q19: 46.688382
A20: Sprinkler System | B20: =C20/$C$30 -> 0.01447441 | C20: =VLOOKUP(A20,'Level 3'!$A$24:$K$289,11,FALSE) -> 1119982.8 | D20: SF (Bldg) | E20: =$F$4 -> 422635 | F20: =C20/E20 -> 2.65 | H20: =1010197/E20 -> 2.3902351 | K20: =AVERAGE(H20:J20) -> 2.3902351 | M20: 2.65 | N20: 3.2147842 | O20: 2.453065 | P20: 2.94 | Q20: 2.4480196
A21: Roofing | B21: =C21/$C$30 -> 0.012830435 | C21: =VLOOKUP(A21,'Level 3'!$A$24:$K$289,11,FALSE) -> 992777.33 | D21: Square | E21: ='Level 3'!$Q$10 -> 1734.0111 | F21: =C21/E21 -> 572.53228 | H21: =898016/E21 -> 517.88365 | I21: =1039240/E21 -> 599.32719 | J21: =1041076/E21 -> 600.38601 | K21: =AVERAGE(H21:J21) -> 572.53228 | M21: 596 | N21: 491.39689 | O21: 603.3984 | P21: 598.38652 | Q21: 535.7424
A22: Painting | B22: =C22/$C$30 -> 0.010487119 | C22: =VLOOKUP(A22,'Level 3'!$A$24:$K$289,11,FALSE) -> 811459.2 | D22: SF (Bldg) | E22: =$F$4 -> 422635 | F22: =C22/E22 -> 1.92 | H22: =686035/E22 -> 1.6232328 | I22: =835493/E22 -> 1.9768666 | J22: =1384220/E22 -> 3.2752138 | K22: =AVERAGE(H22:J22) -> 2.2917711 | M22: 1.58 | N22: 2.0533616 | O22: 1.8370925 | P22: 2.0978638 | Q22: 1.9319964
A23: Lightweight Concrete | B23: =C23/$C$30 -> 0.0087803469 | C23: =VLOOKUP(A23,'Level 3'!$A$24:$K$289,11,FALSE) -> 679394.69 | D23: SF | E23: ='Level 1.1 UPDATE B'!G33 -> 261711 | F23: =C23/E23 -> 2.595973 | H23: =627820/E23 -> 2.3989057 | I23: =679122/E23 -> 2.594931 | K23: =AVERAGE(H23:J23) -> 2.4969184 | M23: 2.8 | N23: 2.9324031 | O23: 2.9421304 | P23: 1.2965678 | Q23: 1.1
A24: Fire Alarm / Two Way Comm AOR | B24: =C24/$C$30 -> 0.012289593 | C24: =VLOOKUP(A24,'Level 3'!$A$24:$K$289,11,FALSE) -> 950928.75 | D24: SF | E24: =$F$4 -> 422635 | F24: =C24/E24 -> 2.25 | H24: =839780/E24 -> 1.9870101 | I24: =1015600/E24 -> 2.4030192 | K24: =AVERAGE(H24:J24) -> 2.1950146 | M24: 1.3350213 | N24: 1.977434 | O24: 1.6733483 | P24: 1.94 | Q24: 1.553436
A25: Flooring - Units | B25: =C25/$C$30 -> 0.008100091 | C25: =VLOOKUP(A25,'Level 3'!$A$24:$K$289,11,FALSE) -> 626758.7 | D25: SY | E25: ='Level 3'!$G$114 -> 36652.556 | F25: =C25/E25 -> 17.1 | M25: 22.5 | N25: 24.63 | O25: =2.33*9 -> 20.97 | P25: 18.754769 | Q25: 16.261536
A26: Counter Tops Units | B26: =C26/$C$30 -> 0.010872173 | C26: =VLOOKUP(A26,'Level 3'!$A$24:$K$289,11,FALSE) -> 841253.4 | D26: Unit | E26: =$F$3 -> 390 | F26: =C26/E26 -> 2157.06 | M26: =362478/194 -> 1868.4433 | N26: 1100 | O26: 1724 | P26: 1551.7283 | Q26: 1600.2513
A27: Windows and Sliding Glass Doors | B27: =C27/$C$30 -> 0.0070563834 | C27: =VLOOKUP(A27,'Level 3'!$A$24:$K$289,11,FALSE) -> 546000 | D27: Unit | E27: =$F$3 -> 390 | F27: =C27/E27 -> 1400 | H27: =417162/E27 -> 1069.6462 | I27: =565499/E27 -> 1449.9974 | J27: =708596/E27 -> 1816.9128 | K27: =AVERAGE(H27:J27) -> 1445.5188 | M27: 1335.866 | N27: 1300.6084 | O27: 1157.8947 | P27: 1408.8261 | Q27: 739.27144
A28: Pools and Spas | B28: =C28/$C$30 -> 0.0032802275 | C28: =VLOOKUP(A28,'Level 3'!$A$24:$K$289,11,FALSE) -> 253813.33 | D28: LS | E28: 1 | F28: =C28/E28 -> 253813.33 | H28: 238500 | I28: 255000 | J28: 267940 | K28: =AVERAGE(H28:J28) -> 253813.33 | M28: 249085 | N28: N/A | O28: 245000 | P28: 228710 | Q28: 208310
A29: Fire Pump | B29: =C29/$C$30 -> 0.002075042 | C29: =VLOOKUP(A29,'Level 3'!$A$24:$K$289,11,FALSE) -> 160560 | D29: LS | E29: 1 | F29: =C29/E29 -> 160560 | H29: N/A | I29: N/A | J29: N/A | K29: N/A | M29: 103700 | N29: N/A | O29: =133300 -> 133300 | P29: 160560 | Q29: =120800 -> 120800
A30: Total Hard Costs | C30: ='Level 3'!$L$14 -> 77376748 | D30: GSF | E30: =$F$4 -> 422635 | F30: =C30/E30 -> 183.08173

Sheet Comparison to Previous (2)
A1: WEST HENDERSON | C1: LEVEL 1.1 (LATEST) | L1: LEVEL 1
C2: Project Details | H2: Unit Breakdown | L2: Project Details | Q2: Unit Breakdown
C3: Project | D3: West Henderson | H3: Unit Type | I3: Number | J3: % | L3: Project | M3: West Henderson | Q3: Unit Type | R3: Number | S3: %
C4: Budget Level | D4: Level 1 | H4: Studios | I4: 0 | J4: =I4/$I$9 -> 0 | L4: Budget Level | M4: Level 1 | Q4: Studios | R4: 0 | S4: =R4/$I$9 -> 0
C5: Product | D5: Afforable | H5: 1 Br - 1 Ba | I5: 171 | J5: =I5/$I$9 -> 0.43846154 | L5: Product | M5: Afforable | Q5: 1 Br - 1 Ba | R5: 166 | S5: =R5/$I$9 -> 0.42564103
C6: Start Date | H6: 2 Br - 1 Ba | I6: 52 | J6: =I6/$I$9 -> 0.13333333 | L6: Start Date | Q6: 2 Br - 1 Ba | R6: 46 | S6: =R6/$I$9 -> 0.11794872
C7: Timeline | D7: 26 | H7: 2 Br - 2 Ba | I7: 118 | J7: =I7/$I$9 -> 0.3025641 | L7: Timeline | M7: 26 | Q7: 2 Br - 2 Ba | R7: 125 | S7: =R7/$I$9 -> 0.32051282
C8: Floors | D8: 2 & 3 Levels | H8: 3 Br - 2 Ba | I8: 49 | J8: =I8/$I$9 -> 0.12564103 | L8: Floors | M8: 2 & 3 Levels | Q8: 3 Br - 2 Ba | R8: 52 | S8: =R8/$I$9 -> 0.13333333
C9: Bldg. SF | D9: 431911 | H9: Totals | I9: =SUM(I4:I8) -> 390 | J9: =I9/$I$9 -> 1 | L9: Bldg. SF | M9: 428629 | Q9: Totals | R9: =SUM(R4:R8) -> 389 | S9: =R9/$I$9 -> 0.9974359
C10: Acres | D10: 15.826 | H10: Parking | L10: Acres | M10: 15.826 | Q10: Parking
C11: Site SF | D11: 689380.56 | H11: Garage Parking | J11: 0 | L11: Site SF | M11: 689380.56 | Q11: Garage Parking | S11: 0
C12: Buildings | D12: 5 | H12: Cover Parking | J12: 388 | L12: Buildings | M12: 5 | Q12: Cover Parking | S12: 360
H13: Open Parking | J13: 403 | Q13: Open Parking | S13: 321
E14: Net Change | H14: Accessible Parking | J14: 16 | Q14: Accessible Parking | S14: 14
C15: TOTAL COST | D15: =J329 -> #REF! | E15: =D15-M15 -> #REF! | F15: =E15/M15 -> #REF! | H15: Private Garages | J15: 0 | L15: TOTAL COST | M15: =S329 -> 82742977 | Q15: Private Garages | S15: 0
C16: PER UNIT | D16: =D15/I9 -> #REF! | E16: =D16-M16 -> #REF! | H16: Total Parking Provided | J16: 807 | L16: PER UNIT | M16: =M15/R9 -> 212706.88 | Q16: Total Parking Provided | S16: 681
C17: PER GSF | D17: =D15/D9 -> #REF! | E17: =D17-M17 -> #REF! | H17: Parking Ratio | J17: 2.0692308 | L17: PER GSF | M17: =M15/M9 -> 193.04101 | Q17: Parking Ratio | S17: 1.79 | U17: Conditions | W17: Conditions
U18: 75000 | W18: 0.05
A19: Description | C19: Source | D19: UOM | E19: QTY | F19: U.P. | G19: % | H19: Total U.P. | I19: Sub Total | J19: Total | L19: Source | M19: UOM | N19: QTY | O19: U.P. | P19: % | Q19: Total U.P. | R19: Sub Total | S19: Total | U19: PV$ | W19: PV% | Y19: Notes
A20: General Requirements | J20: ='Level 1'!L20 -> 4240149 | S20: 3987932 | U20: =J20-S20 -> 252217 | W20: =IF(S20=0,0,U20/S20) -> 0.06324506
A21: General Requirement | C21: ='Level 1'!E21 -> 0 | D21: ='Level 1'!F21 -> Mo | E21: ='Level 1'!G21 -> 26 | F21: ='Level 1'!H21 -> 163082.65 | G21: ='Level 1'!I21 -> 0 | H21: ='Level 1'!J21 -> 163082.65 | I21: ='Level 1'!K21 -> 4240149 | R21: 3987932 | U21: =I21-R21 -> 252217 | W21: =U21/R21 -> 0.06324506
A22: Existing Conditions | J22: ='Level 1'!L22 -> 12000 | S22: 10000 | U22: =J22-S22 -> 2000 | W22: =IF(S22=0,0,U22/S22) -> 0.2
